Workbook

Sheet Read me
A1: Gainsay — revised business plan | B1: Main Scenario
A2: Forecast | B2: October 2026–December 2027
A3: Input policy | B3: All original input values retained; new assumptions are explicitly labeled.
A4: Monthly cash basis | B4: Opening cash minus launch cost, then monthly result; data fee reserved monthly.
A5: Annual-upfront cash basis | B5: Original Ending cash row pays data fee upfront each October. Do not treat monthly reserves as actual installment terms.
A6: Founder draw | B6: Included in cash costs; not accounting salary or profit.
A7: Raised API access cost | B7: Unquoted. $0 is an unpriced placeholder, not free access. Incremental recurring cost starts at first quota crossing; do not double-count an upgrade bundled into the data agreement.
A8: Conservative / measured API | B8: 2 / 0.8 calls per citation. Mata ECF 21: about 13 calls / 16 citations = 0.8125; use 0.8 as the requested rounded case, not a universal benchmark.
A9: Quota calculation | B9: Monthly check calls / 30.4 plus daily docket polls. Default 125/day; hour/minute and burst limits can bind earlier. Commercial permission is separate from throughput.
A10: Cash correction | B10: First negative June 2027 (-$29.89); lowest July (-$53.20); first positive monthly result August 2027.
A11: Loss before first positive month | B11: $4,553.20; opening cash after launch is $4,500.
A12: Cash buffer | B12: Three months of $1,010.60 fixed budget = $3,031.80. Minimum monthly-reserved opening cash $8,085; rounded recommendation $8,500. Existing opening input stays $5,000.
... A23: Quota documentation | B23: https://wiki.free.law/c/courtlistener/help/api/rest/v4/api-usage

Sheet Gainsay drivers · Gainsay fixed
A1: Gainsay drivers · Gainsay fixed assumptions
A2: Financial model (3 pages) · Main Scenario
A4: Variable / dimension | B4: Value
A5: Claude cost per citation | B5: 0.026
A6: Docket monthly price | B6: 29
A7: Brief price | B7: 9
A8: New filings per docket | B8: 2
A9: Citations per paid filing | B9: 35
A10: Citations per free check | B10: 30
A11: Global free checks per month | B11: 20
A12: API calls per citation | B12: 2
A13: Daily default API quota | B13: 125
A14: Poll calls per docket per day | B14: 1
A15: Hosting per month | B15: 15
A16: Tools per month | B16: 30
... A35: Observed Mata citations | B35: 16

Sheet Gainsay drivers · Gainsay deman
A1: Gainsay drivers · Gainsay demand assumptions
A2: Financial model (3 pages) · Main Scenario
A4: Variable / dimension | B4: 2026-10 | C4: 2026-11 | D4: 2026-12 | E4: 2027-01 | F4: 2027-02 | G4: 2027-03 | H4: 2027-04 | I4: 2027-05 | J4: 2027-06 | K4: 2027-07 | L4: 2027-08 | M4: 2027-09 | N4: 2027-10 | O4: 2027-11 | P4: 2027-12
A5: New dockets per month | B5: 3 | C5: ='Gainsay drivers · Gainsay deman'!B5*(1+'Gainsay drivers · Gainsay deman'!C6) -> 3.15 | D5: ='Gainsay drivers · Gainsay deman'!C5*(1+'Gainsay drivers · Gainsay deman'!D6) -> 3.3075 | E5: ='Gainsay drivers · Gainsay deman'!D5*(1+'Gainsay drivers · Gainsay deman'!E6) -> 3.472875 | F5: ='Gainsay drivers · Gainsay deman'!E5*(1+'Gainsay drivers · Gainsay deman'!F6) -> 3.6465187 | G5: ='Gainsay drivers · Gainsay deman'!F5*(1+'Gainsay drivers · Gainsay deman'!G6) -> 3.8288447 | H5: ='Gainsay drivers · Gainsay deman'!G5*(1+'Gainsay drivers · Gainsay deman'!H6) -> 4.0202869 | I5: ='Gainsay drivers · Gainsay deman'!H5*(1+'Gainsay drivers · Gainsay deman'!I6) -> 4.2213013 | J5: ='Gainsay drivers · Gainsay deman'!I5*(1+'Gainsay drivers · Gainsay deman'!J6) -> 4.4323663 | ... P5: ='Gainsay drivers · Gainsay deman'!O5*(1+'Gainsay drivers · Gainsay deman'!P6) -> 5.9397948
A6: Monthly acquisition growth | B6: 0.05 | C6: =IF('Gainsay drivers · Gainsay deman'!B6="","",'Gainsay drivers · Gainsay deman'!B6) -> 0.05 | D6: =IF('Gainsay drivers · Gainsay deman'!C6="","",'Gainsay drivers · Gainsay deman'!C6) -> 0.05 | E6: =IF('Gainsay drivers · Gainsay deman'!D6="","",'Gainsay drivers · Gainsay deman'!D6) -> 0.05 | F6: =IF('Gainsay drivers · Gainsay deman'!E6="","",'Gainsay drivers · Gainsay deman'!E6) -> 0.05 | G6: =IF('Gainsay drivers · Gainsay deman'!F6="","",'Gainsay drivers · Gainsay deman'!F6) -> 0.05 | H6: =IF('Gainsay drivers · Gainsay deman'!G6="","",'Gainsay drivers · Gainsay deman'!G6) -> 0.05 | I6: =IF('Gainsay drivers · Gainsay deman'!H6="","",'Gainsay drivers · Gainsay deman'!H6) -> 0.05 | J6: =IF('Gainsay drivers · Gainsay deman'!I6="","",'Gainsay drivers · Gainsay deman'!I6) -> 0.05 | ... P6: =IF('Gainsay drivers · Gainsay deman'!O6="","",'Gainsay drivers · Gainsay deman'!O6) -> 0.05
A7: Monthly docket churn | B7: 0.03 | C7: =IF('Gainsay drivers · Gainsay deman'!B7="","",'Gainsay drivers · Gainsay deman'!B7) -> 0.03 | D7: =IF('Gainsay drivers · Gainsay deman'!C7="","",'Gainsay drivers · Gainsay deman'!C7) -> 0.03 | E7: =IF('Gainsay drivers · Gainsay deman'!D7="","",'Gainsay drivers · Gainsay deman'!D7) -> 0.03 | F7: =IF('Gainsay drivers · Gainsay deman'!E7="","",'Gainsay drivers · Gainsay deman'!E7) -> 0.03 | G7: =IF('Gainsay drivers · Gainsay deman'!F7="","",'Gainsay drivers · Gainsay deman'!F7) -> 0.03 | H7: =IF('Gainsay drivers · Gainsay deman'!G7="","",'Gainsay drivers · Gainsay deman'!G7) -> 0.03 | I7: =IF('Gainsay drivers · Gainsay deman'!H7="","",'Gainsay drivers · Gainsay deman'!H7) -> 0.03 | J7: =IF('Gainsay drivers · Gainsay deman'!I7="","",'Gainsay drivers · Gainsay deman'!I7) -> 0.03 | ... P7: =IF('Gainsay drivers · Gainsay deman'!O7="","",'Gainsay drivers · Gainsay deman'!O7) -> 0.03
A8: Brief checks sold | B8: 10 | C8: ='Gainsay drivers · Gainsay deman'!B8*(1+'Gainsay drivers · Gainsay deman'!C9) -> 10.5 | D8: ='Gainsay drivers · Gainsay deman'!C8*(1+'Gainsay drivers · Gainsay deman'!D9) -> 11.025 | E8: ='Gainsay drivers · Gainsay deman'!D8*(1+'Gainsay drivers · Gainsay deman'!E9) -> 11.57625 | F8: ='Gainsay drivers · Gainsay deman'!E8*(1+'Gainsay drivers · Gainsay deman'!F9) -> 12.155062 | G8: ='Gainsay drivers · Gainsay deman'!F8*(1+'Gainsay drivers · Gainsay deman'!G9) -> 12.762816 | H8: ='Gainsay drivers · Gainsay deman'!G8*(1+'Gainsay drivers · Gainsay deman'!H9) -> 13.400956 | I8: ='Gainsay drivers · Gainsay deman'!H8*(1+'Gainsay drivers · Gainsay deman'!I9) -> 14.071004 | J8: ='Gainsay drivers · Gainsay deman'!I8*(1+'Gainsay drivers · Gainsay deman'!J9) -> 14.774554 | ... P8: ='Gainsay drivers · Gainsay deman'!O8*(1+'Gainsay drivers · Gainsay deman'!P9) -> 19.799316
A9: Monthly brief demand growth | B9: 0.05 | C9: =IF('Gainsay drivers · Gainsay deman'!B9="","",'Gainsay drivers · Gainsay deman'!B9) -> 0.05 | D9: =IF('Gainsay drivers · Gainsay deman'!C9="","",'Gainsay drivers · Gainsay deman'!C9) -> 0.05 | E9: =IF('Gainsay drivers · Gainsay deman'!D9="","",'Gainsay drivers · Gainsay deman'!D9) -> 0.05 | F9: =IF('Gainsay drivers · Gainsay deman'!E9="","",'Gainsay drivers · Gainsay deman'!E9) -> 0.05 | G9: =IF('Gainsay drivers · Gainsay deman'!F9="","",'Gainsay drivers · Gainsay deman'!F9) -> 0.05 | H9: =IF('Gainsay drivers · Gainsay deman'!G9="","",'Gainsay drivers · Gainsay deman'!G9) -> 0.05 | I9: =IF('Gainsay drivers · Gainsay deman'!H9="","",'Gainsay drivers · Gainsay deman'!H9) -> 0.05 | J9: =IF('Gainsay drivers · Gainsay deman'!I9="","",'Gainsay drivers · Gainsay deman'!I9) -> 0.05 | ... P9: =IF('Gainsay drivers · Gainsay deman'!O9="","",'Gainsay drivers · Gainsay deman'!O9) -> 0.05

Sheet Gainsay drivers · Gainsay prici
A1: Gainsay drivers · Gainsay pricing economics
A2: Financial model (3 pages) · Main Scenario
A4: Variable / dimension | B4: Value
A5: AI cost per average filing | B5: ='Gainsay drivers · Gainsay fixed'!B5*'Gainsay drivers · Gainsay fixed'!B9 -> 0.91
A6: AI cost at 15 citations | B6: ='Gainsay drivers · Gainsay fixed'!B5*15 -> 0.39
A7: AI cost at 50 citations | B7: ='Gainsay drivers · Gainsay fixed'!B5*50 -> 1.3
A8: Docket contribution per month | B8: ='Gainsay drivers · Gainsay fixed'!B6*(1-'Gainsay drivers · Gainsay fixed'!B23)-'Gainsay drivers · Gainsay fixed'!B24-'Gainsay drivers · Gainsay fixed'!B8*'Gainsay drivers · Gainsay prici'!B5 -> 26.039
A9: Brief contribution | B9: ='Gainsay drivers · Gainsay fixed'!B7*(1-'Gainsay drivers · Gainsay fixed'!B23)-'Gainsay drivers · Gainsay fixed'!B24-'Gainsay drivers · Gainsay prici'!B5 -> 7.529
A10: Fixed monthly cash budget | B10: ='Gainsay drivers · Gainsay fixed'!B15+'Gainsay drivers · Gainsay fixed'!B16+'Gainsay drivers · Gainsay fixed'!B17+'Gainsay drivers · Gainsay fixed'!B18+'Gainsay drivers · Gainsay fixed'!B20/12+'Gainsay drivers · Gainsay fixed'!B19+'Gainsay drivers · Gainsay fixed'!B11*'Gainsay drivers · Gainsay fixed'!B10*'Gainsay drivers · Gainsay fixed'!B5 -> 1010.6
A11: Dockets needed for fixed cash budget | B11: =CEILING('Gainsay drivers · Gainsay prici'!B10/'Gainsay drivers · Gainsay prici'!B8,1) -> 39
A12: Observed Mata calls per citation | B12: ='Gainsay drivers · Gainsay fixed'!B34/'Gainsay drivers · Gainsay fixed'!B35 -> 0.8125
A13: Cash after launch | B13: ='Gainsay drivers · Gainsay fixed'!B21-'Gainsay drivers · Gainsay fixed'!B22 -> 4500
A14: Lowest monthly-reserved cash | B14: =MIN('Gainsay economics · Gainsay ope'!B12,'Gainsay economics · Gainsay ope'!C12,'Gainsay economics · Gainsay ope'!D12,'Gainsay economics · Gainsay ope'!E12,'Gainsay economics · Gainsay ope'!F12,'Gainsay economics · Gainsay ope'!G12,'Gainsay economics · Gainsay ope'!H12,'Gainsay economics · Gainsay ope'!I12,'Gainsay economics · Gainsay ope'!J12,'Gainsay economics · Gainsay ope'!K12,'Gainsay economics · Gainsay ope'!L12,'Gainsay economics · Gainsay ope'!M12,'Gainsay economics · Gainsay ope'!N12,'Gainsay economics · Gainsay ope'!O12,'Gainsay economics · Gainsay ope'!P12) -> -53.199018
A15: Losses before first positive month | B15: =-'Model inputs'!B295 -> 4553.199
A16: First positive month | B16: =IF('Model inputs'!B359="","",EDATE(DATE(2026,10,1),IF((IF(AND('Model inputs'!B335="",'Model inputs'!B336="",'Model inputs'!B337="",'Model inputs'!B338="",'Model inputs'!B339="",'Model inputs'!B340="",'Model inputs'!B341="",'Model inputs'!B342="",'Model inputs'!B343="",'Model inputs'!B344="",'Model inputs'!B345="",'Model inputs'!B346="",'Model inputs'!B347="",'Model inputs'!B348="",'Model inputs'!B349="",'Model inputs'!B350="",'Model inputs'!B351="",'Model inputs'!B352="",'Model inputs'!B353="",'Model inputs'!B354="",'Model inputs'!B355="",'Model inputs'!B356="",'Model inputs'!B357="",'Model inputs'!B358=""),"",MIN('Model inputs'!B335,'Model inputs'!B336,'Model inputs'!B337,'Model inputs'!B338,'Model inputs'!B339,'Model inputs'!B340,'Model inputs'!B341,'Model inputs'!B342,'Model inputs'!B343,'Model inputs'!B344,'Model inputs'!B345,'Model inputs'!B346,'Model inputs'!B347,'Model inputs'!B348,'Model inputs'!B349,'Model inputs'!B350,'Model inputs'!B351,'Model inputs'!B352,'Model inputs'!B353,'Model inputs'!B354,'Model inputs'!B355,'Model inputs'!B356,'Model inputs'!B357,'Model inputs'!B358)))="",0,(IF(AND('Model inputs'!B335="",'Model inputs'!B336="",'Model inputs'!B337="",'Model inputs'!B338="",'Model inputs'!B339="",'Model inputs'!B340="",'Model inputs'!B341="",'Model inputs'!B342="",'Model inputs'!B343="",'Model inputs'!B344="",'Model inputs'!B345="",'Model inputs'!B346="",'Model inputs'!B347="",'Model inputs'!B348="",'Model inputs'!B349="",'Model inputs'!B350="",'Model inputs'!B351="",'Model inputs'!B352="",'Model inputs'!B353="",'Model inputs'!B354="",'Model inputs'!B355="",'Model inputs'!B356="",'Model inputs'!B357="",'Model inputs'!B358=""),"",MIN('Model inputs'!B335,'Model inputs'!B336,'Model inputs'!B337,'Model inputs'!B338,'Model inputs'!B339,'Model inputs'!B340,'Model inputs'!B341,'Model inputs'!B342,'Model inputs'!B343,'Model inputs'!B344,'Model inputs'!B345,'Model inputs'!B346,'Model inputs'!B347,'Model inputs'!B348,'Model inputs'!B349,'Model inputs'!B350,'Model inputs'!B351,'Model inputs'!B352,'Model inputs'!B353,'Model inputs'!B354,'Model inputs'!B355,'Model inputs'!B356,'Model inputs'!B357,'Model inputs'!B358))))-1)) -> 46600
A17: First negative cash month monthly reserved | B17: =IF('Model inputs'!B423="","",EDATE(DATE(2026,10,1),IF((IF(AND('Model inputs'!B399="",'Model inputs'!B400="",'Model inputs'!B401="",'Model inputs'!B402="",'Model inputs'!B403="",'Model inputs'!B404="",'Model inputs'!B405="",'Model inputs'!B406="",'Model inputs'!B407="",'Model inputs'!B408="",'Model inputs'!B409="",'Model inputs'!B410="",'Model inputs'!B411="",'Model inputs'!B412="",'Model inputs'!B413="",'Model inputs'!B414="",'Model inputs'!B415="",'Model inputs'!B416="",'Model inputs'!B417="",'Model inputs'!B418="",'Model inputs'!B419="",'Model inputs'!B420="",'Model inputs'!B421="",'Model inputs'!B422=""),"",MIN('Model inputs'!B399,'Model inputs'!B400,'Model inputs'!B401,'Model inputs'!B402,'Model inputs'!B403,'Model inputs'!B404,'Model inputs'!B405,'Model inputs'!B406,'Model inputs'!B407,'Model inputs'!B408,'Model inputs'!B409,'Model inputs'!B410,'Model inputs'!B411,'Model inputs'!B412,'Model inputs'!B413,'Model inputs'!B414,'Model inputs'!B415,'Model inputs'!B416,'Model inputs'!B417,'Model inputs'!B418,'Model inputs'!B419,'Model inputs'!B420,'Model inputs'!B421,'Model inputs'!B422)))="",0,(IF(AND('Model inputs'!B399="",'Model inputs'!B400="",'Model inputs'!B401="",'Model inputs'!B402="",'Model inputs'!B403="",'Model inputs'!B404="",'Model inputs'!B405="",'Model inputs'!B406="",'Model inputs'!B407="",'Model inputs'!B408="",'Model inputs'!B409="",'Model inputs'!B410="",'Model inputs'!B411="",'Model inputs'!B412="",'Model inputs'!B413="",'Model inputs'!B414="",'Model inputs'!B415="",'Model inputs'!B416="",'Model inputs'!B417="",'Model inputs'!B418="",'Model inputs'!B419="",'Model inputs'!B420="",'Model inputs'!B421="",'Model inputs'!B422=""),"",MIN('Model inputs'!B399,'Model inputs'!B400,'Model inputs'!B401,'Model inputs'!B402,'Model inputs'!B403,'Model inputs'!B404,'Model inputs'!B405,'Model inputs'!B406,'Model inputs'!B407,'Model inputs'!B408,'Model inputs'!B409,'Model inputs'!B410,'Model inputs'!B411,'Model inputs'!B412,'Model inputs'!B413,'Model inputs'!B414,'Model inputs'!B415,'Model inputs'!B416,'Model inputs'!B417,'Model inputs'!B418,'Model inputs'!B419,'Model inputs'!B420,'Model inputs'!B421,'Model inputs'!B422))))-1)) -> 46539
A18: Lowest cash month monthly reserved | B18: =IF('Model inputs'!B496="","",EDATE(DATE(2026,10,1),IF((IF(AND('Model inputs'!B472="",'Model inputs'!B473="",'Model inputs'!B474="",'Model inputs'!B475="",'Model inputs'!B476="",'Model inputs'!B477="",'Model inputs'!B478="",'Model inputs'!B479="",'Model inputs'!B480="",'Model inputs'!B481="",'Model inputs'!B482="",'Model inputs'!B483="",'Model inputs'!B484="",'Model inputs'!B485="",'Model inputs'!B486="",'Model inputs'!B487="",'Model inputs'!B488="",'Model inputs'!B489="",'Model inputs'!B490="",'Model inputs'!B491="",'Model inputs'!B492="",'Model inputs'!B493="",'Model inputs'!B494="",'Model inputs'!B495=""),"",MIN('Model inputs'!B472,'Model inputs'!B473,'Model inputs'!B474,'Model inputs'!B475,'Model inputs'!B476,'Model inputs'!B477,'Model inputs'!B478,'Model inputs'!B479,'Model inputs'!B480,'Model inputs'!B481,'Model inputs'!B482,'Model inputs'!B483,'Model inputs'!B484,'Model inputs'!B485,'Model inputs'!B486,'Model inputs'!B487,'Model inputs'!B488,'Model inputs'!B489,'Model inputs'!B490,'Model inputs'!B491,'Model inputs'!B492,'Model inputs'!B493,'Model inputs'!B494,'Model inputs'!B495)))="",0,(IF(AND('Model inputs'!B472="",'Model inputs'!B473="",'Model inputs'!B474="",'Model inputs'!B475="",'Model inputs'!B476="",'Model inputs'!B477="",'Model inputs'!B478="",'Model inputs'!B479="",'Model inputs'!B480="",'Model inputs'!B481="",'Model inputs'!B482="",'Model inputs'!B483="",'Model inputs'!B484="",'Model inputs'!B485="",'Model inputs'!B486="",'Model inputs'!B487="",'Model inputs'!B488="",'Model inputs'!B489="",'Model inputs'!B490="",'Model inputs'!B491="",'Model inputs'!B492="",'Model inputs'!B493="",'Model inputs'!B494="",'Model inputs'!B495=""),"",MIN('Model inputs'!B472,'Model inputs'!B473,'Model inputs'!B474,'Model inputs'!B475,'Model inputs'!B476,'Model inputs'!B477,'Model inputs'!B478,'Model inputs'!B479,'Model inputs'!B480,'Model inputs'!B481,'Model inputs'!B482,'Model inputs'!B483,'Model inputs'!B484,'Model inputs'!B485,'Model inputs'!B486,'Model inputs'!B487,'Model inputs'!B488,'Model inputs'!B489,'Model inputs'!B490,'Model inputs'!B491,'Model inputs'!B492,'Model inputs'!B493,'Model inputs'!B494,'Model inputs'!B495))))-1)) -> 46569
A19: First API quota month conservative | B19: =IF('Model inputs'!B560="","",EDATE(DATE(2026,10,1),IF((IF(AND('Model inputs'!B536="",'Model inputs'!B537="",'Model inputs'!B538="",'Model inputs'!B539="",'Model inputs'!B540="",'Model inputs'!B541="",'Model inputs'!B542="",'Model inputs'!B543="",'Model inputs'!B544="",'Model inputs'!B545="",'Model inputs'!B546="",'Model inputs'!B547="",'Model inputs'!B548="",'Model inputs'!B549="",'Model inputs'!B550="",'Model inputs'!B551="",'Model inputs'!B552="",'Model inputs'!B553="",'Model inputs'!B554="",'Model inputs'!B555="",'Model inputs'!B556="",'Model inputs'!B557="",'Model inputs'!B558="",'Model inputs'!B559=""),"",MIN('Model inputs'!B536,'Model inputs'!B537,'Model inputs'!B538,'Model inputs'!B539,'Model inputs'!B540,'Model inputs'!B541,'Model inputs'!B542,'Model inputs'!B543,'Model inputs'!B544,'Model inputs'!B545,'Model inputs'!B546,'Model inputs'!B547,'Model inputs'!B548,'Model inputs'!B549,'Model inputs'!B550,'Model inputs'!B551,'Model inputs'!B552,'Model inputs'!B553,'Model inputs'!B554,'Model inputs'!B555,'Model inputs'!B556,'Model inputs'!B557,'Model inputs'!B558,'Model inputs'!B559)))="",0,(IF(AND('Model inputs'!B536="",'Model inputs'!B537="",'Model inputs'!B538="",'Model inputs'!B539="",'Model inputs'!B540="",'Model inputs'!B541="",'Model inputs'!B542="",'Model inputs'!B543="",'Model inputs'!B544="",'Model inputs'!B545="",'Model inputs'!B546="",'Model inputs'!B547="",'Model inputs'!B548="",'Model inputs'!B549="",'Model inputs'!B550="",'Model inputs'!B551="",'Model inputs'!B552="",'Model inputs'!B553="",'Model inputs'!B554="",'Model inputs'!B555="",'Model inputs'!B556="",'Model inputs'!B557="",'Model inputs'!B558="",'Model inputs'!B559=""),"",MIN('Model inputs'!B536,'Model inputs'!B537,'Model inputs'!B538,'Model inputs'!B539,'Model inputs'!B540,'Model inputs'!B541,'Model inputs'!B542,'Model inputs'!B543,'Model inputs'!B544,'Model inputs'!B545,'Model inputs'!B546,'Model inputs'!B547,'Model inputs'!B548,'Model inputs'!B549,'Model inputs'!B550,'Model inputs'!B551,'Model inputs'!B552,'Model inputs'!B553,'Model inputs'!B554,'Model inputs'!B555,'Model inputs'!B556,'Model inputs'!B557,'Model inputs'!B558,'Model inputs'!B559))))-1)) -> 46388
A20: First API quota month measured | B20: =IF('Model inputs'!B624="","",EDATE(DATE(2026,10,1),IF((IF(AND('Model inputs'!B600="",'Model inputs'!B601="",'Model inputs'!B602="",'Model inputs'!B603="",'Model inputs'!B604="",'Model inputs'!B605="",'Model inputs'!B606="",'Model inputs'!B607="",'Model inputs'!B608="",'Model inputs'!B609="",'Model inputs'!B610="",'Model inputs'!B611="",'Model inputs'!B612="",'Model inputs'!B613="",'Model inputs'!B614="",'Model inputs'!B615="",'Model inputs'!B616="",'Model inputs'!B617="",'Model inputs'!B618="",'Model inputs'!B619="",'Model inputs'!B620="",'Model inputs'!B621="",'Model inputs'!B622="",'Model inputs'!B623=""),"",MIN('Model inputs'!B600,'Model inputs'!B601,'Model inputs'!B602,'Model inputs'!B603,'Model inputs'!B604,'Model inputs'!B605,'Model inputs'!B606,'Model inputs'!B607,'Model inputs'!B608,'Model inputs'!B609,'Model inputs'!B610,'Model inputs'!B611,'Model inputs'!B612,'Model inputs'!B613,'Model inputs'!B614,'Model inputs'!B615,'Model inputs'!B616,'Model inputs'!B617,'Model inputs'!B618,'Model inputs'!B619,'Model inputs'!B620,'Model inputs'!B621,'Model inputs'!B622,'Model inputs'!B623)))="",0,(IF(AND('Model inputs'!B600="",'Model inputs'!B601="",'Model inputs'!B602="",'Model inputs'!B603="",'Model inputs'!B604="",'Model inputs'!B605="",'Model inputs'!B606="",'Model inputs'!B607="",'Model inputs'!B608="",'Model inputs'!B609="",'Model inputs'!B610="",'Model inputs'!B611="",'Model inputs'!B612="",'Model inputs'!B613="",'Model inputs'!B614="",'Model inputs'!B615="",'Model inputs'!B616="",'Model inputs'!B617="",'Model inputs'!B618="",'Model inputs'!B619="",'Model inputs'!B620="",'Model inputs'!B621="",'Model inputs'!B622="",'Model inputs'!B623=""),"",MIN('Model inputs'!B600,'Model inputs'!B601,'Model inputs'!B602,'Model inputs'!B603,'Model inputs'!B604,'Model inputs'!B605,'Model inputs'!B606,'Model inputs'!B607,'Model inputs'!B608,'Model inputs'!B609,'Model inputs'!B610,'Model inputs'!B611,'Model inputs'!B612,'Model inputs'!B613,'Model inputs'!B614,'Model inputs'!B615,'Model inputs'!B616,'Model inputs'!B617,'Model inputs'!B618,'Model inputs'!B619,'Model inputs'!B620,'Model inputs'!B621,'Model inputs'!B622,'Model inputs'!B623))))-1)) -> 46569
A21: Three month fixed budget buffer | B21: ='Gainsay drivers · Gainsay fixed'!B31*('Gainsay drivers · Gainsay prici'!B10+'Gainsay drivers · Gainsay fixed'!B30) -> 3031.8
A22: Minimum opening cash monthly reserved | B22: ='Gainsay drivers · Gainsay fixed'!B21+'Gainsay drivers · Gainsay prici'!B21-'Gainsay drivers · Gainsay prici'!B14 -> 8084.999
A23: Recommended opening cash monthly reserved | B23: =CEILING('Gainsay drivers · Gainsay prici'!B22,'Gainsay drivers · Gainsay fixed'!B33) -> 8500
A24: Minimum opening cash annual upfront | B24: ='Gainsay drivers · Gainsay fixed'!B21+'Gainsay drivers · Gainsay prici'!B21-MIN('Gainsay economics · Gainsay ope'!B33,'Gainsay economics · Gainsay ope'!C33,'Gainsay economics · Gainsay ope'!D33,'Gainsay economics · Gainsay ope'!E33,'Gainsay economics · Gainsay ope'!F33,'Gainsay economics · Gainsay ope'!G33,'Gainsay economics · Gainsay ope'!H33,'Gainsay economics · Gainsay ope'!I33,'Gainsay economics · Gainsay ope'!J33,'Gainsay economics · Gainsay ope'!K33,'Gainsay economics · Gainsay ope'!L33,'Gainsay economics · Gainsay ope'!M33,'Gainsay economics · Gainsay ope'!N33,'Gainsay economics · Gainsay ope'!O33,'Gainsay economics · Gainsay ope'!P33) -> 10248.406
A25: Recommended opening cash annual upfront | B25: =CEILING('Gainsay drivers · Gainsay prici'!B24,'Gainsay drivers · Gainsay fixed'!B33) -> 10500
A26: API calls at 39 dockets with opening brief volume | B26: =((39*'Gainsay drivers · Gainsay fixed'!B8+'Gainsay drivers · Gainsay deman'!B8)*'Gainsay drivers · Gainsay fixed'!B9+'Gainsay drivers · Gainsay fixed'!B11*'Gainsay drivers · Gainsay fixed'!B10)*'Gainsay drivers · Gainsay fixed'!B12/'Gainsay drivers · Gainsay fixed'!B32+39*'Gainsay drivers · Gainsay fixed'!B14 -> 281.10526
A27: API calls at 39 dockets excluding brief checks | B27: =(39*'Gainsay drivers · Gainsay fixed'!B8*'Gainsay drivers · Gainsay fixed'!B9+'Gainsay drivers · Gainsay fixed'!B11*'Gainsay drivers · Gainsay fixed'!B10)*'Gainsay drivers · Gainsay fixed'!B12/'Gainsay drivers · Gainsay fixed'!B32+39*'Gainsay drivers · Gainsay fixed'!B14 -> 258.07895

Sheet Gainsay drivers · Gainsay data-
A1: Gainsay drivers · Gainsay data-fee tests
A2: Financial model (3 pages) · Main Scenario
A4: Variable / dimension | B4: Test annual data fee | C4: Test fixed monthly cash budget | D4: Test dockets needed for fixed cash budget | E4: Test dockets including contractor trigger | F4: Test first positive month | G4: Test lowest cash | H4: Test lowest cash month | I4: Test recommended opening cash | J4: Test break-even status
A5: High fee stress | B5: 10000 | C5: ='Gainsay drivers · Gainsay prici'!B10+('Gainsay drivers · Gainsay data-'!B5-'Gainsay drivers · Gainsay fixed'!B20)/12 -> 1593.9333 | D5: =CEILING('Gainsay drivers · Gainsay data-'!C5/'Gainsay drivers · Gainsay prici'!B8,1) -> 62 | E5: =IF(IF(IF(ISERROR('Gainsay drivers · Gainsay data-'!D5>='Gainsay drivers · Gainsay fixed'!B27),'Gainsay drivers · Gainsay data-'!D5>='Gainsay drivers · Gainsay fixed'!B27,IF(OR('Gainsay drivers · Gainsay data-'!D5="",'Gainsay drivers · Gainsay fixed'!B27=""),"",'Gainsay drivers · Gainsay data-'!D5>='Gainsay drivers · Gainsay fixed'!B27))="",FALSE(),IF(ISERROR('Gainsay drivers · Gainsay data-'!D5>='Gainsay drivers · Gainsay fixed'!B27),'Gainsay drivers · Gainsay data-'!D5>='Gainsay drivers · Gainsay fixed'!B27,IF(OR('Gainsay drivers · Gainsay data-'!D5="",'Gainsay drivers · Gainsay fixed'!B27=""),"",'Gainsay drivers · Gainsay data-'!D5>='Gainsay drivers · Gainsay fixed'!B27))),CEILING(('Gainsay drivers · Gainsay data-'!C5+'Gainsay drivers · Gainsay fixed'!B28+'Gainsay drivers · Gainsay fixed'!B30)/'Gainsay drivers · Gainsay prici'!B8,1),CEILING(('Gainsay drivers · Gainsay data-'!C5+'Gainsay drivers · Gainsay fixed'!B30)/'Gainsay drivers · Gainsay prici'!B8,1)) -> 77 | F5: =IF('Model inputs'!B688="","",EDATE(DATE(2026,10,1),IF((IF(AND('Model inputs'!B664="",'Model inputs'!B665="",'Model inputs'!B666="",'Model inputs'!B667="",'Model inputs'!B668="",'Model inputs'!B669="",'Model inputs'!B670="",'Model inputs'!B671="",'Model inputs'!B672="",'Model inputs'!B673="",'Model inputs'!B674="",'Model inputs'!B675="",'Model inputs'!B676="",'Model inputs'!B677="",'Model inputs'!B678="",'Model inputs'!B679="",'Model inputs'!B680="",'Model inputs'!B681="",'Model inputs'!B682="",'Model inputs'!B683="",'Model inputs'!B684="",'Model inputs'!B685="",'Model inputs'!B686="",'Model inputs'!B687=""),"",MIN('Model inputs'!B664,'Model inputs'!B665,'Model inputs'!B666,'Model inputs'!B667,'Model inputs'!B668,'Model inputs'!B669,'Model inputs'!B670,'Model inputs'!B671,'Model inputs'!B672,'Model inputs'!B673,'Model inputs'!B674,'Model inputs'!B675,'Model inputs'!B676,'Model inputs'!B677,'Model inputs'!B678,'Model inputs'!B679,'Model inputs'!B680,'Model inputs'!B681,'Model inputs'!B682,'Model inputs'!B683,'Model inputs'!B684,'Model inputs'!B685,'Model inputs'!B686,'Model inputs'!B687)))="",0,(IF(AND('Model inputs'!B664="",'Model inputs'!B665="",'Model inputs'!B666="",'Model inputs'!B667="",'Model inputs'!B668="",'Model inputs'!B669="",'Model inputs'!B670="",'Model inputs'!B671="",'Model inputs'!B672="",'Model inputs'!B673="",'Model inputs'!B674="",'Model inputs'!B675="",'Model inputs'!B676="",'Model inputs'!B677="",'Model inputs'!B678="",'Model inputs'!B679="",'Model inputs'!B680="",'Model inputs'!B681="",'Model inputs'!B682="",'Model inputs'!B683="",'Model inputs'!B684="",'Model inputs'!B685="",'Model inputs'!B686="",'Model inputs'!B687=""),"",MIN('Model inputs'!B664,'Model inputs'!B665,'Model inputs'!B666,'Model inputs'!B667,'Model inputs'!B668,'Model inputs'!B669,'Model inputs'!B670,'Model inputs'!B671,'Model inputs'!B672,'Model inputs'!B673,'Model inputs'!B674,'Model inputs'!B675,'Model inputs'!B676,'Model inputs'!B677,'Model inputs'!B678,'Model inputs'!B679,'Model inputs'!B680,'Model inputs'!B681,'Model inputs'!B682,'Model inputs'!B683,'Model inputs'!B684,'Model inputs'!B685,'Model inputs'!B686,'Model inputs'!B687))))-1)) | G5: =MIN('Gainsay economics · Gainsay dat'!B15,'Gainsay economics · Gainsay dat'!C15,'Gainsay economics · Gainsay dat'!D15,'Gainsay economics · Gainsay dat'!E15,'Gainsay economics · Gainsay dat'!F15,'Gainsay economics · Gainsay dat'!G15,'Gainsay economics · Gainsay dat'!H15,'Gainsay economics · Gainsay dat'!I15,'Gainsay economics · Gainsay dat'!J15,'Gainsay economics · Gainsay dat'!K15,'Gainsay economics · Gainsay dat'!L15,'Gainsay economics · Gainsay dat'!M15,'Gainsay economics · Gainsay dat'!N15,'Gainsay economics · Gainsay dat'!O15,'Gainsay economics · Gainsay dat'!P15) -> -7639.2578 | H5: =IF('Model inputs'!B761="","",EDATE(DATE(2026,10,1),IF((IF(AND('Model inputs'!B737="",'Model inputs'!B738="",'Model inputs'!B739="",'Model inputs'!B740="",'Model inputs'!B741="",'Model inputs'!B742="",'Model inputs'!B743="",'Model inputs'!B744="",'Model inputs'!B745="",'Model inputs'!B746="",'Model inputs'!B747="",'Model inputs'!B748="",'Model inputs'!B749="",'Model inputs'!B750="",'Model inputs'!B751="",'Model inputs'!B752="",'Model inputs'!B753="",'Model inputs'!B754="",'Model inputs'!B755="",'Model inputs'!B756="",'Model inputs'!B757="",'Model inputs'!B758="",'Model inputs'!B759="",'Model inputs'!B760=""),"",MIN('Model inputs'!B737,'Model inputs'!B738,'Model inputs'!B739,'Model inputs'!B740,'Model inputs'!B741,'Model inputs'!B742,'Model inputs'!B743,'Model inputs'!B744,'Model inputs'!B745,'Model inputs'!B746,'Model inputs'!B747,'Model inputs'!B748,'Model inputs'!B749,'Model inputs'!B750,'Model inputs'!B751,'Model inputs'!B752,'Model inputs'!B753,'Model inputs'!B754,'Model inputs'!B755,'Model inputs'!B756,'Model inputs'!B757,'Model inputs'!B758,'Model inputs'!B759,'Model inputs'!B760)))="",0,(IF(AND('Model inputs'!B737="",'Model inputs'!B738="",'Model inputs'!B739="",'Model inputs'!B740="",'Model inputs'!B741="",'Model inputs'!B742="",'Model inputs'!B743="",'Model inputs'!B744="",'Model inputs'!B745="",'Model inputs'!B746="",'Model inputs'!B747="",'Model inputs'!B748="",'Model inputs'!B749="",'Model inputs'!B750="",'Model inputs'!B751="",'Model inputs'!B752="",'Model inputs'!B753="",'Model inputs'!B754="",'Model inputs'!B755="",'Model inputs'!B756="",'Model inputs'!B757="",'Model inputs'!B758="",'Model inputs'!B759="",'Model inputs'!B760=""),"",MIN('Model inputs'!B737,'Model inputs'!B738,'Model inputs'!B739,'Model inputs'!B740,'Model inputs'!B741,'Model inputs'!B742,'Model inputs'!B743,'Model inputs'!B744,'Model inputs'!B745,'Model inputs'!B746,'Model inputs'!B747,'Model inputs'!B748,'Model inputs'!B749,'Model inputs'!B750,'Model inputs'!B751,'Model inputs'!B752,'Model inputs'!B753,'Model inputs'!B754,'Model inputs'!B755,'Model inputs'!B756,'Model inputs'!B757,'Model inputs'!B758,'Model inputs'!B759,'Model inputs'!B760))))-1)) -> 46722 | I5: =CEILING('Gainsay drivers · Gainsay fixed'!B21+'Gainsay drivers · Gainsay fixed'!B31*('Gainsay drivers · Gainsay data-'!C5+'Gainsay drivers · Gainsay fixed'!B30)-'Gainsay drivers · Gainsay data-'!G5,'Gainsay drivers · Gainsay fixed'!B33) -> 17500 | J5: =IF('Gainsay drivers · Gainsay data-'!F5="","Not reached through December 2027","Reached") -> Not reached through December 2027
A6: Illustrative fee | B6: 3000 | C6: ='Gainsay drivers · Gainsay prici'!B10+('Gainsay drivers · Gainsay data-'!B6-'Gainsay drivers · Gainsay fixed'!B20)/12 -> 1010.6 | D6: =CEILING('Gainsay drivers · Gainsay data-'!C6/'Gainsay drivers · Gainsay prici'!B8,1) -> 39 | E6: =IF(IF(IF(ISERROR('Gainsay drivers · Gainsay data-'!D6>='Gainsay drivers · Gainsay fixed'!B27),'Gainsay drivers · Gainsay data-'!D6>='Gainsay drivers · Gainsay fixed'!B27,IF(OR('Gainsay drivers · Gainsay data-'!D6="",'Gainsay drivers · Gainsay fixed'!B27=""),"",'Gainsay drivers · Gainsay data-'!D6>='Gainsay drivers · Gainsay fixed'!B27))="",FALSE(),IF(ISERROR('Gainsay drivers · Gainsay data-'!D6>='Gainsay drivers · Gainsay fixed'!B27),'Gainsay drivers · Gainsay data-'!D6>='Gainsay drivers · Gainsay fixed'!B27,IF(OR('Gainsay drivers · Gainsay data-'!D6="",'Gainsay drivers · Gainsay fixed'!B27=""),"",'Gainsay drivers · Gainsay data-'!D6>='Gainsay drivers · Gainsay fixed'!B27))),CEILING(('Gainsay drivers · Gainsay data-'!C6+'Gainsay drivers · Gainsay fixed'!B28+'Gainsay drivers · Gainsay fixed'!B30)/'Gainsay drivers · Gainsay prici'!B8,1),CEILING(('Gainsay drivers · Gainsay data-'!C6+'Gainsay drivers · Gainsay fixed'!B30)/'Gainsay drivers · Gainsay prici'!B8,1)) -> 39 | F6: =IF('Model inputs'!B825="","",EDATE(DATE(2026,10,1),IF((IF(AND('Model inputs'!B801="",'Model inputs'!B802="",'Model inputs'!B803="",'Model inputs'!B804="",'Model inputs'!B805="",'Model inputs'!B806="",'Model inputs'!B807="",'Model inputs'!B808="",'Model inputs'!B809="",'Model inputs'!B810="",'Model inputs'!B811="",'Model inputs'!B812="",'Model inputs'!B813="",'Model inputs'!B814="",'Model inputs'!B815="",'Model inputs'!B816="",'Model inputs'!B817="",'Model inputs'!B818="",'Model inputs'!B819="",'Model inputs'!B820="",'Model inputs'!B821="",'Model inputs'!B822="",'Model inputs'!B823="",'Model inputs'!B824=""),"",MIN('Model inputs'!B801,'Model inputs'!B802,'Model inputs'!B803,'Model inputs'!B804,'Model inputs'!B805,'Model inputs'!B806,'Model inputs'!B807,'Model inputs'!B808,'Model inputs'!B809,'Model inputs'!B810,'Model inputs'!B811,'Model inputs'!B812,'Model inputs'!B813,'Model inputs'!B814,'Model inputs'!B815,'Model inputs'!B816,'Model inputs'!B817,'Model inputs'!B818,'Model inputs'!B819,'Model inputs'!B820,'Model inputs'!B821,'Model inputs'!B822,'Model inputs'!B823,'Model inputs'!B824)))="",0,(IF(AND('Model inputs'!B801="",'Model inputs'!B802="",'Model inputs'!B803="",'Model inputs'!B804="",'Model inputs'!B805="",'Model inputs'!B806="",'Model inputs'!B807="",'Model inputs'!B808="",'Model inputs'!B809="",'Model inputs'!B810="",'Model inputs'!B811="",'Model inputs'!B812="",'Model inputs'!B813="",'Model inputs'!B814="",'Model inputs'!B815="",'Model inputs'!B816="",'Model inputs'!B817="",'Model inputs'!B818="",'Model inputs'!B819="",'Model inputs'!B820="",'Model inputs'!B821="",'Model inputs'!B822="",'Model inputs'!B823="",'Model inputs'!B824=""),"",MIN('Model inputs'!B801,'Model inputs'!B802,'Model inputs'!B803,'Model inputs'!B804,'Model inputs'!B805,'Model inputs'!B806,'Model inputs'!B807,'Model inputs'!B808,'Model inputs'!B809,'Model inputs'!B810,'Model inputs'!B811,'Model inputs'!B812,'Model inputs'!B813,'Model inputs'!B814,'Model inputs'!B815,'Model inputs'!B816,'Model inputs'!B817,'Model inputs'!B818,'Model inputs'!B819,'Model inputs'!B820,'Model inputs'!B821,'Model inputs'!B822,'Model inputs'!B823,'Model inputs'!B824))))-1)) -> 46600 | G6: =MIN('Gainsay economics · Gainsay dat'!B16,'Gainsay economics · Gainsay dat'!C16,'Gainsay economics · Gainsay dat'!D16,'Gainsay economics · Gainsay dat'!E16,'Gainsay economics · Gainsay dat'!F16,'Gainsay economics · Gainsay dat'!G16,'Gainsay economics · Gainsay dat'!H16,'Gainsay economics · Gainsay dat'!I16,'Gainsay economics · Gainsay dat'!J16,'Gainsay economics · Gainsay dat'!K16,'Gainsay economics · Gainsay dat'!L16,'Gainsay economics · Gainsay dat'!M16,'Gainsay economics · Gainsay dat'!N16,'Gainsay economics · Gainsay dat'!O16,'Gainsay economics · Gainsay dat'!P16) -> -53.199018 | H6: =IF('Model inputs'!B898="","",EDATE(DATE(2026,10,1),IF((IF(AND('Model inputs'!B874="",'Model inputs'!B875="",'Model inputs'!B876="",'Model inputs'!B877="",'Model inputs'!B878="",'Model inputs'!B879="",'Model inputs'!B880="",'Model inputs'!B881="",'Model inputs'!B882="",'Model inputs'!B883="",'Model inputs'!B884="",'Model inputs'!B885="",'Model inputs'!B886="",'Model inputs'!B887="",'Model inputs'!B888="",'Model inputs'!B889="",'Model inputs'!B890="",'Model inputs'!B891="",'Model inputs'!B892="",'Model inputs'!B893="",'Model inputs'!B894="",'Model inputs'!B895="",'Model inputs'!B896="",'Model inputs'!B897=""),"",MIN('Model inputs'!B874,'Model inputs'!B875,'Model inputs'!B876,'Model inputs'!B877,'Model inputs'!B878,'Model inputs'!B879,'Model inputs'!B880,'Model inputs'!B881,'Model inputs'!B882,'Model inputs'!B883,'Model inputs'!B884,'Model inputs'!B885,'Model inputs'!B886,'Model inputs'!B887,'Model inputs'!B888,'Model inputs'!B889,'Model inputs'!B890,'Model inputs'!B891,'Model inputs'!B892,'Model inputs'!B893,'Model inputs'!B894,'Model inputs'!B895,'Model inputs'!B896,'Model inputs'!B897)))="",0,(IF(AND('Model inputs'!B874="",'Model inputs'!B875="",'Model inputs'!B876="",'Model inputs'!B877="",'Model inputs'!B878="",'Model inputs'!B879="",'Model inputs'!B880="",'Model inputs'!B881="",'Model inputs'!B882="",'Model inputs'!B883="",'Model inputs'!B884="",'Model inputs'!B885="",'Model inputs'!B886="",'Model inputs'!B887="",'Model inputs'!B888="",'Model inputs'!B889="",'Model inputs'!B890="",'Model inputs'!B891="",'Model inputs'!B892="",'Model inputs'!B893="",'Model inputs'!B894="",'Model inputs'!B895="",'Model inputs'!B896="",'Model inputs'!B897=""),"",MIN('Model inputs'!B874,'Model inputs'!B875,'Model inputs'!B876,'Model inputs'!B877,'Model inputs'!B878,'Model inputs'!B879,'Model inputs'!B880,'Model inputs'!B881,'Model inputs'!B882,'Model inputs'!B883,'Model inputs'!B884,'Model inputs'!B885,'Model inputs'!B886,'Model inputs'!B887,'Model inputs'!B888,'Model inputs'!B889,'Model inputs'!B890,'Model inputs'!B891,'Model inputs'!B892,'Model inputs'!B893,'Model inputs'!B894,'Model inputs'!B895,'Model inputs'!B896,'Model inputs'!B897))))-1)) -> 46569 | I6: =CEILING('Gainsay drivers · Gainsay fixed'!B21+'Gainsay drivers · Gainsay fixed'!B31*('Gainsay drivers · Gainsay data-'!C6+'Gainsay drivers · Gainsay fixed'!B30)-'Gainsay drivers · Gainsay data-'!G6,'Gainsay drivers · Gainsay fixed'!B33) -> 8500 | J6: =IF('Gainsay drivers · Gainsay data-'!F6="","Not reached through December 2027","Reached") -> Reached
A7: No fee sensitivity only | B7: 0 | C7: ='Gainsay drivers · Gainsay prici'!B10+('Gainsay drivers · Gainsay data-'!B7-'Gainsay drivers · Gainsay fixed'!B20)/12 -> 760.6 | D7: =CEILING('Gainsay drivers · Gainsay data-'!C7/'Gainsay drivers · Gainsay prici'!B8,1) -> 30 | E7: =IF(IF(IF(ISERROR('Gainsay drivers · Gainsay data-'!D7>='Gainsay drivers · Gainsay fixed'!B27),'Gainsay drivers · Gainsay data-'!D7>='Gainsay drivers · Gainsay fixed'!B27,IF(OR('Gainsay drivers · Gainsay data-'!D7="",'Gainsay drivers · Gainsay fixed'!B27=""),"",'Gainsay drivers · Gainsay data-'!D7>='Gainsay drivers · Gainsay fixed'!B27))="",FALSE(),IF(ISERROR('Gainsay drivers · Gainsay data-'!D7>='Gainsay drivers · Gainsay fixed'!B27),'Gainsay drivers · Gainsay data-'!D7>='Gainsay drivers · Gainsay fixed'!B27,IF(OR('Gainsay drivers · Gainsay data-'!D7="",'Gainsay drivers · Gainsay fixed'!B27=""),"",'Gainsay drivers · Gainsay data-'!D7>='Gainsay drivers · Gainsay fixed'!B27))),CEILING(('Gainsay drivers · Gainsay data-'!C7+'Gainsay drivers · Gainsay fixed'!B28+'Gainsay drivers · Gainsay fixed'!B30)/'Gainsay drivers · Gainsay prici'!B8,1),CEILING(('Gainsay drivers · Gainsay data-'!C7+'Gainsay drivers · Gainsay fixed'!B30)/'Gainsay drivers · Gainsay prici'!B8,1)) -> 30 | F7: =IF('Model inputs'!B962="","",EDATE(DATE(2026,10,1),IF((IF(AND('Model inputs'!B938="",'Model inputs'!B939="",'Model inputs'!B940="",'Model inputs'!B941="",'Model inputs'!B942="",'Model inputs'!B943="",'Model inputs'!B944="",'Model inputs'!B945="",'Model inputs'!B946="",'Model inputs'!B947="",'Model inputs'!B948="",'Model inputs'!B949="",'Model inputs'!B950="",'Model inputs'!B951="",'Model inputs'!B952="",'Model inputs'!B953="",'Model inputs'!B954="",'Model inputs'!B955="",'Model inputs'!B956="",'Model inputs'!B957="",'Model inputs'!B958="",'Model inputs'!B959="",'Model inputs'!B960="",'Model inputs'!B961=""),"",MIN('Model inputs'!B938,'Model inputs'!B939,'Model inputs'!B940,'Model inputs'!B941,'Model inputs'!B942,'Model inputs'!B943,'Model inputs'!B944,'Model inputs'!B945,'Model inputs'!B946,'Model inputs'!B947,'Model inputs'!B948,'Model inputs'!B949,'Model inputs'!B950,'Model inputs'!B951,'Model inputs'!B952,'Model inputs'!B953,'Model inputs'!B954,'Model inputs'!B955,'Model inputs'!B956,'Model inputs'!B957,'Model inputs'!B958,'Model inputs'!B959,'Model inputs'!B960,'Model inputs'!B961)))="",0,(IF(AND('Model inputs'!B938="",'Model inputs'!B939="",'Model inputs'!B940="",'Model inputs'!B941="",'Model inputs'!B942="",'Model inputs'!B943="",'Model inputs'!B944="",'Model inputs'!B945="",'Model inputs'!B946="",'Model inputs'!B947="",'Model inputs'!B948="",'Model inputs'!B949="",'Model inputs'!B950="",'Model inputs'!B951="",'Model inputs'!B952="",'Model inputs'!B953="",'Model inputs'!B954="",'Model inputs'!B955="",'Model inputs'!B956="",'Model inputs'!B957="",'Model inputs'!B958="",'Model inputs'!B959="",'Model inputs'!B960="",'Model inputs'!B961=""),"",MIN('Model inputs'!B938,'Model inputs'!B939,'Model inputs'!B940,'Model inputs'!B941,'Model inputs'!B942,'Model inputs'!B943,'Model inputs'!B944,'Model inputs'!B945,'Model inputs'!B946,'Model inputs'!B947,'Model inputs'!B948,'Model inputs'!B949,'Model inputs'!B950,'Model inputs'!B951,'Model inputs'!B952,'Model inputs'!B953,'Model inputs'!B954,'Model inputs'!B955,'Model inputs'!B956,'Model inputs'!B957,'Model inputs'!B958,'Model inputs'!B959,'Model inputs'!B960,'Model inputs'!B961))))-1)) -> 46508 | G7: =MIN('Gainsay economics · Gainsay dat'!B17,'Gainsay economics · Gainsay dat'!C17,'Gainsay economics · Gainsay dat'!D17,'Gainsay economics · Gainsay dat'!E17,'Gainsay economics · Gainsay dat'!F17,'Gainsay economics · Gainsay dat'!G17,'Gainsay economics · Gainsay dat'!H17,'Gainsay economics · Gainsay dat'!I17,'Gainsay economics · Gainsay dat'!J17,'Gainsay economics · Gainsay dat'!K17,'Gainsay economics · Gainsay dat'!L17,'Gainsay economics · Gainsay dat'!M17,'Gainsay economics · Gainsay dat'!N17,'Gainsay economics · Gainsay dat'!O17,'Gainsay economics · Gainsay dat'!P17) -> 2074.2752 | H7: =IF('Model inputs'!B1035="","",EDATE(DATE(2026,10,1),IF((IF(AND('Model inputs'!B1011="",'Model inputs'!B1012="",'Model inputs'!B1013="",'Model inputs'!B1014="",'Model inputs'!B1015="",'Model inputs'!B1016="",'Model inputs'!B1017="",'Model inputs'!B1018="",'Model inputs'!B1019="",'Model inputs'!B1020="",'Model inputs'!B1021="",'Model inputs'!B1022="",'Model inputs'!B1023="",'Model inputs'!B1024="",'Model inputs'!B1025="",'Model inputs'!B1026="",'Model inputs'!B1027="",'Model inputs'!B1028="",'Model inputs'!B1029="",'Model inputs'!B1030="",'Model inputs'!B1031="",'Model inputs'!B1032="",'Model inputs'!B1033="",'Model inputs'!B1034=""),"",MIN('Model inputs'!B1011,'Model inputs'!B1012,'Model inputs'!B1013,'Model inputs'!B1014,'Model inputs'!B1015,'Model inputs'!B1016,'Model inputs'!B1017,'Model inputs'!B1018,'Model inputs'!B1019,'Model inputs'!B1020,'Model inputs'!B1021,'Model inputs'!B1022,'Model inputs'!B1023,'Model inputs'!B1024,'Model inputs'!B1025,'Model inputs'!B1026,'Model inputs'!B1027,'Model inputs'!B1028,'Model inputs'!B1029,'Model inputs'!B1030,'Model inputs'!B1031,'Model inputs'!B1032,'Model inputs'!B1033,'Model inputs'!B1034)))="",0,(IF(AND('Model inputs'!B1011="",'Model inputs'!B1012="",'Model inputs'!B1013="",'Model inputs'!B1014="",'Model inputs'!B1015="",'Model inputs'!B1016="",'Model inputs'!B1017="",'Model inputs'!B1018="",'Model inputs'!B1019="",'Model inputs'!B1020="",'Model inputs'!B1021="",'Model inputs'!B1022="",'Model inputs'!B1023="",'Model inputs'!B1024="",'Model inputs'!B1025="",'Model inputs'!B1026="",'Model inputs'!B1027="",'Model inputs'!B1028="",'Model inputs'!B1029="",'Model inputs'!B1030="",'Model inputs'!B1031="",'Model inputs'!B1032="",'Model inputs'!B1033="",'Model inputs'!B1034=""),"",MIN('Model inputs'!B1011,'Model inputs'!B1012,'Model inputs'!B1013,'Model inputs'!B1014,'Model inputs'!B1015,'Model inputs'!B1016,'Model inputs'!B1017,'Model inputs'!B1018,'Model inputs'!B1019,'Model inputs'!B1020,'Model inputs'!B1021,'Model inputs'!B1022,'Model inputs'!B1023,'Model inputs'!B1024,'Model inputs'!B1025,'Model inputs'!B1026,'Model inputs'!B1027,'Model inputs'!B1028,'Model inputs'!B1029,'Model inputs'!B1030,'Model inputs'!B1031,'Model inputs'!B1032,'Model inputs'!B1033,'Model inputs'!B1034))))-1)) -> 46478 | I7: =CEILING('Gainsay drivers · Gainsay fixed'!B21+'Gainsay drivers · Gainsay fixed'!B31*('Gainsay drivers · Gainsay data-'!C7+'Gainsay drivers · Gainsay fixed'!B30)-'Gainsay drivers · Gainsay data-'!G7,'Gainsay drivers · Gainsay fixed'!B33) -> 5500 | J7: =IF('Gainsay drivers · Gainsay data-'!F7="","Not reached through December 2027","Reached") -> Reached

Sheet Gainsay economics · Gainsay ope
A1: Gainsay economics · Gainsay operating forecast
A2: Financial model (3 pages) · Main Scenario
A4: Variable / dimension | B4: 2026-10 | C4: 2026-11 | D4: 2026-12 | E4: 2027-01 | F4: 2027-02 | G4: 2027-03 | H4: 2027-04 | I4: 2027-05 | J4: 2027-06 | K4: 2027-07 | L4: 2027-08 | M4: 2027-09 | N4: 2027-10 | O4: 2027-11 | P4: 2027-12
A5: Active dockets | B5: ='Model inputs'!J6*(1-'Gainsay drivers · Gainsay deman'!B7)+'Gainsay drivers · Gainsay deman'!B5 -> 3 | C5: ='Gainsay economics · Gainsay ope'!B5*(1-'Gainsay drivers · Gainsay deman'!C7)+'Gainsay drivers · Gainsay deman'!C5 -> 6.06 | D5: ='Gainsay economics · Gainsay ope'!C5*(1-'Gainsay drivers · Gainsay deman'!D7)+'Gainsay drivers · Gainsay deman'!D5 -> 9.1857 | E5: ='Gainsay economics · Gainsay ope'!D5*(1-'Gainsay drivers · Gainsay deman'!E7)+'Gainsay drivers · Gainsay deman'!E5 -> 12.383004 | F5: ='Gainsay economics · Gainsay ope'!E5*(1-'Gainsay drivers · Gainsay deman'!F7)+'Gainsay drivers · Gainsay deman'!F5 -> 15.658033 | G5: ='Gainsay economics · Gainsay ope'!F5*(1-'Gainsay drivers · Gainsay deman'!G7)+'Gainsay drivers · Gainsay deman'!G5 -> 19.017136 | H5: ='Gainsay economics · Gainsay ope'!G5*(1-'Gainsay drivers · Gainsay deman'!H7)+'Gainsay drivers · Gainsay deman'!H5 -> 22.466909 | I5: ='Gainsay economics · Gainsay ope'!H5*(1-'Gainsay drivers · Gainsay deman'!I7)+'Gainsay drivers · Gainsay deman'!I5 -> 26.014203 | J5: ='Gainsay economics · Gainsay ope'!I5*(1-'Gainsay drivers · Gainsay deman'!J7)+'Gainsay drivers · Gainsay deman'!J5 -> 29.666143 | ... P5: ='Gainsay economics · Gainsay ope'!O5*(1-'Gainsay drivers · Gainsay deman'!P7)+'Gainsay drivers · Gainsay deman'!P5 -> 54.212887
A6: Brief checks sold | B6: ='Gainsay drivers · Gainsay deman'!B8 -> 10 | C6: ='Gainsay economics · Gainsay ope'!B6*(1+'Gainsay drivers · Gainsay deman'!C9) -> 10.5 | D6: ='Gainsay economics · Gainsay ope'!C6*(1+'Gainsay drivers · Gainsay deman'!D9) -> 11.025 | E6: ='Gainsay economics · Gainsay ope'!D6*(1+'Gainsay drivers · Gainsay deman'!E9) -> 11.57625 | F6: ='Gainsay economics · Gainsay ope'!E6*(1+'Gainsay drivers · Gainsay deman'!F9) -> 12.155062 | G6: ='Gainsay economics · Gainsay ope'!F6*(1+'Gainsay drivers · Gainsay deman'!G9) -> 12.762816 | H6: ='Gainsay economics · Gainsay ope'!G6*(1+'Gainsay drivers · Gainsay deman'!H9) -> 13.400956 | I6: ='Gainsay economics · Gainsay ope'!H6*(1+'Gainsay drivers · Gainsay deman'!I9) -> 14.071004 | J6: ='Gainsay economics · Gainsay ope'!I6*(1+'Gainsay drivers · Gainsay deman'!J9) -> 14.774554 | ... P6: ='Gainsay economics · Gainsay ope'!O6*(1+'Gainsay drivers · Gainsay deman'!P9) -> 19.799316
A7: Gainsay revenue | B7: ='Gainsay economics · Gainsay ope'!B16+'Gainsay economics · Gainsay ope'!B17 -> 177 | C7: ='Gainsay economics · Gainsay ope'!C16+'Gainsay economics · Gainsay ope'!C17 -> 270.24 | D7: ='Gainsay economics · Gainsay ope'!D16+'Gainsay economics · Gainsay ope'!D17 -> 365.6103 | E7: ='Gainsay economics · Gainsay ope'!E16+'Gainsay economics · Gainsay ope'!E17 -> 463.29337 | F7: ='Gainsay economics · Gainsay ope'!F16+'Gainsay economics · Gainsay ope'!F17 -> 563.47851 | G7: ='Gainsay economics · Gainsay ope'!G16+'Gainsay economics · Gainsay ope'!G17 -> 666.36229 | H7: ='Gainsay economics · Gainsay ope'!H16+'Gainsay economics · Gainsay ope'!H17 -> 772.14897 | I7: ='Gainsay economics · Gainsay ope'!I16+'Gainsay economics · Gainsay ope'!I17 -> 881.05093 | ... P7: ='Gainsay economics · Gainsay ope'!P16+'Gainsay economics · Gainsay ope'!P17 -> 1750.3676
A8: Card fees | B8: =IF('Gainsay economics · Gainsay ope'!B24="","",'Gainsay economics · Gainsay ope'!B24) -> 9.033 | C8: =IF('Gainsay economics · Gainsay ope'!C24="","",'Gainsay economics · Gainsay ope'!C24) -> 12.80496 | D8: =IF('Gainsay economics · Gainsay ope'!D24="","",'Gainsay economics · Gainsay ope'!D24) -> 16.665909 | E8: =IF('Gainsay economics · Gainsay ope'!E24="","",'Gainsay economics · Gainsay ope'!E24) -> 20.623284 | F8: =IF('Gainsay economics · Gainsay ope'!F24="","",'Gainsay economics · Gainsay ope'!F24) -> 24.684805 | G8: =IF('Gainsay economics · Gainsay ope'!G24="","",'Gainsay economics · Gainsay ope'!G24) -> 28.858492 | H8: =IF('Gainsay economics · Gainsay ope'!H24="","",'Gainsay economics · Gainsay ope'!H24) -> 33.15268 | I8: =IF('Gainsay economics · Gainsay ope'!I24="","",'Gainsay economics · Gainsay ope'!I24) -> 37.576039 | ... P8: =IF('Gainsay economics · Gainsay ope'!P24="","",'Gainsay economics · Gainsay ope'!P24) -> 72.96432
A9: Claude cost | B9: ='Gainsay economics · Gainsay ope'!B22+'Gainsay economics · Gainsay ope'!B23 -> 30.16 | C9: ='Gainsay economics · Gainsay ope'!C22+'Gainsay economics · Gainsay ope'!C23 -> 36.1842 | D9: ='Gainsay economics · Gainsay ope'!D22+'Gainsay economics · Gainsay ope'!D23 -> 42.350724 | E9: ='Gainsay economics · Gainsay ope'!E22+'Gainsay economics · Gainsay ope'!E23 -> 48.671455 | F9: ='Gainsay economics · Gainsay ope'!F22+'Gainsay economics · Gainsay ope'!F23 -> 55.158726 | G9: ='Gainsay economics · Gainsay ope'!G22+'Gainsay economics · Gainsay ope'!G23 -> 61.82535 | H9: ='Gainsay economics · Gainsay ope'!H22+'Gainsay economics · Gainsay ope'!H23 -> 68.684645 | I9: ='Gainsay economics · Gainsay ope'!I22+'Gainsay economics · Gainsay ope'!I23 -> 75.750464 | ... P9: ='Gainsay economics · Gainsay ope'!P22+'Gainsay economics · Gainsay ope'!P23 -> 132.28483
A10: Fixed costs monthly reserved | B10: ='Gainsay drivers · Gainsay prici'!B10-'Gainsay economics · Gainsay ope'!B23+'Gainsay economics · Gainsay ope'!B27+'Gainsay economics · Gainsay ope'!B49 -> 995 | C10: ='Gainsay drivers · Gainsay prici'!B10-'Gainsay economics · Gainsay ope'!C23+'Gainsay economics · Gainsay ope'!C27+'Gainsay economics · Gainsay ope'!C49 -> 995 | D10: ='Gainsay drivers · Gainsay prici'!B10-'Gainsay economics · Gainsay ope'!D23+'Gainsay economics · Gainsay ope'!D27+'Gainsay economics · Gainsay ope'!D49 -> 995 | E10: ='Gainsay drivers · Gainsay prici'!B10-'Gainsay economics · Gainsay ope'!E23+'Gainsay economics · Gainsay ope'!E27+'Gainsay economics · Gainsay ope'!E49 -> 995 | F10: ='Gainsay drivers · Gainsay prici'!B10-'Gainsay economics · Gainsay ope'!F23+'Gainsay economics · Gainsay ope'!F27+'Gainsay economics · Gainsay ope'!F49 -> 995 | G10: ='Gainsay drivers · Gainsay prici'!B10-'Gainsay economics · Gainsay ope'!G23+'Gainsay economics · Gainsay ope'!G27+'Gainsay economics · Gainsay ope'!G49 -> 995 | H10: ='Gainsay drivers · Gainsay prici'!B10-'Gainsay economics · Gainsay ope'!H23+'Gainsay economics · Gainsay ope'!H27+'Gainsay economics · Gainsay ope'!H49 -> 995 | I10: ='Gainsay drivers · Gainsay prici'!B10-'Gainsay economics · Gainsay ope'!I23+'Gainsay economics · Gainsay ope'!I27+'Gainsay economics · Gainsay ope'!I49 -> 995 | J10: ='Gainsay drivers · Gainsay prici'!B10-'Gainsay economics · Gainsay ope'!J23+'Gainsay economics · Gainsay ope'!J27+'Gainsay economics · Gainsay ope'!J49 -> 995 | K10: ='Gainsay drivers · Gainsay prici'!B10-'Gainsay economics · Gainsay ope'!K23+'Gainsay economics · Gainsay ope'!K27+'Gainsay economics · Gainsay ope'!K49 -> 995 | L10: ='Gainsay drivers · Gainsay prici'!B10-'Gainsay economics · Gainsay ope'!L23+'Gainsay economics · Gainsay ope'!L27+'Gainsay economics · Gainsay ope'!L49 -> 995 | M10: ='Gainsay drivers · Gainsay prici'!B10-'Gainsay economics · Gainsay ope'!M23+'Gainsay economics · Gainsay ope'!M27+'Gainsay economics · Gainsay ope'!M49 -> 995 | N10: ='Gainsay drivers · Gainsay prici'!B10-'Gainsay economics · Gainsay ope'!N23+'Gainsay economics · Gainsay ope'!N27+'Gainsay economics · Gainsay ope'!N49 -> 995 | O10: ='Gainsay drivers · Gainsay prici'!B10-'Gainsay economics · Gainsay ope'!O23+'Gainsay economics · Gainsay ope'!O27+'Gainsay economics · Gainsay ope'!O49 -> 995 | P10: ='Gainsay drivers · Gainsay prici'!B10-'Gainsay economics · Gainsay ope'!P23+'Gainsay economics · Gainsay ope'!P27+'Gainsay economics · Gainsay ope'!P49 -> 1395
A11: Monthly result | B11: ='Gainsay economics · Gainsay ope'!B7-'Gainsay economics · Gainsay ope'!B8-'Gainsay economics · Gainsay ope'!B9-'Gainsay economics · Gainsay ope'!B10 -> -857.193 | C11: ='Gainsay economics · Gainsay ope'!C7-'Gainsay economics · Gainsay ope'!C8-'Gainsay economics · Gainsay ope'!C9-'Gainsay economics · Gainsay ope'!C10 -> -773.74916 | D11: ='Gainsay economics · Gainsay ope'!D7-'Gainsay economics · Gainsay ope'!D8-'Gainsay economics · Gainsay ope'!D9-'Gainsay economics · Gainsay ope'!D10 -> -688.40633 | E11: ='Gainsay economics · Gainsay ope'!E7-'Gainsay economics · Gainsay ope'!E8-'Gainsay economics · Gainsay ope'!E9-'Gainsay economics · Gainsay ope'!E10 -> -601.00137 | F11: ='Gainsay economics · Gainsay ope'!F7-'Gainsay economics · Gainsay ope'!F8-'Gainsay economics · Gainsay ope'!F9-'Gainsay economics · Gainsay ope'!F10 -> -511.36502 | G11: ='Gainsay economics · Gainsay ope'!G7-'Gainsay economics · Gainsay ope'!G8-'Gainsay economics · Gainsay ope'!G9-'Gainsay economics · Gainsay ope'!G10 -> -419.32155 | H11: ='Gainsay economics · Gainsay ope'!H7-'Gainsay economics · Gainsay ope'!H8-'Gainsay economics · Gainsay ope'!H9-'Gainsay economics · Gainsay ope'!H10 -> -324.68835 | I11: ='Gainsay economics · Gainsay ope'!I7-'Gainsay economics · Gainsay ope'!I8-'Gainsay economics · Gainsay ope'!I9-'Gainsay economics · Gainsay ope'!I10 -> -227.27557 | ... P11: ='Gainsay economics · Gainsay ope'!P7-'Gainsay economics · Gainsay ope'!P8-'Gainsay economics · Gainsay ope'!P9-'Gainsay economics · Gainsay ope'!P10 -> 150.11842
A12: Cumulative cash monthly reserved | B12: =IF(IF(DATE(2026,10,1)=DATE(2026,10,1),'Gainsay drivers · Gainsay fixed'!B21-'Gainsay drivers · Gainsay fixed'!B22,IF('Model inputs'!J32="","",'Model inputs'!J32))="",0,IF(DATE(2026,10,1)=DATE(2026,10,1),'Gainsay drivers · Gainsay fixed'!B21-'Gainsay drivers · Gainsay fixed'!B22,IF('Model inputs'!J32="","",'Model inputs'!J32)))+'Gainsay economics · Gainsay ope'!B11 -> 3642.807 | C12: =IF(IF(DATE(2026,11,1)=DATE(2026,10,1),'Gainsay drivers · Gainsay fixed'!B21-'Gainsay drivers · Gainsay fixed'!B22,IF('Gainsay economics · Gainsay ope'!B12="","",'Gainsay economics · Gainsay ope'!B12))="",0,IF(DATE(2026,11,1)=DATE(2026,10,1),'Gainsay drivers · Gainsay fixed'!B21-'Gainsay drivers · Gainsay fixed'!B22,IF('Gainsay economics · Gainsay ope'!B12="","",'Gainsay economics · Gainsay ope'!B12)))+'Gainsay economics · Gainsay ope'!C11 -> 2869.0578 | D12: =IF(IF(DATE(2026,12,1)=DATE(2026,10,1),'Gainsay drivers · Gainsay fixed'!B21-'Gainsay drivers · Gainsay fixed'!B22,IF('Gainsay economics · Gainsay ope'!C12="","",'Gainsay economics · Gainsay ope'!C12))="",0,IF(DATE(2026,12,1)=DATE(2026,10,1),'Gainsay drivers · Gainsay fixed'!B21-'Gainsay drivers · Gainsay fixed'!B22,IF('Gainsay economics · Gainsay ope'!C12="","",'Gainsay economics · Gainsay ope'!C12)))+'Gainsay economics · Gainsay ope'!D11 -> 2180.6515 | E12: =IF(IF(DATE(2027,1,1)=DATE(2026,10,1),'Gainsay drivers · Gainsay fixed'!B21-'Gainsay drivers · Gainsay fixed'!B22,IF('Gainsay economics · Gainsay ope'!D12="","",'Gainsay economics · Gainsay ope'!D12))="",0,IF(DATE(2027,1,1)=DATE(2026,10,1),'Gainsay drivers · Gainsay fixed'!B21-'Gainsay drivers · Gainsay fixed'!B22,IF('Gainsay economics · Gainsay ope'!D12="","",'Gainsay economics · Gainsay ope'!D12)))+'Gainsay economics · Gainsay ope'!E11 -> 1579.6501 | F12: =IF(IF(DATE(2027,2,1)=DATE(2026,10,1),'Gainsay drivers · Gainsay fixed'!B21-'Gainsay drivers · Gainsay fixed'!B22,IF('Gainsay economics · Gainsay ope'!E12="","",'Gainsay economics · Gainsay ope'!E12))="",0,IF(DATE(2027,2,1)=DATE(2026,10,1),'Gainsay drivers · Gainsay fixed'!B21-'Gainsay drivers · Gainsay fixed'!B22,IF('Gainsay economics · Gainsay ope'!E12="","",'Gainsay economics · Gainsay ope'!E12)))+'Gainsay economics · Gainsay ope'!F11 -> 1068.2851 | G12: =IF(IF(DATE(2027,3,1)=DATE(2026,10,1),'Gainsay drivers · Gainsay fixed'!B21-'Gainsay drivers · Gainsay fixed'!B22,IF('Gainsay economics · Gainsay ope'!F12="","",'Gainsay economics · Gainsay ope'!F12))="",0,IF(DATE(2027,3,1)=DATE(2026,10,1),'Gainsay drivers · Gainsay fixed'!B21-'Gainsay drivers · Gainsay fixed'!B22,IF('Gainsay economics · Gainsay ope'!F12="","",'Gainsay economics · Gainsay ope'!F12)))+'Gainsay economics · Gainsay ope'!G11 -> 648.96356 | H12: =IF(IF(DATE(2027,4,1)=DATE(2026,10,1),'Gainsay drivers · Gainsay fixed'!B21-'Gainsay drivers · Gainsay fixed'!B22,IF('Gainsay economics · Gainsay ope'!G12="","",'Gainsay economics · Gainsay ope'!G12))="",0,IF(DATE(2027,4,1)=DATE(2026,10,1),'Gainsay drivers · Gainsay fixed'!B21-'Gainsay drivers · Gainsay fixed'!B22,IF('Gainsay economics · Gainsay ope'!G12="","",'Gainsay economics · Gainsay ope'!G12)))+'Gainsay economics · Gainsay ope'!H11 -> 324.27521 | I12: =IF(IF(DATE(2027,5,1)=DATE(2026,10,1),'Gainsay drivers · Gainsay fixed'!B21-'Gainsay drivers · Gainsay fixed'!B22,IF('Gainsay economics · Gainsay ope'!H12="","",'Gainsay economics · Gainsay ope'!H12))="",0,IF(DATE(2027,5,1)=DATE(2026,10,1),'Gainsay drivers · Gainsay fixed'!B21-'Gainsay drivers · Gainsay fixed'!B22,IF('Gainsay economics · Gainsay ope'!H12="","",'Gainsay economics · Gainsay ope'!H12)))+'Gainsay economics · Gainsay ope'!I11 -> 96.99964 | J12: =IF(IF(DATE(2027,6,1)=DATE(2026,10,1),'Gainsay drivers · Gainsay fixed'!B21-'Gainsay drivers · Gainsay fixed'!B22,IF('Gainsay economics · Gainsay ope'!I12="","",'Gainsay economics · Gainsay ope'!I12))="",0,IF(DATE(2027,6,1)=DATE(2026,10,1),'Gainsay drivers · Gainsay fixed'!B21-'Gainsay drivers · Gainsay fixed'!B22,IF('Gainsay economics · Gainsay ope'!I12="","",'Gainsay economics · Gainsay ope'!I12)))+'Gainsay economics · Gainsay ope'!J11 -> -29.886032 | K12: =IF(IF(DATE(2027,7,1)=DATE(2026,10,1),'Gainsay drivers · Gainsay fixed'!B21-'Gainsay drivers · Gainsay fixed'!B22,IF('Gainsay economics · Gainsay ope'!J12="","",'Gainsay economics · Gainsay ope'!J12))="",0,IF(DATE(2027,7,1)=DATE(2026,10,1),'Gainsay drivers · Gainsay fixed'!B21-'Gainsay drivers · Gainsay fixed'!B22,IF('Gainsay economics · Gainsay ope'!J12="","",'Gainsay economics · Gainsay ope'!J12)))+'Gainsay economics · Gainsay ope'!K11 -> -53.199018 | L12: =IF(IF(DATE(2027,8,1)=DATE(2026,10,1),'Gainsay drivers · Gainsay fixed'!B21-'Gainsay drivers · Gainsay fixed'!B22,IF('Gainsay economics · Gainsay ope'!K12="","",'Gainsay economics · Gainsay ope'!K12))="",0,IF(DATE(2027,8,1)=DATE(2026,10,1),'Gainsay drivers · Gainsay fixed'!B21-'Gainsay drivers · Gainsay fixed'!B22,IF('Gainsay economics · Gainsay ope'!K12="","",'Gainsay economics · Gainsay ope'!K12)))+'Gainsay economics · Gainsay ope'!L11 -> 30.457708 | M12: =IF(IF(DATE(2027,9,1)=DATE(2026,10,1),'Gainsay drivers · Gainsay fixed'!B21-'Gainsay drivers · Gainsay fixed'!B22,IF('Gainsay economics · Gainsay ope'!L12="","",'Gainsay economics · Gainsay ope'!L12))="",0,IF(DATE(2027,9,1)=DATE(2026,10,1),'Gainsay drivers · Gainsay fixed'!B21-'Gainsay drivers · Gainsay fixed'!B22,IF('Gainsay economics · Gainsay ope'!L12="","",'Gainsay economics · Gainsay ope'!L12)))+'Gainsay economics · Gainsay ope'!M11 -> 224.70447 | N12: =IF(IF(DATE(2027,10,1)=DATE(2026,10,1),'Gainsay drivers · Gainsay fixed'!B21-'Gainsay drivers · Gainsay fixed'!B22,IF('Gainsay economics · Gainsay ope'!M12="","",'Gainsay economics · Gainsay ope'!M12))="",0,IF(DATE(2027,10,1)=DATE(2026,10,1),'Gainsay drivers · Gainsay fixed'!B21-'Gainsay drivers · Gainsay fixed'!B22,IF('Gainsay economics · Gainsay ope'!M12="","",'Gainsay economics · Gainsay ope'!M12)))+'Gainsay economics · Gainsay ope'!N11 -> 533.39445 | O12: =IF(IF(DATE(2027,11,1)=DATE(2026,10,1),'Gainsay drivers · Gainsay fixed'!B21-'Gainsay drivers · Gainsay fixed'!B22,IF('Gainsay economics · Gainsay ope'!N12="","",'Gainsay economics · Gainsay ope'!N12))="",0,IF(DATE(2027,11,1)=DATE(2026,10,1),'Gainsay drivers · Gainsay fixed'!B21-'Gainsay drivers · Gainsay fixed'!B22,IF('Gainsay economics · Gainsay ope'!N12="","",'Gainsay economics · Gainsay ope'!N12)))+'Gainsay economics · Gainsay ope'!O11 -> 960.62379 | P12: =IF(IF(DATE(2027,12,1)=DATE(2026,10,1),'Gainsay drivers · Gainsay fixed'!B21-'Gainsay drivers · Gainsay fixed'!B22,IF('Gainsay economics · Gainsay ope'!O12="","",'Gainsay economics · Gainsay ope'!O12))="",0,IF(DATE(2027,12,1)=DATE(2026,10,1),'Gainsay drivers · Gainsay fixed'!B21-'Gainsay drivers · Gainsay fixed'!B22,IF('Gainsay economics · Gainsay ope'!O12="","",'Gainsay economics · Gainsay ope'!O12)))+'Gainsay economics · Gainsay ope'!P11 -> 1110.7422
A13: Opening watched dockets | B13: =IF('Model inputs'!J40="","",'Model inputs'!J40) -> 0 | C13: =IF('Gainsay economics · Gainsay ope'!B15="","",'Gainsay economics · Gainsay ope'!B15) -> 3 | D13: =IF('Gainsay economics · Gainsay ope'!C15="","",'Gainsay economics · Gainsay ope'!C15) -> 6.06 | E13: =IF('Gainsay economics · Gainsay ope'!D15="","",'Gainsay economics · Gainsay ope'!D15) -> 9.1857 | F13: =IF('Gainsay economics · Gainsay ope'!E15="","",'Gainsay economics · Gainsay ope'!E15) -> 12.383004 | G13: =IF('Gainsay economics · Gainsay ope'!F15="","",'Gainsay economics · Gainsay ope'!F15) -> 15.658033 | H13: =IF('Gainsay economics · Gainsay ope'!G15="","",'Gainsay economics · Gainsay ope'!G15) -> 19.017136 | I13: =IF('Gainsay economics · Gainsay ope'!H15="","",'Gainsay economics · Gainsay ope'!H15) -> 22.466909 | J13: =IF('Gainsay economics · Gainsay ope'!I15="","",'Gainsay economics · Gainsay ope'!I15) -> 26.014203 | ... P13: =IF('Gainsay economics · Gainsay ope'!O15="","",'Gainsay economics · Gainsay ope'!O15) -> 49.766075
A14: Churned dockets | B14: ='Gainsay economics · Gainsay ope'!B13*'Gainsay drivers · Gainsay deman'!B7 -> 0 | C14: ='Gainsay economics · Gainsay ope'!C13*'Gainsay drivers · Gainsay deman'!C7 -> 0.09 | D14: ='Gainsay economics · Gainsay ope'!D13*'Gainsay drivers · Gainsay deman'!D7 -> 0.1818 | E14: ='Gainsay economics · Gainsay ope'!E13*'Gainsay drivers · Gainsay deman'!E7 -> 0.275571 | F14: ='Gainsay economics · Gainsay ope'!F13*'Gainsay drivers · Gainsay deman'!F7 -> 0.37149012 | G14: ='Gainsay economics · Gainsay ope'!G13*'Gainsay drivers · Gainsay deman'!G7 -> 0.46974098 | H14: ='Gainsay economics · Gainsay ope'!H13*'Gainsay drivers · Gainsay deman'!H7 -> 0.57051409 | I14: ='Gainsay economics · Gainsay ope'!I13*'Gainsay drivers · Gainsay deman'!I7 -> 0.67400728 | ... P14: ='Gainsay economics · Gainsay ope'!P13*'Gainsay drivers · Gainsay deman'!P7 -> 1.4929822
A15: Ending watched dockets | B15: =IF('Gainsay economics · Gainsay ope'!B5="","",'Gainsay economics · Gainsay ope'!B5) -> 3 | C15: =IF('Gainsay economics · Gainsay ope'!C5="","",'Gainsay economics · Gainsay ope'!C5) -> 6.06 | D15: =IF('Gainsay economics · Gainsay ope'!D5="","",'Gainsay economics · Gainsay ope'!D5) -> 9.1857 | E15: =IF('Gainsay economics · Gainsay ope'!E5="","",'Gainsay economics · Gainsay ope'!E5) -> 12.383004 | F15: =IF('Gainsay economics · Gainsay ope'!F5="","",'Gainsay economics · Gainsay ope'!F5) -> 15.658033 | G15: =IF('Gainsay economics · Gainsay ope'!G5="","",'Gainsay economics · Gainsay ope'!G5) -> 19.017136 | H15: =IF('Gainsay economics · Gainsay ope'!H5="","",'Gainsay economics · Gainsay ope'!H5) -> 22.466909 | I15: =IF('Gainsay economics · Gainsay ope'!I5="","",'Gainsay economics · Gainsay ope'!I5) -> 26.014203 | ... P15: =IF('Gainsay economics · Gainsay ope'!P5="","",'Gainsay economics · Gainsay ope'!P5) -> 54.212887
A16: Docket MRR | B16: ='Gainsay economics · Gainsay ope'!B15*'Gainsay drivers · Gainsay fixed'!B6 -> 87 | C16: ='Gainsay economics · Gainsay ope'!C15*'Gainsay drivers · Gainsay fixed'!B6 -> 175.74 | D16: ='Gainsay economics · Gainsay ope'!D15*'Gainsay drivers · Gainsay fixed'!B6 -> 266.3853 | E16: ='Gainsay economics · Gainsay ope'!E15*'Gainsay drivers · Gainsay fixed'!B6 -> 359.10712 | F16: ='Gainsay economics · Gainsay ope'!F15*'Gainsay drivers · Gainsay fixed'!B6 -> 454.08295 | G16: ='Gainsay economics · Gainsay ope'!G15*'Gainsay drivers · Gainsay fixed'!B6 -> 551.49695 | H16: ='Gainsay economics · Gainsay ope'!H15*'Gainsay drivers · Gainsay fixed'!B6 -> 651.54037 | I16: ='Gainsay economics · Gainsay ope'!I15*'Gainsay drivers · Gainsay fixed'!B6 -> 754.41189 | J16: ='Gainsay economics · Gainsay ope'!J15*'Gainsay drivers · Gainsay fixed'!B6 -> 860.31816 | K16: ='Gainsay economics · Gainsay ope'!K15*'Gainsay drivers · Gainsay fixed'!B6 -> 969.47417 | L16: ='Gainsay economics · Gainsay ope'!L15*'Gainsay drivers · Gainsay fixed'!B6 -> 1082.1038 | M16: ='Gainsay economics · Gainsay ope'!M15*'Gainsay drivers · Gainsay fixed'!B6 -> 1198.4402 | N16: ='Gainsay economics · Gainsay ope'!N15*'Gainsay drivers · Gainsay fixed'!B6 -> 1318.7265 | O16: ='Gainsay economics · Gainsay ope'!O15*'Gainsay drivers · Gainsay fixed'!B6 -> 1443.2162 | P16: ='Gainsay economics · Gainsay ope'!P15*'Gainsay drivers · Gainsay fixed'!B6 -> 1572.1737
A17: Brief revenue | B17: ='Gainsay economics · Gainsay ope'!B6*'Gainsay drivers · Gainsay fixed'!B7 -> 90 | C17: ='Gainsay economics · Gainsay ope'!C6*'Gainsay drivers · Gainsay fixed'!B7 -> 94.5 | D17: ='Gainsay economics · Gainsay ope'!D6*'Gainsay drivers · Gainsay fixed'!B7 -> 99.225 | E17: ='Gainsay economics · Gainsay ope'!E6*'Gainsay drivers · Gainsay fixed'!B7 -> 104.18625 | F17: ='Gainsay economics · Gainsay ope'!F6*'Gainsay drivers · Gainsay fixed'!B7 -> 109.39556 | G17: ='Gainsay economics · Gainsay ope'!G6*'Gainsay drivers · Gainsay fixed'!B7 -> 114.86534 | H17: ='Gainsay economics · Gainsay ope'!H6*'Gainsay drivers · Gainsay fixed'!B7 -> 120.60861 | I17: ='Gainsay economics · Gainsay ope'!I6*'Gainsay drivers · Gainsay fixed'!B7 -> 126.63904 | J17: ='Gainsay economics · Gainsay ope'!J6*'Gainsay drivers · Gainsay fixed'!B7 -> 132.97099 | K17: ='Gainsay economics · Gainsay ope'!K6*'Gainsay drivers · Gainsay fixed'!B7 -> 139.61954 | L17: ='Gainsay economics · Gainsay ope'!L6*'Gainsay drivers · Gainsay fixed'!B7 -> 146.60052 | M17: ='Gainsay economics · Gainsay ope'!M6*'Gainsay drivers · Gainsay fixed'!B7 -> 153.93054 | N17: ='Gainsay economics · Gainsay ope'!N6*'Gainsay drivers · Gainsay fixed'!B7 -> 161.62707 | O17: ='Gainsay economics · Gainsay ope'!O6*'Gainsay drivers · Gainsay fixed'!B7 -> 169.70842 | P17: ='Gainsay economics · Gainsay ope'!P6*'Gainsay drivers · Gainsay fixed'!B7 -> 178.19384
A18: Docket filings checked | B18: ='Gainsay economics · Gainsay ope'!B15*'Gainsay drivers · Gainsay fixed'!B8 -> 6 | C18: ='Gainsay economics · Gainsay ope'!C15*'Gainsay drivers · Gainsay fixed'!B8 -> 12.12 | D18: ='Gainsay economics · Gainsay ope'!D15*'Gainsay drivers · Gainsay fixed'!B8 -> 18.3714 | E18: ='Gainsay economics · Gainsay ope'!E15*'Gainsay drivers · Gainsay fixed'!B8 -> 24.766008 | F18: ='Gainsay economics · Gainsay ope'!F15*'Gainsay drivers · Gainsay fixed'!B8 -> 31.316065 | G18: ='Gainsay economics · Gainsay ope'!G15*'Gainsay drivers · Gainsay fixed'!B8 -> 38.034273 | H18: ='Gainsay economics · Gainsay ope'!H15*'Gainsay drivers · Gainsay fixed'!B8 -> 44.933818 | I18: ='Gainsay economics · Gainsay ope'!I15*'Gainsay drivers · Gainsay fixed'!B8 -> 52.028406 | J18: ='Gainsay economics · Gainsay ope'!J15*'Gainsay drivers · Gainsay fixed'!B8 -> 59.332287 | K18: ='Gainsay economics · Gainsay ope'!K15*'Gainsay drivers · Gainsay fixed'!B8 -> 66.860287 | L18: ='Gainsay economics · Gainsay ope'!L15*'Gainsay drivers · Gainsay fixed'!B8 -> 74.627847 | M18: ='Gainsay economics · Gainsay ope'!M15*'Gainsay drivers · Gainsay fixed'!B8 -> 82.651047 | N18: ='Gainsay economics · Gainsay ope'!N15*'Gainsay drivers · Gainsay fixed'!B8 -> 90.946654 | O18: ='Gainsay economics · Gainsay ope'!O15*'Gainsay drivers · Gainsay fixed'!B8 -> 99.532149 | P18: ='Gainsay economics · Gainsay ope'!P15*'Gainsay drivers · Gainsay fixed'!B8 -> 108.42577
A19: Free checks delivered | B19: =IF('Gainsay drivers · Gainsay fixed'!B11="","",'Gainsay drivers · Gainsay fixed'!B11) -> 20 | C19: =IF('Gainsay drivers · Gainsay fixed'!B11="","",'Gainsay drivers · Gainsay fixed'!B11) -> 20 | D19: =IF('Gainsay drivers · Gainsay fixed'!B11="","",'Gainsay drivers · Gainsay fixed'!B11) -> 20 | E19: =IF('Gainsay drivers · Gainsay fixed'!B11="","",'Gainsay drivers · Gainsay fixed'!B11) -> 20 | F19: =IF('Gainsay drivers · Gainsay fixed'!B11="","",'Gainsay drivers · Gainsay fixed'!B11) -> 20 | G19: =IF('Gainsay drivers · Gainsay fixed'!B11="","",'Gainsay drivers · Gainsay fixed'!B11) -> 20 | H19: =IF('Gainsay drivers · Gainsay fixed'!B11="","",'Gainsay drivers · Gainsay fixed'!B11) -> 20 | I19: =IF('Gainsay drivers · Gainsay fixed'!B11="","",'Gainsay drivers · Gainsay fixed'!B11) -> 20 | J19: =IF('Gainsay drivers · Gainsay fixed'!B11="","",'Gainsay drivers · Gainsay fixed'!B11) -> 20 | K19: =IF('Gainsay drivers · Gainsay fixed'!B11="","",'Gainsay drivers · Gainsay fixed'!B11) -> 20 | L19: =IF('Gainsay drivers · Gainsay fixed'!B11="","",'Gainsay drivers · Gainsay fixed'!B11) -> 20 | M19: =IF('Gainsay drivers · Gainsay fixed'!B11="","",'Gainsay drivers · Gainsay fixed'!B11) -> 20 | N19: =IF('Gainsay drivers · Gainsay fixed'!B11="","",'Gainsay drivers · Gainsay fixed'!B11) -> 20 | O19: =IF('Gainsay drivers · Gainsay fixed'!B11="","",'Gainsay drivers · Gainsay fixed'!B11) -> 20 | P19: =IF('Gainsay drivers · Gainsay fixed'!B11="","",'Gainsay drivers · Gainsay fixed'!B11) -> 20
A20: Paid citations checked | B20: =('Gainsay economics · Gainsay ope'!B18+'Gainsay economics · Gainsay ope'!B6)*'Gainsay drivers · Gainsay fixed'!B9 -> 560 | C20: =('Gainsay economics · Gainsay ope'!C18+'Gainsay economics · Gainsay ope'!C6)*'Gainsay drivers · Gainsay fixed'!B9 -> 791.7 | D20: =('Gainsay economics · Gainsay ope'!D18+'Gainsay economics · Gainsay ope'!D6)*'Gainsay drivers · Gainsay fixed'!B9 -> 1028.874 | E20: =('Gainsay economics · Gainsay ope'!E18+'Gainsay economics · Gainsay ope'!E6)*'Gainsay drivers · Gainsay fixed'!B9 -> 1271.979 | F20: =('Gainsay economics · Gainsay ope'!F18+'Gainsay economics · Gainsay ope'!F6)*'Gainsay drivers · Gainsay fixed'!B9 -> 1521.4895 | G20: =('Gainsay economics · Gainsay ope'!G18+'Gainsay economics · Gainsay ope'!G6)*'Gainsay drivers · Gainsay fixed'!B9 -> 1777.8981 | H20: =('Gainsay economics · Gainsay ope'!H18+'Gainsay economics · Gainsay ope'!H6)*'Gainsay drivers · Gainsay fixed'!B9 -> 2041.7171 | I20: =('Gainsay economics · Gainsay ope'!I18+'Gainsay economics · Gainsay ope'!I6)*'Gainsay drivers · Gainsay fixed'!B9 -> 2313.4794 | J20: =('Gainsay economics · Gainsay ope'!J18+'Gainsay economics · Gainsay ope'!J6)*'Gainsay drivers · Gainsay fixed'!B9 -> 2593.7394 | K20: =('Gainsay economics · Gainsay ope'!K18+'Gainsay economics · Gainsay ope'!K6)*'Gainsay drivers · Gainsay fixed'!B9 -> 2883.0749 | L20: =('Gainsay economics · Gainsay ope'!L18+'Gainsay economics · Gainsay ope'!L6)*'Gainsay drivers · Gainsay fixed'!B9 -> 3182.0878 | M20: =('Gainsay economics · Gainsay ope'!M18+'Gainsay economics · Gainsay ope'!M6)*'Gainsay drivers · Gainsay fixed'!B9 -> 3491.4054 | N20: =('Gainsay economics · Gainsay ope'!N18+'Gainsay economics · Gainsay ope'!N6)*'Gainsay drivers · Gainsay fixed'!B9 -> 3811.6826 | O20: =('Gainsay economics · Gainsay ope'!O18+'Gainsay economics · Gainsay ope'!O6)*'Gainsay drivers · Gainsay fixed'!B9 -> 4143.6024 | P20: =('Gainsay economics · Gainsay ope'!P18+'Gainsay economics · Gainsay ope'!P6)*'Gainsay drivers · Gainsay fixed'!B9 -> 4487.8782
A21: Free citations checked | B21: ='Gainsay economics · Gainsay ope'!B19*'Gainsay drivers · Gainsay fixed'!B10 -> 600 | C21: ='Gainsay economics · Gainsay ope'!C19*'Gainsay drivers · Gainsay fixed'!B10 -> 600 | D21: ='Gainsay economics · Gainsay ope'!D19*'Gainsay drivers · Gainsay fixed'!B10 -> 600 | E21: ='Gainsay economics · Gainsay ope'!E19*'Gainsay drivers · Gainsay fixed'!B10 -> 600 | F21: ='Gainsay economics · Gainsay ope'!F19*'Gainsay drivers · Gainsay fixed'!B10 -> 600 | G21: ='Gainsay economics · Gainsay ope'!G19*'Gainsay drivers · Gainsay fixed'!B10 -> 600 | H21: ='Gainsay economics · Gainsay ope'!H19*'Gainsay drivers · Gainsay fixed'!B10 -> 600 | I21: ='Gainsay economics · Gainsay ope'!I19*'Gainsay drivers · Gainsay fixed'!B10 -> 600 | J21: ='Gainsay economics · Gainsay ope'!J19*'Gainsay drivers · Gainsay fixed'!B10 -> 600 | K21: ='Gainsay economics · Gainsay ope'!K19*'Gainsay drivers · Gainsay fixed'!B10 -> 600 | L21: ='Gainsay economics · Gainsay ope'!L19*'Gainsay drivers · Gainsay fixed'!B10 -> 600 | M21: ='Gainsay economics · Gainsay ope'!M19*'Gainsay drivers · Gainsay fixed'!B10 -> 600 | N21: ='Gainsay economics · Gainsay ope'!N19*'Gainsay drivers · Gainsay fixed'!B10 -> 600 | O21: ='Gainsay economics · Gainsay ope'!O19*'Gainsay drivers · Gainsay fixed'!B10 -> 600 | P21: ='Gainsay economics · Gainsay ope'!P19*'Gainsay drivers · Gainsay fixed'!B10 -> 600
A22: Paid AI cost | B22: ='Gainsay economics · Gainsay ope'!B20*'Gainsay drivers · Gainsay fixed'!B5 -> 14.56 | C22: ='Gainsay economics · Gainsay ope'!C20*'Gainsay drivers · Gainsay fixed'!B5 -> 20.5842 | D22: ='Gainsay economics · Gainsay ope'!D20*'Gainsay drivers · Gainsay fixed'!B5 -> 26.750724 | E22: ='Gainsay economics · Gainsay ope'!E20*'Gainsay drivers · Gainsay fixed'!B5 -> 33.071455 | F22: ='Gainsay economics · Gainsay ope'!F20*'Gainsay drivers · Gainsay fixed'!B5 -> 39.558726 | G22: ='Gainsay economics · Gainsay ope'!G20*'Gainsay drivers · Gainsay fixed'!B5 -> 46.22535 | H22: ='Gainsay economics · Gainsay ope'!H20*'Gainsay drivers · Gainsay fixed'!B5 -> 53.084645 | I22: ='Gainsay economics · Gainsay ope'!I20*'Gainsay drivers · Gainsay fixed'!B5 -> 60.150464 | J22: ='Gainsay economics · Gainsay ope'!J20*'Gainsay drivers · Gainsay fixed'!B5 -> 67.437226 | K22: ='Gainsay economics · Gainsay ope'!K20*'Gainsay drivers · Gainsay fixed'!B5 -> 74.959948 | L22: ='Gainsay economics · Gainsay ope'!L20*'Gainsay drivers · Gainsay fixed'!B5 -> 82.734282 | M22: ='Gainsay economics · Gainsay ope'!M20*'Gainsay drivers · Gainsay fixed'!B5 -> 90.776541 | N22: ='Gainsay economics · Gainsay ope'!N20*'Gainsay drivers · Gainsay fixed'!B5 -> 99.103748 | O22: ='Gainsay economics · Gainsay ope'!O20*'Gainsay drivers · Gainsay fixed'!B5 -> 107.73366 | P22: ='Gainsay economics · Gainsay ope'!P20*'Gainsay drivers · Gainsay fixed'!B5 -> 116.68483
A23: Free AI cost | B23: ='Gainsay economics · Gainsay ope'!B21*'Gainsay drivers · Gainsay fixed'!B5 -> 15.6 | C23: ='Gainsay economics · Gainsay ope'!C21*'Gainsay drivers · Gainsay fixed'!B5 -> 15.6 | D23: ='Gainsay economics · Gainsay ope'!D21*'Gainsay drivers · Gainsay fixed'!B5 -> 15.6 | E23: ='Gainsay economics · Gainsay ope'!E21*'Gainsay drivers · Gainsay fixed'!B5 -> 15.6 | F23: ='Gainsay economics · Gainsay ope'!F21*'Gainsay drivers · Gainsay fixed'!B5 -> 15.6 | G23: ='Gainsay economics · Gainsay ope'!G21*'Gainsay drivers · Gainsay fixed'!B5 -> 15.6 | H23: ='Gainsay economics · Gainsay ope'!H21*'Gainsay drivers · Gainsay fixed'!B5 -> 15.6 | I23: ='Gainsay economics · Gainsay ope'!I21*'Gainsay drivers · Gainsay fixed'!B5 -> 15.6 | J23: ='Gainsay economics · Gainsay ope'!J21*'Gainsay drivers · Gainsay fixed'!B5 -> 15.6 | K23: ='Gainsay economics · Gainsay ope'!K21*'Gainsay drivers · Gainsay fixed'!B5 -> 15.6 | L23: ='Gainsay economics · Gainsay ope'!L21*'Gainsay drivers · Gainsay fixed'!B5 -> 15.6 | M23: ='Gainsay economics · Gainsay ope'!M21*'Gainsay drivers · Gainsay fixed'!B5 -> 15.6 | N23: ='Gainsay economics · Gainsay ope'!N21*'Gainsay drivers · Gainsay fixed'!B5 -> 15.6 | O23: ='Gainsay economics · Gainsay ope'!O21*'Gainsay drivers · Gainsay fixed'!B5 -> 15.6 | P23: ='Gainsay economics · Gainsay ope'!P21*'Gainsay drivers · Gainsay fixed'!B5 -> 15.6
A24: Payment fees | B24: ='Gainsay economics · Gainsay ope'!B7*'Gainsay drivers · Gainsay fixed'!B23+('Gainsay economics · Gainsay ope'!B15+'Gainsay economics · Gainsay ope'!B6)*'Gainsay drivers · Gainsay fixed'!B24 -> 9.033 | C24: ='Gainsay economics · Gainsay ope'!C7*'Gainsay drivers · Gainsay fixed'!B23+('Gainsay economics · Gainsay ope'!C15+'Gainsay economics · Gainsay ope'!C6)*'Gainsay drivers · Gainsay fixed'!B24 -> 12.80496 | D24: ='Gainsay economics · Gainsay ope'!D7*'Gainsay drivers · Gainsay fixed'!B23+('Gainsay economics · Gainsay ope'!D15+'Gainsay economics · Gainsay ope'!D6)*'Gainsay drivers · Gainsay fixed'!B24 -> 16.665909 | E24: ='Gainsay economics · Gainsay ope'!E7*'Gainsay drivers · Gainsay fixed'!B23+('Gainsay economics · Gainsay ope'!E15+'Gainsay economics · Gainsay ope'!E6)*'Gainsay drivers · Gainsay fixed'!B24 -> 20.623284 | F24: ='Gainsay economics · Gainsay ope'!F7*'Gainsay drivers · Gainsay fixed'!B23+('Gainsay economics · Gainsay ope'!F15+'Gainsay economics · Gainsay ope'!F6)*'Gainsay drivers · Gainsay fixed'!B24 -> 24.684805 | G24: ='Gainsay economics · Gainsay ope'!G7*'Gainsay drivers · Gainsay fixed'!B23+('Gainsay economics · Gainsay ope'!G15+'Gainsay economics · Gainsay ope'!G6)*'Gainsay drivers · Gainsay fixed'!B24 -> 28.858492 | H24: ='Gainsay economics · Gainsay ope'!H7*'Gainsay drivers · Gainsay fixed'!B23+('Gainsay economics · Gainsay ope'!H15+'Gainsay economics · Gainsay ope'!H6)*'Gainsay drivers · Gainsay fixed'!B24 -> 33.15268 | I24: ='Gainsay economics · Gainsay ope'!I7*'Gainsay drivers · Gainsay fixed'!B23+('Gainsay economics · Gainsay ope'!I15+'Gainsay economics · Gainsay ope'!I6)*'Gainsay drivers · Gainsay fixed'!B24 -> 37.576039 | J24: ='Gainsay economics · Gainsay ope'!J7*'Gainsay drivers · Gainsay fixed'!B23+('Gainsay economics · Gainsay ope'!J15+'Gainsay economics · Gainsay ope'!J6)*'Gainsay drivers · Gainsay fixed'!B24 -> 42.137595 | K24: ='Gainsay economics · Gainsay ope'!K7*'Gainsay drivers · Gainsay fixed'!B23+('Gainsay economics · Gainsay ope'!K15+'Gainsay economics · Gainsay ope'!K6)*'Gainsay drivers · Gainsay fixed'!B24 -> 46.846745 | L24: ='Gainsay economics · Gainsay ope'!L7*'Gainsay drivers · Gainsay fixed'!B23+('Gainsay economics · Gainsay ope'!L15+'Gainsay economics · Gainsay ope'!L6)*'Gainsay drivers · Gainsay fixed'!B24 -> 51.713285 | M24: ='Gainsay economics · Gainsay ope'!M7*'Gainsay drivers · Gainsay fixed'!B23+('Gainsay economics · Gainsay ope'!M15+'Gainsay economics · Gainsay ope'!M6)*'Gainsay drivers · Gainsay fixed'!B24 -> 56.747426 | N24: ='Gainsay economics · Gainsay ope'!N7*'Gainsay drivers · Gainsay fixed'!B23+('Gainsay economics · Gainsay ope'!N15+'Gainsay economics · Gainsay ope'!N6)*'Gainsay drivers · Gainsay fixed'!B24 -> 61.95982 | O24: ='Gainsay economics · Gainsay ope'!O7*'Gainsay drivers · Gainsay fixed'!B23+('Gainsay economics · Gainsay ope'!O15+'Gainsay economics · Gainsay ope'!O6)*'Gainsay drivers · Gainsay fixed'!B24 -> 67.361583 | P24: ='Gainsay economics · Gainsay ope'!P7*'Gainsay drivers · Gainsay fixed'!B23+('Gainsay economics · Gainsay ope'!P15+'Gainsay economics · Gainsay ope'!P6)*'Gainsay drivers · Gainsay fixed'!B24 -> 72.96432
A25: Data expense | B25: ='Gainsay drivers · Gainsay fixed'!B20/12 -> 250 | C25: ='Gainsay drivers · Gainsay fixed'!B20/12 -> 250 | D25: ='Gainsay drivers · Gainsay fixed'!B20/12 -> 250 | E25: ='Gainsay drivers · Gainsay fixed'!B20/12 -> 250 | F25: ='Gainsay drivers · Gainsay fixed'!B20/12 -> 250 | G25: ='Gainsay drivers · Gainsay fixed'!B20/12 -> 250 | H25: ='Gainsay drivers · Gainsay fixed'!B20/12 -> 250 | I25: ='Gainsay drivers · Gainsay fixed'!B20/12 -> 250 | J25: ='Gainsay drivers · Gainsay fixed'!B20/12 -> 250 | K25: ='Gainsay drivers · Gainsay fixed'!B20/12 -> 250 | L25: ='Gainsay drivers · Gainsay fixed'!B20/12 -> 250 | M25: ='Gainsay drivers · Gainsay fixed'!B20/12 -> 250 | N25: ='Gainsay drivers · Gainsay fixed'!B20/12 -> 250 | O25: ='Gainsay drivers · Gainsay fixed'!B20/12 -> 250 | P25: ='Gainsay drivers · Gainsay fixed'!B20/12 -> 250
A26: Gross profit | B26: ='Gainsay economics · Gainsay ope'!B7-'Gainsay economics · Gainsay ope'!B22-'Gainsay economics · Gainsay ope'!B23-'Gainsay economics · Gainsay ope'!B24-'Gainsay drivers · Gainsay fixed'!B15-'Gainsay economics · Gainsay ope'!B25 -> -127.193 | C26: ='Gainsay economics · Gainsay ope'!C7-'Gainsay economics · Gainsay ope'!C22-'Gainsay economics · Gainsay ope'!C23-'Gainsay economics · Gainsay ope'!C24-'Gainsay drivers · Gainsay fixed'!B15-'Gainsay economics · Gainsay ope'!C25 -> -43.74916 | D26: ='Gainsay economics · Gainsay ope'!D7-'Gainsay economics · Gainsay ope'!D22-'Gainsay economics · Gainsay ope'!D23-'Gainsay economics · Gainsay ope'!D24-'Gainsay drivers · Gainsay fixed'!B15-'Gainsay economics · Gainsay ope'!D25 -> 41.593667 | E26: ='Gainsay economics · Gainsay ope'!E7-'Gainsay economics · Gainsay ope'!E22-'Gainsay economics · Gainsay ope'!E23-'Gainsay economics · Gainsay ope'!E24-'Gainsay drivers · Gainsay fixed'!B15-'Gainsay economics · Gainsay ope'!E25 -> 128.99863 | F26: ='Gainsay economics · Gainsay ope'!F7-'Gainsay economics · Gainsay ope'!F22-'Gainsay economics · Gainsay ope'!F23-'Gainsay economics · Gainsay ope'!F24-'Gainsay drivers · Gainsay fixed'!B15-'Gainsay economics · Gainsay ope'!F25 -> 218.63498 | G26: ='Gainsay economics · Gainsay ope'!G7-'Gainsay economics · Gainsay ope'!G22-'Gainsay economics · Gainsay ope'!G23-'Gainsay economics · Gainsay ope'!G24-'Gainsay drivers · Gainsay fixed'!B15-'Gainsay economics · Gainsay ope'!G25 -> 310.67845 | H26: ='Gainsay economics · Gainsay ope'!H7-'Gainsay economics · Gainsay ope'!H22-'Gainsay economics · Gainsay ope'!H23-'Gainsay economics · Gainsay ope'!H24-'Gainsay drivers · Gainsay fixed'!B15-'Gainsay economics · Gainsay ope'!H25 -> 405.31165 | I26: ='Gainsay economics · Gainsay ope'!I7-'Gainsay economics · Gainsay ope'!I22-'Gainsay economics · Gainsay ope'!I23-'Gainsay economics · Gainsay ope'!I24-'Gainsay drivers · Gainsay fixed'!B15-'Gainsay economics · Gainsay ope'!I25 -> 502.72443 | J26: ='Gainsay economics · Gainsay ope'!J7-'Gainsay economics · Gainsay ope'!J22-'Gainsay economics · Gainsay ope'!J23-'Gainsay economics · Gainsay ope'!J24-'Gainsay drivers · Gainsay fixed'!B15-'Gainsay economics · Gainsay ope'!J25 -> 603.11433 | K26: ='Gainsay economics · Gainsay ope'!K7-'Gainsay economics · Gainsay ope'!K22-'Gainsay economics · Gainsay ope'!K23-'Gainsay economics · Gainsay ope'!K24-'Gainsay drivers · Gainsay fixed'!B15-'Gainsay economics · Gainsay ope'!K25 -> 706.68701 | L26: ='Gainsay economics · Gainsay ope'!L7-'Gainsay economics · Gainsay ope'!L22-'Gainsay economics · Gainsay ope'!L23-'Gainsay economics · Gainsay ope'!L24-'Gainsay drivers · Gainsay fixed'!B15-'Gainsay economics · Gainsay ope'!L25 -> 813.65673 | M26: ='Gainsay economics · Gainsay ope'!M7-'Gainsay economics · Gainsay ope'!M22-'Gainsay economics · Gainsay ope'!M23-'Gainsay economics · Gainsay ope'!M24-'Gainsay drivers · Gainsay fixed'!B15-'Gainsay economics · Gainsay ope'!M25 -> 924.24676 | N26: ='Gainsay economics · Gainsay ope'!N7-'Gainsay economics · Gainsay ope'!N22-'Gainsay economics · Gainsay ope'!N23-'Gainsay economics · Gainsay ope'!N24-'Gainsay drivers · Gainsay fixed'!B15-'Gainsay economics · Gainsay ope'!N25 -> 1038.69 | O26: ='Gainsay economics · Gainsay ope'!O7-'Gainsay economics · Gainsay ope'!O22-'Gainsay economics · Gainsay ope'!O23-'Gainsay economics · Gainsay ope'!O24-'Gainsay drivers · Gainsay fixed'!B15-'Gainsay economics · Gainsay ope'!O25 -> 1157.2293 | P26: ='Gainsay economics · Gainsay ope'!P7-'Gainsay economics · Gainsay ope'!P22-'Gainsay economics · Gainsay ope'!P23-'Gainsay economics · Gainsay ope'!P24-'Gainsay drivers · Gainsay fixed'!B15-'Gainsay economics · Gainsay ope'!P25 -> 1280.1184
A27: Contractor support cost | B27: =IF(IF(IF(ISERROR('Gainsay economics · Gainsay ope'!B15>='Gainsay drivers · Gainsay fixed'!B27),'Gainsay economics · Gainsay ope'!B15>='Gainsay drivers · Gainsay fixed'!B27,IF(OR('Gainsay economics · Gainsay ope'!B15="",'Gainsay drivers · Gainsay fixed'!B27=""),"",'Gainsay economics · Gainsay ope'!B15>='Gainsay drivers · Gainsay fixed'!B27))="",FALSE(),IF(ISERROR('Gainsay economics · Gainsay ope'!B15>='Gainsay drivers · Gainsay fixed'!B27),'Gainsay economics · Gainsay ope'!B15>='Gainsay drivers · Gainsay fixed'!B27,IF(OR('Gainsay economics · Gainsay ope'!B15="",'Gainsay drivers · Gainsay fixed'!B27=""),"",'Gainsay economics · Gainsay ope'!B15>='Gainsay drivers · Gainsay fixed'!B27))),IF('Gainsay drivers · Gainsay fixed'!B28="","",'Gainsay drivers · Gainsay fixed'!B28),0) -> 0 | C27: =IF(IF(IF(ISERROR('Gainsay economics · Gainsay ope'!C15>='Gainsay drivers · Gainsay fixed'!B27),'Gainsay economics · Gainsay ope'!C15>='Gainsay drivers · Gainsay fixed'!B27,IF(OR('Gainsay economics · Gainsay ope'!C15="",'Gainsay drivers · Gainsay fixed'!B27=""),"",'Gainsay economics · Gainsay ope'!C15>='Gainsay drivers · Gainsay fixed'!B27))="",FALSE(),IF(ISERROR('Gainsay economics · Gainsay ope'!C15>='Gainsay drivers · Gainsay fixed'!B27),'Gainsay economics · Gainsay ope'!C15>='Gainsay drivers · Gainsay fixed'!B27,IF(OR('Gainsay economics · Gainsay ope'!C15="",'Gainsay drivers · Gainsay fixed'!B27=""),"",'Gainsay economics · Gainsay ope'!C15>='Gainsay drivers · Gainsay fixed'!B27))),IF('Gainsay drivers · Gainsay fixed'!B28="","",'Gainsay drivers · Gainsay fixed'!B28),0) -> 0 | D27: =IF(IF(IF(ISERROR('Gainsay economics · Gainsay ope'!D15>='Gainsay drivers · Gainsay fixed'!B27),'Gainsay economics · Gainsay ope'!D15>='Gainsay drivers · Gainsay fixed'!B27,IF(OR('Gainsay economics · Gainsay ope'!D15="",'Gainsay drivers · Gainsay fixed'!B27=""),"",'Gainsay economics · Gainsay ope'!D15>='Gainsay drivers · Gainsay fixed'!B27))="",FALSE(),IF(ISERROR('Gainsay economics · Gainsay ope'!D15>='Gainsay drivers · Gainsay fixed'!B27),'Gainsay economics · Gainsay ope'!D15>='Gainsay drivers · Gainsay fixed'!B27,IF(OR('Gainsay economics · Gainsay ope'!D15="",'Gainsay drivers · Gainsay fixed'!B27=""),"",'Gainsay economics · Gainsay ope'!D15>='Gainsay drivers · Gainsay fixed'!B27))),IF('Gainsay drivers · Gainsay fixed'!B28="","",'Gainsay drivers · Gainsay fixed'!B28),0) -> 0 | E27: =IF(IF(IF(ISERROR('Gainsay economics · Gainsay ope'!E15>='Gainsay drivers · Gainsay fixed'!B27),'Gainsay economics · Gainsay ope'!E15>='Gainsay drivers · Gainsay fixed'!B27,IF(OR('Gainsay economics · Gainsay ope'!E15="",'Gainsay drivers · Gainsay fixed'!B27=""),"",'Gainsay economics · Gainsay ope'!E15>='Gainsay drivers · Gainsay fixed'!B27))="",FALSE(),IF(ISERROR('Gainsay economics · Gainsay ope'!E15>='Gainsay drivers · Gainsay fixed'!B27),'Gainsay economics · Gainsay ope'!E15>='Gainsay drivers · Gainsay fixed'!B27,IF(OR('Gainsay economics · Gainsay ope'!E15="",'Gainsay drivers · Gainsay fixed'!B27=""),"",'Gainsay economics · Gainsay ope'!E15>='Gainsay drivers · Gainsay fixed'!B27))),IF('Gainsay drivers · Gainsay fixed'!B28="","",'Gainsay drivers · Gainsay fixed'!B28),0) -> 0 | F27: =IF(IF(IF(ISERROR('Gainsay economics · Gainsay ope'!F15>='Gainsay drivers · Gainsay fixed'!B27),'Gainsay economics · Gainsay ope'!F15>='Gainsay drivers · Gainsay fixed'!B27,IF(OR('Gainsay economics · Gainsay ope'!F15="",'Gainsay drivers · Gainsay fixed'!B27=""),"",'Gainsay economics · Gainsay ope'!F15>='Gainsay drivers · Gainsay fixed'!B27))="",FALSE(),IF(ISERROR('Gainsay economics · Gainsay ope'!F15>='Gainsay drivers · Gainsay fixed'!B27),'Gainsay economics · Gainsay ope'!F15>='Gainsay drivers · Gainsay fixed'!B27,IF(OR('Gainsay economics · Gainsay ope'!F15="",'Gainsay drivers · Gainsay fixed'!B27=""),"",'Gainsay economics · Gainsay ope'!F15>='Gainsay drivers · Gainsay fixed'!B27))),IF('Gainsay drivers · Gainsay fixed'!B28="","",'Gainsay drivers · Gainsay fixed'!B28),0) -> 0 | G27: =IF(IF(IF(ISERROR('Gainsay economics · Gainsay ope'!G15>='Gainsay drivers · Gainsay fixed'!B27),'Gainsay economics · Gainsay ope'!G15>='Gainsay drivers · Gainsay fixed'!B27,IF(OR('Gainsay economics · Gainsay ope'!G15="",'Gainsay drivers · Gainsay fixed'!B27=""),"",'Gainsay economics · Gainsay ope'!G15>='Gainsay drivers · Gainsay fixed'!B27))="",FALSE(),IF(ISERROR('Gainsay economics · Gainsay ope'!G15>='Gainsay drivers · Gainsay fixed'!B27),'Gainsay economics · Gainsay ope'!G15>='Gainsay drivers · Gainsay fixed'!B27,IF(OR('Gainsay economics · Gainsay ope'!G15="",'Gainsay drivers · Gainsay fixed'!B27=""),"",'Gainsay economics · Gainsay ope'!G15>='Gainsay drivers · Gainsay fixed'!B27))),IF('Gainsay drivers · Gainsay fixed'!B28="","",'Gainsay drivers · Gainsay fixed'!B28),0) -> 0 | H27: =IF(IF(IF(ISERROR('Gainsay economics · Gainsay ope'!H15>='Gainsay drivers · Gainsay fixed'!B27),'Gainsay economics · Gainsay ope'!H15>='Gainsay drivers · Gainsay fixed'!B27,IF(OR('Gainsay economics · Gainsay ope'!H15="",'Gainsay drivers · Gainsay fixed'!B27=""),"",'Gainsay economics · Gainsay ope'!H15>='Gainsay drivers · Gainsay fixed'!B27))="",FALSE(),IF(ISERROR('Gainsay economics · Gainsay ope'!H15>='Gainsay drivers · Gainsay fixed'!B27),'Gainsay economics · Gainsay ope'!H15>='Gainsay drivers · Gainsay fixed'!B27,IF(OR('Gainsay economics · Gainsay ope'!H15="",'Gainsay drivers · Gainsay fixed'!B27=""),"",'Gainsay economics · Gainsay ope'!H15>='Gainsay drivers · Gainsay fixed'!B27))),IF('Gainsay drivers · Gainsay fixed'!B28="","",'Gainsay drivers · Gainsay fixed'!B28),0) -> 0 | I27: =IF(IF(IF(ISERROR('Gainsay economics · Gainsay ope'!I15>='Gainsay drivers · Gainsay fixed'!B27),'Gainsay economics · Gainsay ope'!I15>='Gainsay drivers · Gainsay fixed'!B27,IF(OR('Gainsay economics · Gainsay ope'!I15="",'Gainsay drivers · Gainsay fixed'!B27=""),"",'Gainsay economics · Gainsay ope'!I15>='Gainsay drivers · Gainsay fixed'!B27))="",FALSE(),IF(ISERROR('Gainsay economics · Gainsay ope'!I15>='Gainsay drivers · Gainsay fixed'!B27),'Gainsay economics · Gainsay ope'!I15>='Gainsay drivers · Gainsay fixed'!B27,IF(OR('Gainsay economics · Gainsay ope'!I15="",'Gainsay drivers · Gainsay fixed'!B27=""),"",'Gainsay economics · Gainsay ope'!I15>='Gainsay drivers · Gainsay fixed'!B27))),IF('Gainsay drivers · Gainsay fixed'!B28="","",'Gainsay drivers · Gainsay fixed'!B28),0) -> 0 | J27: =IF(IF(IF(ISERROR('Gainsay economics · Gainsay ope'!J15>='Gainsay drivers · Gainsay fixed'!B27),'Gainsay economics · Gainsay ope'!J15>='Gainsay drivers · Gainsay fixed'!B27,IF(OR('Gainsay economics · Gainsay ope'!J15="",'Gainsay drivers · Gainsay fixed'!B27=""),"",'Gainsay economics · Gainsay ope'!J15>='Gainsay drivers · Gainsay fixed'!B27))="",FALSE(),IF(ISERROR('Gainsay economics · Gainsay ope'!J15>='Gainsay drivers · Gainsay fixed'!B27),'Gainsay economics · Gainsay ope'!J15>='Gainsay drivers · Gainsay fixed'!B27,IF(OR('Gainsay economics · Gainsay ope'!J15="",'Gainsay drivers · Gainsay fixed'!B27=""),"",'Gainsay economics · Gainsay ope'!J15>='Gainsay drivers · Gainsay fixed'!B27))),IF('Gainsay drivers · Gainsay fixed'!B28="","",'Gainsay drivers · Gainsay fixed'!B28),0) -> 0 | K27: =IF(IF(IF(ISERROR('Gainsay economics · Gainsay ope'!K15>='Gainsay drivers · Gainsay fixed'!B27),'Gainsay economics · Gainsay ope'!K15>='Gainsay drivers · Gainsay fixed'!B27,IF(OR('Gainsay economics · Gainsay ope'!K15="",'Gainsay drivers · Gainsay fixed'!B27=""),"",'Gainsay economics · Gainsay ope'!K15>='Gainsay drivers · Gainsay fixed'!B27))="",FALSE(),IF(ISERROR('Gainsay economics · Gainsay ope'!K15>='Gainsay drivers · Gainsay fixed'!B27),'Gainsay economics · Gainsay ope'!K15>='Gainsay drivers · Gainsay fixed'!B27,IF(OR('Gainsay economics · Gainsay ope'!K15="",'Gainsay drivers · Gainsay fixed'!B27=""),"",'Gainsay economics · Gainsay ope'!K15>='Gainsay drivers · Gainsay fixed'!B27))),IF('Gainsay drivers · Gainsay fixed'!B28="","",'Gainsay drivers · Gainsay fixed'!B28),0) -> 0 | L27: =IF(IF(IF(ISERROR('Gainsay economics · Gainsay ope'!L15>='Gainsay drivers · Gainsay fixed'!B27),'Gainsay economics · Gainsay ope'!L15>='Gainsay drivers · Gainsay fixed'!B27,IF(OR('Gainsay economics · Gainsay ope'!L15="",'Gainsay drivers · Gainsay fixed'!B27=""),"",'Gainsay economics · Gainsay ope'!L15>='Gainsay drivers · Gainsay fixed'!B27))="",FALSE(),IF(ISERROR('Gainsay economics · Gainsay ope'!L15>='Gainsay drivers · Gainsay fixed'!B27),'Gainsay economics · Gainsay ope'!L15>='Gainsay drivers · Gainsay fixed'!B27,IF(OR('Gainsay economics · Gainsay ope'!L15="",'Gainsay drivers · Gainsay fixed'!B27=""),"",'Gainsay economics · Gainsay ope'!L15>='Gainsay drivers · Gainsay fixed'!B27))),IF('Gainsay drivers · Gainsay fixed'!B28="","",'Gainsay drivers · Gainsay fixed'!B28),0) -> 0 | M27: =IF(IF(IF(ISERROR('Gainsay economics · Gainsay ope'!M15>='Gainsay drivers · Gainsay fixed'!B27),'Gainsay economics · Gainsay ope'!M15>='Gainsay drivers · Gainsay fixed'!B27,IF(OR('Gainsay economics · Gainsay ope'!M15="",'Gainsay drivers · Gainsay fixed'!B27=""),"",'Gainsay economics · Gainsay ope'!M15>='Gainsay drivers · Gainsay fixed'!B27))="",FALSE(),IF(ISERROR('Gainsay economics · Gainsay ope'!M15>='Gainsay drivers · Gainsay fixed'!B27),'Gainsay economics · Gainsay ope'!M15>='Gainsay drivers · Gainsay fixed'!B27,IF(OR('Gainsay economics · Gainsay ope'!M15="",'Gainsay drivers · Gainsay fixed'!B27=""),"",'Gainsay economics · Gainsay ope'!M15>='Gainsay drivers · Gainsay fixed'!B27))),IF('Gainsay drivers · Gainsay fixed'!B28="","",'Gainsay drivers · Gainsay fixed'!B28),0) -> 0 | N27: =IF(IF(IF(ISERROR('Gainsay economics · Gainsay ope'!N15>='Gainsay drivers · Gainsay fixed'!B27),'Gainsay economics · Gainsay ope'!N15>='Gainsay drivers · Gainsay fixed'!B27,IF(OR('Gainsay economics · Gainsay ope'!N15="",'Gainsay drivers · Gainsay fixed'!B27=""),"",'Gainsay economics · Gainsay ope'!N15>='Gainsay drivers · Gainsay fixed'!B27))="",FALSE(),IF(ISERROR('Gainsay economics · Gainsay ope'!N15>='Gainsay drivers · Gainsay fixed'!B27),'Gainsay economics · Gainsay ope'!N15>='Gainsay drivers · Gainsay fixed'!B27,IF(OR('Gainsay economics · Gainsay ope'!N15="",'Gainsay drivers · Gainsay fixed'!B27=""),"",'Gainsay economics · Gainsay ope'!N15>='Gainsay drivers · Gainsay fixed'!B27))),IF('Gainsay drivers · Gainsay fixed'!B28="","",'Gainsay drivers · Gainsay fixed'!B28),0) -> 0 | O27: =IF(IF(IF(ISERROR('Gainsay economics · Gainsay ope'!O15>='Gainsay drivers · Gainsay fixed'!B27),'Gainsay economics · Gainsay ope'!O15>='Gainsay drivers · Gainsay fixed'!B27,IF(OR('Gainsay economics · Gainsay ope'!O15="",'Gainsay drivers · Gainsay fixed'!B27=""),"",'Gainsay economics · Gainsay ope'!O15>='Gainsay drivers · Gainsay fixed'!B27))="",FALSE(),IF(ISERROR('Gainsay economics · Gainsay ope'!O15>='Gainsay drivers · Gainsay fixed'!B27),'Gainsay economics · Gainsay ope'!O15>='Gainsay drivers · Gainsay fixed'!B27,IF(OR('Gainsay economics · Gainsay ope'!O15="",'Gainsay drivers · Gainsay fixed'!B27=""),"",'Gainsay economics · Gainsay ope'!O15>='Gainsay drivers · Gainsay fixed'!B27))),IF('Gainsay drivers · Gainsay fixed'!B28="","",'Gainsay drivers · Gainsay fixed'!B28),0) -> 0 | P27: =IF(IF(IF(ISERROR('Gainsay economics · Gainsay ope'!P15>='Gainsay drivers · Gainsay fixed'!B27),'Gainsay economics · Gainsay ope'!P15>='Gainsay drivers · Gainsay fixed'!B27,IF(OR('Gainsay economics · Gainsay ope'!P15="",'Gainsay drivers · Gainsay fixed'!B27=""),"",'Gainsay economics · Gainsay ope'!P15>='Gainsay drivers · Gainsay fixed'!B27))="",FALSE(),IF(ISERROR('Gainsay economics · Gainsay ope'!P15>='Gainsay drivers · Gainsay fixed'!B27),'Gainsay economics · Gainsay ope'!P15>='Gainsay drivers · Gainsay fixed'!B27,IF(OR('Gainsay economics · Gainsay ope'!P15="",'Gainsay drivers · Gainsay fixed'!B27=""),"",'Gainsay economics · Gainsay ope'!P15>='Gainsay drivers · Gainsay fixed'!B27))),IF('Gainsay drivers · Gainsay fixed'!B28="","",'Gainsay drivers · Gainsay fixed'!B28),0) -> 400
A28: Operating expense | B28: ='Gainsay drivers · Gainsay fixed'!B16+'Gainsay drivers · Gainsay fixed'!B17+'Gainsay drivers · Gainsay fixed'!B18+'Gainsay economics · Gainsay ope'!B27+'Gainsay economics · Gainsay ope'!B49+IF(IF(DATE(2026,10,1)=DATE(2026,10,1),IF('Gainsay drivers · Gainsay fixed'!B22="","",'Gainsay drivers · Gainsay fixed'!B22),0)="",0,IF(DATE(2026,10,1)=DATE(2026,10,1),IF('Gainsay drivers · Gainsay fixed'!B22="","",'Gainsay drivers · Gainsay fixed'!B22),0)) -> 730 | C28: ='Gainsay drivers · Gainsay fixed'!B16+'Gainsay drivers · Gainsay fixed'!B17+'Gainsay drivers · Gainsay fixed'!B18+'Gainsay economics · Gainsay ope'!C27+'Gainsay economics · Gainsay ope'!C49+IF(IF(DATE(2026,11,1)=DATE(2026,10,1),IF('Gainsay drivers · Gainsay fixed'!B22="","",'Gainsay drivers · Gainsay fixed'!B22),0)="",0,IF(DATE(2026,11,1)=DATE(2026,10,1),IF('Gainsay drivers · Gainsay fixed'!B22="","",'Gainsay drivers · Gainsay fixed'!B22),0)) -> 230 | D28: ='Gainsay drivers · Gainsay fixed'!B16+'Gainsay drivers · Gainsay fixed'!B17+'Gainsay drivers · Gainsay fixed'!B18+'Gainsay economics · Gainsay ope'!D27+'Gainsay economics · Gainsay ope'!D49+IF(IF(DATE(2026,12,1)=DATE(2026,10,1),IF('Gainsay drivers · Gainsay fixed'!B22="","",'Gainsay drivers · Gainsay fixed'!B22),0)="",0,IF(DATE(2026,12,1)=DATE(2026,10,1),IF('Gainsay drivers · Gainsay fixed'!B22="","",'Gainsay drivers · Gainsay fixed'!B22),0)) -> 230 | E28: ='Gainsay drivers · Gainsay fixed'!B16+'Gainsay drivers · Gainsay fixed'!B17+'Gainsay drivers · Gainsay fixed'!B18+'Gainsay economics · Gainsay ope'!E27+'Gainsay economics · Gainsay ope'!E49+IF(IF(DATE(2027,1,1)=DATE(2026,10,1),IF('Gainsay drivers · Gainsay fixed'!B22="","",'Gainsay drivers · Gainsay fixed'!B22),0)="",0,IF(DATE(2027,1,1)=DATE(2026,10,1),IF('Gainsay drivers · Gainsay fixed'!B22="","",'Gainsay drivers · Gainsay fixed'!B22),0)) -> 230 | F28: ='Gainsay drivers · Gainsay fixed'!B16+'Gainsay drivers · Gainsay fixed'!B17+'Gainsay drivers · Gainsay fixed'!B18+'Gainsay economics · Gainsay ope'!F27+'Gainsay economics · Gainsay ope'!F49+IF(IF(DATE(2027,2,1)=DATE(2026,10,1),IF('Gainsay drivers · Gainsay fixed'!B22="","",'Gainsay drivers · Gainsay fixed'!B22),0)="",0,IF(DATE(2027,2,1)=DATE(2026,10,1),IF('Gainsay drivers · Gainsay fixed'!B22="","",'Gainsay drivers · Gainsay fixed'!B22),0)) -> 230 | G28: ='Gainsay drivers · Gainsay fixed'!B16+'Gainsay drivers · Gainsay fixed'!B17+'Gainsay drivers · Gainsay fixed'!B18+'Gainsay economics · Gainsay ope'!G27+'Gainsay economics · Gainsay ope'!G49+IF(IF(DATE(2027,3,1)=DATE(2026,10,1),IF('Gainsay drivers · Gainsay fixed'!B22="","",'Gainsay drivers · Gainsay fixed'!B22),0)="",0,IF(DATE(2027,3,1)=DATE(2026,10,1),IF('Gainsay drivers · Gainsay fixed'!B22="","",'Gainsay drivers · Gainsay fixed'!B22),0)) -> 230 | H28: ='Gainsay drivers · Gainsay fixed'!B16+'Gainsay drivers · Gainsay fixed'!B17+'Gainsay drivers · Gainsay fixed'!B18+'Gainsay economics · Gainsay ope'!H27+'Gainsay economics · Gainsay ope'!H49+IF(IF(DATE(2027,4,1)=DATE(2026,10,1),IF('Gainsay drivers · Gainsay fixed'!B22="","",'Gainsay drivers · Gainsay fixed'!B22),0)="",0,IF(DATE(2027,4,1)=DATE(2026,10,1),IF('Gainsay drivers · Gainsay fixed'!B22="","",'Gainsay drivers · Gainsay fixed'!B22),0)) -> 230 | I28: ='Gainsay drivers · Gainsay fixed'!B16+'Gainsay drivers · Gainsay fixed'!B17+'Gainsay drivers · Gainsay fixed'!B18+'Gainsay economics · Gainsay ope'!I27+'Gainsay economics · Gainsay ope'!I49+IF(IF(DATE(2027,5,1)=DATE(2026,10,1),IF('Gainsay drivers · Gainsay fixed'!B22="","",'Gainsay drivers · Gainsay fixed'!B22),0)="",0,IF(DATE(2027,5,1)=DATE(2026,10,1),IF('Gainsay drivers · Gainsay fixed'!B22="","",'Gainsay drivers · Gainsay fixed'!B22),0)) -> 230 | J28: ='Gainsay drivers · Gainsay fixed'!B16+'Gainsay drivers · Gainsay fixed'!B17+'Gainsay drivers · Gainsay fixed'!B18+'Gainsay economics · Gainsay ope'!J27+'Gainsay economics · Gainsay ope'!J49+IF(IF(DATE(2027,6,1)=DATE(2026,10,1),IF('Gainsay drivers · Gainsay fixed'!B22="","",'Gainsay drivers · Gainsay fixed'!B22),0)="",0,IF(DATE(2027,6,1)=DATE(2026,10,1),IF('Gainsay drivers · Gainsay fixed'!B22="","",'Gainsay drivers · Gainsay fixed'!B22),0)) -> 230 | K28: ='Gainsay drivers · Gainsay fixed'!B16+'Gainsay drivers · Gainsay fixed'!B17+'Gainsay drivers · Gainsay fixed'!B18+'Gainsay economics · Gainsay ope'!K27+'Gainsay economics · Gainsay ope'!K49+IF(IF(DATE(2027,7,1)=DATE(2026,10,1),IF('Gainsay drivers · Gainsay fixed'!B22="","",'Gainsay drivers · Gainsay fixed'!B22),0)="",0,IF(DATE(2027,7,1)=DATE(2026,10,1),IF('Gainsay drivers · Gainsay fixed'!B22="","",'Gainsay drivers · Gainsay fixed'!B22),0)) -> 230 | L28: ='Gainsay drivers · Gainsay fixed'!B16+'Gainsay drivers · Gainsay fixed'!B17+'Gainsay drivers · Gainsay fixed'!B18+'Gainsay economics · Gainsay ope'!L27+'Gainsay economics · Gainsay ope'!L49+IF(IF(DATE(2027,8,1)=DATE(2026,10,1),IF('Gainsay drivers · Gainsay fixed'!B22="","",'Gainsay drivers · Gainsay fixed'!B22),0)="",0,IF(DATE(2027,8,1)=DATE(2026,10,1),IF('Gainsay drivers · Gainsay fixed'!B22="","",'Gainsay drivers · Gainsay fixed'!B22),0)) -> 230 | M28: ='Gainsay drivers · Gainsay fixed'!B16+'Gainsay drivers · Gainsay fixed'!B17+'Gainsay drivers · Gainsay fixed'!B18+'Gainsay economics · Gainsay ope'!M27+'Gainsay economics · Gainsay ope'!M49+IF(IF(DATE(2027,9,1)=DATE(2026,10,1),IF('Gainsay drivers · Gainsay fixed'!B22="","",'Gainsay drivers · Gainsay fixed'!B22),0)="",0,IF(DATE(2027,9,1)=DATE(2026,10,1),IF('Gainsay drivers · Gainsay fixed'!B22="","",'Gainsay drivers · Gainsay fixed'!B22),0)) -> 230 | N28: ='Gainsay drivers · Gainsay fixed'!B16+'Gainsay drivers · Gainsay fixed'!B17+'Gainsay drivers · Gainsay fixed'!B18+'Gainsay economics · Gainsay ope'!N27+'Gainsay economics · Gainsay ope'!N49+IF(IF(DATE(2027,10,1)=DATE(2026,10,1),IF('Gainsay drivers · Gainsay fixed'!B22="","",'Gainsay drivers · Gainsay fixed'!B22),0)="",0,IF(DATE(2027,10,1)=DATE(2026,10,1),IF('Gainsay drivers · Gainsay fixed'!B22="","",'Gainsay drivers · Gainsay fixed'!B22),0)) -> 230 | O28: ='Gainsay drivers · Gainsay fixed'!B16+'Gainsay drivers · Gainsay fixed'!B17+'Gainsay drivers · Gainsay fixed'!B18+'Gainsay economics · Gainsay ope'!O27+'Gainsay economics · Gainsay ope'!O49+IF(IF(DATE(2027,11,1)=DATE(2026,10,1),IF('Gainsay drivers · Gainsay fixed'!B22="","",'Gainsay drivers · Gainsay fixed'!B22),0)="",0,IF(DATE(2027,11,1)=DATE(2026,10,1),IF('Gainsay drivers · Gainsay fixed'!B22="","",'Gainsay drivers · Gainsay fixed'!B22),0)) -> 230 | P28: ='Gainsay drivers · Gainsay fixed'!B16+'Gainsay drivers · Gainsay fixed'!B17+'Gainsay drivers · Gainsay fixed'!B18+'Gainsay economics · Gainsay ope'!P27+'Gainsay economics · Gainsay ope'!P49+IF(IF(DATE(2027,12,1)=DATE(2026,10,1),IF('Gainsay drivers · Gainsay fixed'!B22="","",'Gainsay drivers · Gainsay fixed'!B22),0)="",0,IF(DATE(2027,12,1)=DATE(2026,10,1),IF('Gainsay drivers · Gainsay fixed'!B22="","",'Gainsay drivers · Gainsay fixed'!B22),0)) -> 630
A29: Operating profit | B29: ='Gainsay economics · Gainsay ope'!B26-'Gainsay economics · Gainsay ope'!B28 -> -857.193 | C29: ='Gainsay economics · Gainsay ope'!C26-'Gainsay economics · Gainsay ope'!C28 -> -273.74916 | D29: ='Gainsay economics · Gainsay ope'!D26-'Gainsay economics · Gainsay ope'!D28 -> -188.40633 | E29: ='Gainsay economics · Gainsay ope'!E26-'Gainsay economics · Gainsay ope'!E28 -> -101.00137 | F29: ='Gainsay economics · Gainsay ope'!F26-'Gainsay economics · Gainsay ope'!F28 -> -11.365023 | G29: ='Gainsay economics · Gainsay ope'!G26-'Gainsay economics · Gainsay ope'!G28 -> 80.678452 | H29: ='Gainsay economics · Gainsay ope'!H26-'Gainsay economics · Gainsay ope'!H28 -> 175.31165 | I29: ='Gainsay economics · Gainsay ope'!I26-'Gainsay economics · Gainsay ope'!I28 -> 272.72443 | ... P29: ='Gainsay economics · Gainsay ope'!P26-'Gainsay economics · Gainsay ope'!P28 -> 650.11842
A30: Data cash payment | B30: =IF(MONTH(DATE(2026,10,1))=10,IF('Gainsay drivers · Gainsay fixed'!B20="","",'Gainsay drivers · Gainsay fixed'!B20),0) -> 3000 | C30: =IF(MONTH(DATE(2026,11,1))=10,IF('Gainsay drivers · Gainsay fixed'!B20="","",'Gainsay drivers · Gainsay fixed'!B20),0) -> 0 | D30: =IF(MONTH(DATE(2026,12,1))=10,IF('Gainsay drivers · Gainsay fixed'!B20="","",'Gainsay drivers · Gainsay fixed'!B20),0) -> 0 | E30: =IF(MONTH(DATE(2027,1,1))=10,IF('Gainsay drivers · Gainsay fixed'!B20="","",'Gainsay drivers · Gainsay fixed'!B20),0) -> 0 | F30: =IF(MONTH(DATE(2027,2,1))=10,IF('Gainsay drivers · Gainsay fixed'!B20="","",'Gainsay drivers · Gainsay fixed'!B20),0) -> 0 | G30: =IF(MONTH(DATE(2027,3,1))=10,IF('Gainsay drivers · Gainsay fixed'!B20="","",'Gainsay drivers · Gainsay fixed'!B20),0) -> 0 | H30: =IF(MONTH(DATE(2027,4,1))=10,IF('Gainsay drivers · Gainsay fixed'!B20="","",'Gainsay drivers · Gainsay fixed'!B20),0) -> 0 | I30: =IF(MONTH(DATE(2027,5,1))=10,IF('Gainsay drivers · Gainsay fixed'!B20="","",'Gainsay drivers · Gainsay fixed'!B20),0) -> 0 | J30: =IF(MONTH(DATE(2027,6,1))=10,IF('Gainsay drivers · Gainsay fixed'!B20="","",'Gainsay drivers · Gainsay fixed'!B20),0) -> 0 | K30: =IF(MONTH(DATE(2027,7,1))=10,IF('Gainsay drivers · Gainsay fixed'!B20="","",'Gainsay drivers · Gainsay fixed'!B20),0) -> 0 | L30: =IF(MONTH(DATE(2027,8,1))=10,IF('Gainsay drivers · Gainsay fixed'!B20="","",'Gainsay drivers · Gainsay fixed'!B20),0) -> 0 | M30: =IF(MONTH(DATE(2027,9,1))=10,IF('Gainsay drivers · Gainsay fixed'!B20="","",'Gainsay drivers · Gainsay fixed'!B20),0) -> 0 | N30: =IF(MONTH(DATE(2027,10,1))=10,IF('Gainsay drivers · Gainsay fixed'!B20="","",'Gainsay drivers · Gainsay fixed'!B20),0) -> 3000 | O30: =IF(MONTH(DATE(2027,11,1))=10,IF('Gainsay drivers · Gainsay fixed'!B20="","",'Gainsay drivers · Gainsay fixed'!B20),0) -> 0 | P30: =IF(MONTH(DATE(2027,12,1))=10,IF('Gainsay drivers · Gainsay fixed'!B20="","",'Gainsay drivers · Gainsay fixed'!B20),0) -> 0
A31: Founder withdrawals | B31: =IF('Gainsay drivers · Gainsay fixed'!B19="","",'Gainsay drivers · Gainsay fixed'!B19) -> 500 | C31: =IF('Gainsay drivers · Gainsay fixed'!B19="","",'Gainsay drivers · Gainsay fixed'!B19) -> 500 | D31: =IF('Gainsay drivers · Gainsay fixed'!B19="","",'Gainsay drivers · Gainsay fixed'!B19) -> 500 | E31: =IF('Gainsay drivers · Gainsay fixed'!B19="","",'Gainsay drivers · Gainsay fixed'!B19) -> 500 | F31: =IF('Gainsay drivers · Gainsay fixed'!B19="","",'Gainsay drivers · Gainsay fixed'!B19) -> 500 | G31: =IF('Gainsay drivers · Gainsay fixed'!B19="","",'Gainsay drivers · Gainsay fixed'!B19) -> 500 | H31: =IF('Gainsay drivers · Gainsay fixed'!B19="","",'Gainsay drivers · Gainsay fixed'!B19) -> 500 | I31: =IF('Gainsay drivers · Gainsay fixed'!B19="","",'Gainsay drivers · Gainsay fixed'!B19) -> 500 | J31: =IF('Gainsay drivers · Gainsay fixed'!B19="","",'Gainsay drivers · Gainsay fixed'!B19) -> 500 | K31: =IF('Gainsay drivers · Gainsay fixed'!B19="","",'Gainsay drivers · Gainsay fixed'!B19) -> 500 | L31: =IF('Gainsay drivers · Gainsay fixed'!B19="","",'Gainsay drivers · Gainsay fixed'!B19) -> 500 | M31: =IF('Gainsay drivers · Gainsay fixed'!B19="","",'Gainsay drivers · Gainsay fixed'!B19) -> 500 | N31: =IF('Gainsay drivers · Gainsay fixed'!B19="","",'Gainsay drivers · Gainsay fixed'!B19) -> 500 | O31: =IF('Gainsay drivers · Gainsay fixed'!B19="","",'Gainsay drivers · Gainsay fixed'!B19) -> 500 | P31: =IF('Gainsay drivers · Gainsay fixed'!B19="","",'Gainsay drivers · Gainsay fixed'!B19) -> 500
A32: Net cash flow | B32: ='Gainsay economics · Gainsay ope'!B29+'Gainsay economics · Gainsay ope'!B25-'Gainsay economics · Gainsay ope'!B30-'Gainsay economics · Gainsay ope'!B31 -> -4107.193 | C32: ='Gainsay economics · Gainsay ope'!C29+'Gainsay economics · Gainsay ope'!C25-'Gainsay economics · Gainsay ope'!C30-'Gainsay economics · Gainsay ope'!C31 -> -523.74916 | D32: ='Gainsay economics · Gainsay ope'!D29+'Gainsay economics · Gainsay ope'!D25-'Gainsay economics · Gainsay ope'!D30-'Gainsay economics · Gainsay ope'!D31 -> -438.40633 | E32: ='Gainsay economics · Gainsay ope'!E29+'Gainsay economics · Gainsay ope'!E25-'Gainsay economics · Gainsay ope'!E30-'Gainsay economics · Gainsay ope'!E31 -> -351.00137 | F32: ='Gainsay economics · Gainsay ope'!F29+'Gainsay economics · Gainsay ope'!F25-'Gainsay economics · Gainsay ope'!F30-'Gainsay economics · Gainsay ope'!F31 -> -261.36502 | G32: ='Gainsay economics · Gainsay ope'!G29+'Gainsay economics · Gainsay ope'!G25-'Gainsay economics · Gainsay ope'!G30-'Gainsay economics · Gainsay ope'!G31 -> -169.32155 | H32: ='Gainsay economics · Gainsay ope'!H29+'Gainsay economics · Gainsay ope'!H25-'Gainsay economics · Gainsay ope'!H30-'Gainsay economics · Gainsay ope'!H31 -> -74.688351 | I32: ='Gainsay economics · Gainsay ope'!I29+'Gainsay economics · Gainsay ope'!I25-'Gainsay economics · Gainsay ope'!I30-'Gainsay economics · Gainsay ope'!I31 -> 22.724427 | ... P32: ='Gainsay economics · Gainsay ope'!P29+'Gainsay economics · Gainsay ope'!P25-'Gainsay economics · Gainsay ope'!P30-'Gainsay economics · Gainsay ope'!P31 -> 400.11842
A33: Ending cash | B33: ='Model inputs'!J37+'Gainsay economics · Gainsay ope'!B32 -> 892.807 | C33: ='Gainsay economics · Gainsay ope'!B33+'Gainsay economics · Gainsay ope'!C32 -> 369.05784 | D33: ='Gainsay economics · Gainsay ope'!C33+'Gainsay economics · Gainsay ope'!D32 -> -69.348493 | E33: ='Gainsay economics · Gainsay ope'!D33+'Gainsay economics · Gainsay ope'!E32 -> -420.34987 | F33: ='Gainsay economics · Gainsay ope'!E33+'Gainsay economics · Gainsay ope'!F32 -> -681.71489 | G33: ='Gainsay economics · Gainsay ope'!F33+'Gainsay economics · Gainsay ope'!G32 -> -851.03644 | H33: ='Gainsay economics · Gainsay ope'!G33+'Gainsay economics · Gainsay ope'!H32 -> -925.72479 | I33: ='Gainsay economics · Gainsay ope'!H33+'Gainsay economics · Gainsay ope'!I32 -> -903.00036 | J33: ='Gainsay economics · Gainsay ope'!I33+'Gainsay economics · Gainsay ope'!J32 -> -779.88603 | ... P33: ='Gainsay economics · Gainsay ope'!O33+'Gainsay economics · Gainsay ope'!P32 -> -1139.2578
A34: API calls required | B34: =('Gainsay economics · Gainsay ope'!B20+'Gainsay economics · Gainsay ope'!B21)*'Gainsay drivers · Gainsay fixed'!B12+'Gainsay economics · Gainsay ope'!B15*'Gainsay drivers · Gainsay fixed'!B14*DAY(EOMONTH(DATE(2026,10,1),0)) -> 2413 | C34: =('Gainsay economics · Gainsay ope'!C20+'Gainsay economics · Gainsay ope'!C21)*'Gainsay drivers · Gainsay fixed'!B12+'Gainsay economics · Gainsay ope'!C15*'Gainsay drivers · Gainsay fixed'!B14*DAY(EOMONTH(DATE(2026,11,1),0)) -> 2965.2 | D34: =('Gainsay economics · Gainsay ope'!D20+'Gainsay economics · Gainsay ope'!D21)*'Gainsay drivers · Gainsay fixed'!B12+'Gainsay economics · Gainsay ope'!D15*'Gainsay drivers · Gainsay fixed'!B14*DAY(EOMONTH(DATE(2026,12,1),0)) -> 3542.5047 | E34: =('Gainsay economics · Gainsay ope'!E20+'Gainsay economics · Gainsay ope'!E21)*'Gainsay drivers · Gainsay fixed'!B12+'Gainsay economics · Gainsay ope'!E15*'Gainsay drivers · Gainsay fixed'!B14*DAY(EOMONTH(DATE(2027,1,1),0)) -> 4127.8312 | F34: =('Gainsay economics · Gainsay ope'!F20+'Gainsay economics · Gainsay ope'!F21)*'Gainsay drivers · Gainsay fixed'!B12+'Gainsay economics · Gainsay ope'!F15*'Gainsay drivers · Gainsay fixed'!B14*DAY(EOMONTH(DATE(2027,2,1),0)) -> 4681.4039 | G34: =('Gainsay economics · Gainsay ope'!G20+'Gainsay economics · Gainsay ope'!G21)*'Gainsay drivers · Gainsay fixed'!B12+'Gainsay economics · Gainsay ope'!G15*'Gainsay drivers · Gainsay fixed'!B14*DAY(EOMONTH(DATE(2027,3,1),0)) -> 5345.3274 | H34: =('Gainsay economics · Gainsay ope'!H20+'Gainsay economics · Gainsay ope'!H21)*'Gainsay drivers · Gainsay fixed'!B12+'Gainsay economics · Gainsay ope'!H15*'Gainsay drivers · Gainsay fixed'!B14*DAY(EOMONTH(DATE(2027,4,1),0)) -> 5957.4415 | I34: =('Gainsay economics · Gainsay ope'!I20+'Gainsay economics · Gainsay ope'!I21)*'Gainsay drivers · Gainsay fixed'!B12+'Gainsay economics · Gainsay ope'!I15*'Gainsay drivers · Gainsay fixed'!B14*DAY(EOMONTH(DATE(2027,5,1),0)) -> 6633.399 | J34: =('Gainsay economics · Gainsay ope'!J20+'Gainsay economics · Gainsay ope'!J21)*'Gainsay drivers · Gainsay fixed'!B12+'Gainsay economics · Gainsay ope'!J15*'Gainsay drivers · Gainsay fixed'!B14*DAY(EOMONTH(DATE(2027,6,1),0)) -> 7277.4632 | K34: =('Gainsay economics · Gainsay ope'!K20+'Gainsay economics · Gainsay ope'!K21)*'Gainsay drivers · Gainsay fixed'!B12+'Gainsay economics · Gainsay ope'!K15*'Gainsay drivers · Gainsay fixed'!B14*DAY(EOMONTH(DATE(2027,7,1),0)) -> 8002.4843 | L34: =('Gainsay economics · Gainsay ope'!L20+'Gainsay economics · Gainsay ope'!L21)*'Gainsay drivers · Gainsay fixed'!B12+'Gainsay economics · Gainsay ope'!L15*'Gainsay drivers · Gainsay fixed'!B14*DAY(EOMONTH(DATE(2027,8,1),0)) -> 8720.9071 | M34: =('Gainsay economics · Gainsay ope'!M20+'Gainsay economics · Gainsay ope'!M21)*'Gainsay drivers · Gainsay fixed'!B12+'Gainsay economics · Gainsay ope'!M15*'Gainsay drivers · Gainsay fixed'!B14*DAY(EOMONTH(DATE(2027,9,1),0)) -> 9422.5766 | N34: =('Gainsay economics · Gainsay ope'!N20+'Gainsay economics · Gainsay ope'!N21)*'Gainsay drivers · Gainsay fixed'!B12+'Gainsay economics · Gainsay ope'!N15*'Gainsay drivers · Gainsay fixed'!B14*DAY(EOMONTH(DATE(2027,10,1),0)) -> 10233.038 | O34: =('Gainsay economics · Gainsay ope'!O20+'Gainsay economics · Gainsay ope'!O21)*'Gainsay drivers · Gainsay fixed'!B12+'Gainsay economics · Gainsay ope'!O15*'Gainsay drivers · Gainsay fixed'!B14*DAY(EOMONTH(DATE(2027,11,1),0)) -> 10980.187 | P34: =('Gainsay economics · Gainsay ope'!P20+'Gainsay economics · Gainsay ope'!P21)*'Gainsay drivers · Gainsay fixed'!B12+'Gainsay economics · Gainsay ope'!P15*'Gainsay drivers · Gainsay fixed'!B14*DAY(EOMONTH(DATE(2027,12,1),0)) -> 11856.356
A35: Default API capacity | B35: ='Gainsay drivers · Gainsay fixed'!B13*DAY(EOMONTH(DATE(2026,10,1),0)) -> 3875 | C35: ='Gainsay drivers · Gainsay fixed'!B13*DAY(EOMONTH(DATE(2026,11,1),0)) -> 3750 | D35: ='Gainsay drivers · Gainsay fixed'!B13*DAY(EOMONTH(DATE(2026,12,1),0)) -> 3875 | E35: ='Gainsay drivers · Gainsay fixed'!B13*DAY(EOMONTH(DATE(2027,1,1),0)) -> 3875 | F35: ='Gainsay drivers · Gainsay fixed'!B13*DAY(EOMONTH(DATE(2027,2,1),0)) -> 3500 | G35: ='Gainsay drivers · Gainsay fixed'!B13*DAY(EOMONTH(DATE(2027,3,1),0)) -> 3875 | H35: ='Gainsay drivers · Gainsay fixed'!B13*DAY(EOMONTH(DATE(2027,4,1),0)) -> 3750 | I35: ='Gainsay drivers · Gainsay fixed'!B13*DAY(EOMONTH(DATE(2027,5,1),0)) -> 3875 | J35: ='Gainsay drivers · Gainsay fixed'!B13*DAY(EOMONTH(DATE(2027,6,1),0)) -> 3750 | K35: ='Gainsay drivers · Gainsay fixed'!B13*DAY(EOMONTH(DATE(2027,7,1),0)) -> 3875 | L35: ='Gainsay drivers · Gainsay fixed'!B13*DAY(EOMONTH(DATE(2027,8,1),0)) -> 3875 | M35: ='Gainsay drivers · Gainsay fixed'!B13*DAY(EOMONTH(DATE(2027,9,1),0)) -> 3750 | N35: ='Gainsay drivers · Gainsay fixed'!B13*DAY(EOMONTH(DATE(2027,10,1),0)) -> 3875 | O35: ='Gainsay drivers · Gainsay fixed'!B13*DAY(EOMONTH(DATE(2027,11,1),0)) -> 3750 | P35: ='Gainsay drivers · Gainsay fixed'!B13*DAY(EOMONTH(DATE(2027,12,1),0)) -> 3875
A36: API capacity shortfall | B36: =MAX('Gainsay economics · Gainsay ope'!B34-'Gainsay economics · Gainsay ope'!B35,0) -> 0 | C36: =MAX('Gainsay economics · Gainsay ope'!C34-'Gainsay economics · Gainsay ope'!C35,0) -> 0 | D36: =MAX('Gainsay economics · Gainsay ope'!D34-'Gainsay economics · Gainsay ope'!D35,0) -> 0 | E36: =MAX('Gainsay economics · Gainsay ope'!E34-'Gainsay economics · Gainsay ope'!E35,0) -> 252.83118 | F36: =MAX('Gainsay economics · Gainsay ope'!F34-'Gainsay economics · Gainsay ope'!F35,0) -> 1181.4039 | G36: =MAX('Gainsay economics · Gainsay ope'!G34-'Gainsay economics · Gainsay ope'!G35,0) -> 1470.3274 | H36: =MAX('Gainsay economics · Gainsay ope'!H34-'Gainsay economics · Gainsay ope'!H35,0) -> 2207.4415 | I36: =MAX('Gainsay economics · Gainsay ope'!I34-'Gainsay economics · Gainsay ope'!I35,0) -> 2758.399 | ... P36: =MAX('Gainsay economics · Gainsay ope'!P34-'Gainsay economics · Gainsay ope'!P35,0) -> 7981.3558
A37: Human review hours | B37: =('Gainsay economics · Gainsay ope'!B18+'Gainsay economics · Gainsay ope'!B6+'Gainsay economics · Gainsay ope'!B19)*'Gainsay drivers · Gainsay fixed'!B25/60 -> 1.8 | C37: =('Gainsay economics · Gainsay ope'!C18+'Gainsay economics · Gainsay ope'!C6+'Gainsay economics · Gainsay ope'!C19)*'Gainsay drivers · Gainsay fixed'!B25/60 -> 2.131 | D37: =('Gainsay economics · Gainsay ope'!D18+'Gainsay economics · Gainsay ope'!D6+'Gainsay economics · Gainsay ope'!D19)*'Gainsay drivers · Gainsay fixed'!B25/60 -> 2.46982 | E37: =('Gainsay economics · Gainsay ope'!E18+'Gainsay economics · Gainsay ope'!E6+'Gainsay economics · Gainsay ope'!E19)*'Gainsay drivers · Gainsay fixed'!B25/60 -> 2.8171129 | F37: =('Gainsay economics · Gainsay ope'!F18+'Gainsay economics · Gainsay ope'!F6+'Gainsay economics · Gainsay ope'!F19)*'Gainsay drivers · Gainsay fixed'!B25/60 -> 3.1735564 | G37: =('Gainsay economics · Gainsay ope'!G18+'Gainsay economics · Gainsay ope'!G6+'Gainsay economics · Gainsay ope'!G19)*'Gainsay drivers · Gainsay fixed'!B25/60 -> 3.5398544 | H37: =('Gainsay economics · Gainsay ope'!H18+'Gainsay economics · Gainsay ope'!H6+'Gainsay economics · Gainsay ope'!H19)*'Gainsay drivers · Gainsay fixed'!B25/60 -> 3.9167387 | I37: =('Gainsay economics · Gainsay ope'!I18+'Gainsay economics · Gainsay ope'!I6+'Gainsay economics · Gainsay ope'!I19)*'Gainsay drivers · Gainsay fixed'!B25/60 -> 4.3049705 | J37: =('Gainsay economics · Gainsay ope'!J18+'Gainsay economics · Gainsay ope'!J6+'Gainsay economics · Gainsay ope'!J19)*'Gainsay drivers · Gainsay fixed'!B25/60 -> 4.7053421 | K37: =('Gainsay economics · Gainsay ope'!K18+'Gainsay economics · Gainsay ope'!K6+'Gainsay economics · Gainsay ope'!K19)*'Gainsay drivers · Gainsay fixed'!B25/60 -> 5.1186785 | L37: =('Gainsay economics · Gainsay ope'!L18+'Gainsay economics · Gainsay ope'!L6+'Gainsay economics · Gainsay ope'!L19)*'Gainsay drivers · Gainsay fixed'!B25/60 -> 5.5458396 | M37: =('Gainsay economics · Gainsay ope'!M18+'Gainsay economics · Gainsay ope'!M6+'Gainsay economics · Gainsay ope'!M19)*'Gainsay drivers · Gainsay fixed'!B25/60 -> 5.987722 | N37: =('Gainsay economics · Gainsay ope'!N18+'Gainsay economics · Gainsay ope'!N6+'Gainsay economics · Gainsay ope'!N19)*'Gainsay drivers · Gainsay fixed'!B25/60 -> 6.4452609 | O37: =('Gainsay economics · Gainsay ope'!O18+'Gainsay economics · Gainsay ope'!O6+'Gainsay economics · Gainsay ope'!O19)*'Gainsay drivers · Gainsay fixed'!B25/60 -> 6.919432 | P37: =('Gainsay economics · Gainsay ope'!P18+'Gainsay economics · Gainsay ope'!P6+'Gainsay economics · Gainsay ope'!P19)*'Gainsay drivers · Gainsay fixed'!B25/60 -> 7.4112545
A38: Founder review capacity gap | B38: =MAX('Gainsay economics · Gainsay ope'!B37-'Gainsay drivers · Gainsay fixed'!B26,0) -> 0 | C38: =MAX('Gainsay economics · Gainsay ope'!C37-'Gainsay drivers · Gainsay fixed'!B26,0) -> 0 | D38: =MAX('Gainsay economics · Gainsay ope'!D37-'Gainsay drivers · Gainsay fixed'!B26,0) -> 0 | E38: =MAX('Gainsay economics · Gainsay ope'!E37-'Gainsay drivers · Gainsay fixed'!B26,0) -> 0 | F38: =MAX('Gainsay economics · Gainsay ope'!F37-'Gainsay drivers · Gainsay fixed'!B26,0) -> 0 | G38: =MAX('Gainsay economics · Gainsay ope'!G37-'Gainsay drivers · Gainsay fixed'!B26,0) -> 0 | H38: =MAX('Gainsay economics · Gainsay ope'!H37-'Gainsay drivers · Gainsay fixed'!B26,0) -> 0 | I38: =MAX('Gainsay economics · Gainsay ope'!I37-'Gainsay drivers · Gainsay fixed'!B26,0) -> 0 | J38: =MAX('Gainsay economics · Gainsay ope'!J37-'Gainsay drivers · Gainsay fixed'!B26,0) -> 0 | K38: =MAX('Gainsay economics · Gainsay ope'!K37-'Gainsay drivers · Gainsay fixed'!B26,0) -> 0 | L38: =MAX('Gainsay economics · Gainsay ope'!L37-'Gainsay drivers · Gainsay fixed'!B26,0) -> 0 | M38: =MAX('Gainsay economics · Gainsay ope'!M37-'Gainsay drivers · Gainsay fixed'!B26,0) -> 0 | N38: =MAX('Gainsay economics · Gainsay ope'!N37-'Gainsay drivers · Gainsay fixed'!B26,0) -> 0 | O38: =MAX('Gainsay economics · Gainsay ope'!O37-'Gainsay drivers · Gainsay fixed'!B26,0) -> 0 | P38: =MAX('Gainsay economics · Gainsay ope'!P37-'Gainsay drivers · Gainsay fixed'!B26,0) -> 0
A39: Founder headcount | B39: =1 -> 1 | C39: =1 -> 1 | D39: =1 -> 1 | E39: =1 -> 1 | F39: =1 -> 1 | G39: =1 -> 1 | H39: =1 -> 1 | I39: =1 -> 1 | ... P39: =1 -> 1
A40: ARR run rate | B40: ='Gainsay economics · Gainsay ope'!B16*12 -> 1044 | C40: ='Gainsay economics · Gainsay ope'!C16*12 -> 2108.88 | D40: ='Gainsay economics · Gainsay ope'!D16*12 -> 3196.6236 | E40: ='Gainsay economics · Gainsay ope'!E16*12 -> 4309.2854 | F40: ='Gainsay economics · Gainsay ope'!F16*12 -> 5448.9954 | G40: ='Gainsay economics · Gainsay ope'!G16*12 -> 6617.9634 | H40: ='Gainsay economics · Gainsay ope'!H16*12 -> 7818.4844 | I40: ='Gainsay economics · Gainsay ope'!I16*12 -> 9052.9427 | ... P40: ='Gainsay economics · Gainsay ope'!P16*12 -> 18866.085
A41: Gross margin | B41: =IFERROR('Gainsay economics · Gainsay ope'!B26/'Gainsay economics · Gainsay ope'!B7,"") -> -0.71860452 | C41: =IFERROR('Gainsay economics · Gainsay ope'!C26/'Gainsay economics · Gainsay ope'!C7,"") -> -0.16189002 | D41: =IFERROR('Gainsay economics · Gainsay ope'!D26/'Gainsay economics · Gainsay ope'!D7,"") -> 0.11376503 | E41: =IFERROR('Gainsay economics · Gainsay ope'!E26/'Gainsay economics · Gainsay ope'!E7,"") -> 0.27843832 | F41: =IFERROR('Gainsay economics · Gainsay ope'!F26/'Gainsay economics · Gainsay ope'!F7,"") -> 0.38800943 | G41: =IFERROR('Gainsay economics · Gainsay ope'!G26/'Gainsay economics · Gainsay ope'!G7,"") -> 0.46623054 | H41: =IFERROR('Gainsay economics · Gainsay ope'!H26/'Gainsay economics · Gainsay ope'!H7,"") -> 0.5249138 | I41: =IFERROR('Gainsay economics · Gainsay ope'!I26/'Gainsay economics · Gainsay ope'!I7,"") -> 0.57059633 | ... P41: =IFERROR('Gainsay economics · Gainsay ope'!P26/'Gainsay economics · Gainsay ope'!P7,"") -> 0.73134263
A42: Projection month number | B42: =DATEDIF(DATE(2026,10,1),DATE(2026,10,1),"M")+1 -> 1 | C42: =DATEDIF(DATE(2026,10,1),DATE(2026,11,1),"M")+1 -> 2 | D42: =DATEDIF(DATE(2026,10,1),DATE(2026,12,1),"M")+1 -> 3 | E42: =DATEDIF(DATE(2026,10,1),DATE(2027,1,1),"M")+1 -> 4 | F42: =DATEDIF(DATE(2026,10,1),DATE(2027,2,1),"M")+1 -> 5 | G42: =DATEDIF(DATE(2026,10,1),DATE(2027,3,1),"M")+1 -> 6 | H42: =DATEDIF(DATE(2026,10,1),DATE(2027,4,1),"M")+1 -> 7 | I42: =DATEDIF(DATE(2026,10,1),DATE(2027,5,1),"M")+1 -> 8 | J42: =DATEDIF(DATE(2026,10,1),DATE(2027,6,1),"M")+1 -> 9 | K42: =DATEDIF(DATE(2026,10,1),DATE(2027,7,1),"M")+1 -> 10 | L42: =DATEDIF(DATE(2026,10,1),DATE(2027,8,1),"M")+1 -> 11 | M42: =DATEDIF(DATE(2026,10,1),DATE(2027,9,1),"M")+1 -> 12 | N42: =DATEDIF(DATE(2026,10,1),DATE(2027,10,1),"M")+1 -> 13 | O42: =DATEDIF(DATE(2026,10,1),DATE(2027,11,1),"M")+1 -> 14 | P42: =DATEDIF(DATE(2026,10,1),DATE(2027,12,1),"M")+1 -> 15
A43: API calls per day conservative | B43: =(('Gainsay economics · Gainsay ope'!B5*'Gainsay drivers · Gainsay fixed'!B8+'Gainsay economics · Gainsay ope'!B6)*'Gainsay drivers · Gainsay fixed'!B9+'Gainsay drivers · Gainsay fixed'!B11*'Gainsay drivers · Gainsay fixed'!B10)*'Gainsay drivers · Gainsay fixed'!B12/'Gainsay drivers · Gainsay fixed'!B32+'Gainsay economics · Gainsay ope'!B5*'Gainsay drivers · Gainsay fixed'!B14 -> 79.315789 | C43: =(('Gainsay economics · Gainsay ope'!C5*'Gainsay drivers · Gainsay fixed'!B8+'Gainsay economics · Gainsay ope'!C6)*'Gainsay drivers · Gainsay fixed'!B9+'Gainsay drivers · Gainsay fixed'!B11*'Gainsay drivers · Gainsay fixed'!B10)*'Gainsay drivers · Gainsay fixed'!B12/'Gainsay drivers · Gainsay fixed'!B32+'Gainsay economics · Gainsay ope'!C5*'Gainsay drivers · Gainsay fixed'!B14 -> 97.619211 | D43: =(('Gainsay economics · Gainsay ope'!D5*'Gainsay drivers · Gainsay fixed'!B8+'Gainsay economics · Gainsay ope'!D6)*'Gainsay drivers · Gainsay fixed'!B9+'Gainsay drivers · Gainsay fixed'!B11*'Gainsay drivers · Gainsay fixed'!B10)*'Gainsay drivers · Gainsay fixed'!B12/'Gainsay drivers · Gainsay fixed'!B32+'Gainsay economics · Gainsay ope'!D5*'Gainsay drivers · Gainsay fixed'!B14 -> 116.34846 | E43: =(('Gainsay economics · Gainsay ope'!E5*'Gainsay drivers · Gainsay fixed'!B8+'Gainsay economics · Gainsay ope'!E6)*'Gainsay drivers · Gainsay fixed'!B9+'Gainsay drivers · Gainsay fixed'!B11*'Gainsay drivers · Gainsay fixed'!B10)*'Gainsay drivers · Gainsay fixed'!B12/'Gainsay drivers · Gainsay fixed'!B32+'Gainsay economics · Gainsay ope'!E5*'Gainsay drivers · Gainsay fixed'!B14 -> 135.53952 | F43: =(('Gainsay economics · Gainsay ope'!F5*'Gainsay drivers · Gainsay fixed'!B8+'Gainsay economics · Gainsay ope'!F6)*'Gainsay drivers · Gainsay fixed'!B9+'Gainsay drivers · Gainsay fixed'!B11*'Gainsay drivers · Gainsay fixed'!B10)*'Gainsay drivers · Gainsay fixed'!B12/'Gainsay drivers · Gainsay fixed'!B32+'Gainsay economics · Gainsay ope'!F5*'Gainsay drivers · Gainsay fixed'!B14 -> 155.22971 | G43: =(('Gainsay economics · Gainsay ope'!G5*'Gainsay drivers · Gainsay fixed'!B8+'Gainsay economics · Gainsay ope'!G6)*'Gainsay drivers · Gainsay fixed'!B9+'Gainsay drivers · Gainsay fixed'!B11*'Gainsay drivers · Gainsay fixed'!B10)*'Gainsay drivers · Gainsay fixed'!B12/'Gainsay drivers · Gainsay fixed'!B32+'Gainsay economics · Gainsay ope'!G5*'Gainsay drivers · Gainsay fixed'!B14 -> 175.4578 | H43: =(('Gainsay economics · Gainsay ope'!H5*'Gainsay drivers · Gainsay fixed'!B8+'Gainsay economics · Gainsay ope'!H6)*'Gainsay drivers · Gainsay fixed'!B9+'Gainsay drivers · Gainsay fixed'!B11*'Gainsay drivers · Gainsay fixed'!B10)*'Gainsay drivers · Gainsay fixed'!B12/'Gainsay drivers · Gainsay fixed'!B32+'Gainsay economics · Gainsay ope'!H5*'Gainsay drivers · Gainsay fixed'!B14 -> 196.26409 | I43: =(('Gainsay economics · Gainsay ope'!I5*'Gainsay drivers · Gainsay fixed'!B8+'Gainsay economics · Gainsay ope'!I6)*'Gainsay drivers · Gainsay fixed'!B9+'Gainsay drivers · Gainsay fixed'!B11*'Gainsay drivers · Gainsay fixed'!B10)*'Gainsay drivers · Gainsay fixed'!B12/'Gainsay drivers · Gainsay fixed'!B32+'Gainsay economics · Gainsay ope'!I5*'Gainsay drivers · Gainsay fixed'!B14 -> 217.69048 | J43: =(('Gainsay economics · Gainsay ope'!J5*'Gainsay drivers · Gainsay fixed'!B8+'Gainsay economics · Gainsay ope'!J6)*'Gainsay drivers · Gainsay fixed'!B9+'Gainsay drivers · Gainsay fixed'!B11*'Gainsay drivers · Gainsay fixed'!B10)*'Gainsay drivers · Gainsay fixed'!B12/'Gainsay drivers · Gainsay fixed'!B32+'Gainsay economics · Gainsay ope'!J5*'Gainsay drivers · Gainsay fixed'!B14 -> 239.78058 | K43: =(('Gainsay economics · Gainsay ope'!K5*'Gainsay drivers · Gainsay fixed'!B8+'Gainsay economics · Gainsay ope'!K6)*'Gainsay drivers · Gainsay fixed'!B9+'Gainsay drivers · Gainsay fixed'!B11*'Gainsay drivers · Gainsay fixed'!B10)*'Gainsay drivers · Gainsay fixed'!B12/'Gainsay drivers · Gainsay fixed'!B32+'Gainsay economics · Gainsay ope'!K5*'Gainsay drivers · Gainsay fixed'!B14 -> 262.57981 | L43: =(('Gainsay economics · Gainsay ope'!L5*'Gainsay drivers · Gainsay fixed'!B8+'Gainsay economics · Gainsay ope'!L6)*'Gainsay drivers · Gainsay fixed'!B9+'Gainsay drivers · Gainsay fixed'!B11*'Gainsay drivers · Gainsay fixed'!B10)*'Gainsay drivers · Gainsay fixed'!B12/'Gainsay drivers · Gainsay fixed'!B32+'Gainsay economics · Gainsay ope'!L5*'Gainsay drivers · Gainsay fixed'!B14 -> 286.13549 | M43: =(('Gainsay economics · Gainsay ope'!M5*'Gainsay drivers · Gainsay fixed'!B8+'Gainsay economics · Gainsay ope'!M6)*'Gainsay drivers · Gainsay fixed'!B9+'Gainsay drivers · Gainsay fixed'!B11*'Gainsay drivers · Gainsay fixed'!B10)*'Gainsay drivers · Gainsay fixed'!B12/'Gainsay drivers · Gainsay fixed'!B32+'Gainsay economics · Gainsay ope'!M5*'Gainsay drivers · Gainsay fixed'!B14 -> 310.49693 | N43: =(('Gainsay economics · Gainsay ope'!N5*'Gainsay drivers · Gainsay fixed'!B8+'Gainsay economics · Gainsay ope'!N6)*'Gainsay drivers · Gainsay fixed'!B9+'Gainsay drivers · Gainsay fixed'!B11*'Gainsay drivers · Gainsay fixed'!B10)*'Gainsay drivers · Gainsay fixed'!B12/'Gainsay drivers · Gainsay fixed'!B32+'Gainsay economics · Gainsay ope'!N5*'Gainsay drivers · Gainsay fixed'!B14 -> 335.7156 | O43: =(('Gainsay economics · Gainsay ope'!O5*'Gainsay drivers · Gainsay fixed'!B8+'Gainsay economics · Gainsay ope'!O6)*'Gainsay drivers · Gainsay fixed'!B9+'Gainsay drivers · Gainsay fixed'!B11*'Gainsay drivers · Gainsay fixed'!B10)*'Gainsay drivers · Gainsay fixed'!B12/'Gainsay drivers · Gainsay fixed'!B32+'Gainsay economics · Gainsay ope'!O5*'Gainsay drivers · Gainsay fixed'!B14 -> 361.84518 | P43: =(('Gainsay economics · Gainsay ope'!P5*'Gainsay drivers · Gainsay fixed'!B8+'Gainsay economics · Gainsay ope'!P6)*'Gainsay drivers · Gainsay fixed'!B9+'Gainsay drivers · Gainsay fixed'!B11*'Gainsay drivers · Gainsay fixed'!B10)*'Gainsay drivers · Gainsay fixed'!B12/'Gainsay drivers · Gainsay fixed'!B32+'Gainsay economics · Gainsay ope'!P5*'Gainsay drivers · Gainsay fixed'!B14 -> 388.94171
A44: API calls per day measured | B44: =(('Gainsay economics · Gainsay ope'!B5*'Gainsay drivers · Gainsay fixed'!B8+'Gainsay economics · Gainsay ope'!B6)*'Gainsay drivers · Gainsay fixed'!B9+'Gainsay drivers · Gainsay fixed'!B11*'Gainsay drivers · Gainsay fixed'!B10)*'Gainsay drivers · Gainsay fixed'!B29/'Gainsay drivers · Gainsay fixed'!B32+'Gainsay economics · Gainsay ope'!B5*'Gainsay drivers · Gainsay fixed'!B14 -> 33.526316 | C44: =(('Gainsay economics · Gainsay ope'!C5*'Gainsay drivers · Gainsay fixed'!B8+'Gainsay economics · Gainsay ope'!C6)*'Gainsay drivers · Gainsay fixed'!B9+'Gainsay drivers · Gainsay fixed'!B11*'Gainsay drivers · Gainsay fixed'!B10)*'Gainsay drivers · Gainsay fixed'!B29/'Gainsay drivers · Gainsay fixed'!B32+'Gainsay economics · Gainsay ope'!C5*'Gainsay drivers · Gainsay fixed'!B14 -> 42.683684 | D44: =(('Gainsay economics · Gainsay ope'!D5*'Gainsay drivers · Gainsay fixed'!B8+'Gainsay economics · Gainsay ope'!D6)*'Gainsay drivers · Gainsay fixed'!B9+'Gainsay drivers · Gainsay fixed'!B11*'Gainsay drivers · Gainsay fixed'!B10)*'Gainsay drivers · Gainsay fixed'!B29/'Gainsay drivers · Gainsay fixed'!B32+'Gainsay economics · Gainsay ope'!D5*'Gainsay drivers · Gainsay fixed'!B14 -> 52.050805 | E44: =(('Gainsay economics · Gainsay ope'!E5*'Gainsay drivers · Gainsay fixed'!B8+'Gainsay economics · Gainsay ope'!E6)*'Gainsay drivers · Gainsay fixed'!B9+'Gainsay drivers · Gainsay fixed'!B11*'Gainsay drivers · Gainsay fixed'!B10)*'Gainsay drivers · Gainsay fixed'!B29/'Gainsay drivers · Gainsay fixed'!B32+'Gainsay economics · Gainsay ope'!E5*'Gainsay drivers · Gainsay fixed'!B14 -> 61.64561 | F44: =(('Gainsay economics · Gainsay ope'!F5*'Gainsay drivers · Gainsay fixed'!B8+'Gainsay economics · Gainsay ope'!F6)*'Gainsay drivers · Gainsay fixed'!B9+'Gainsay drivers · Gainsay fixed'!B11*'Gainsay drivers · Gainsay fixed'!B10)*'Gainsay drivers · Gainsay fixed'!B29/'Gainsay drivers · Gainsay fixed'!B32+'Gainsay economics · Gainsay ope'!F5*'Gainsay drivers · Gainsay fixed'!B14 -> 71.486703 | G44: =(('Gainsay economics · Gainsay ope'!G5*'Gainsay drivers · Gainsay fixed'!B8+'Gainsay economics · Gainsay ope'!G6)*'Gainsay drivers · Gainsay fixed'!B9+'Gainsay drivers · Gainsay fixed'!B11*'Gainsay drivers · Gainsay fixed'!B10)*'Gainsay drivers · Gainsay fixed'!B29/'Gainsay drivers · Gainsay fixed'!B32+'Gainsay economics · Gainsay ope'!G5*'Gainsay drivers · Gainsay fixed'!B14 -> 81.593402 | H44: =(('Gainsay economics · Gainsay ope'!H5*'Gainsay drivers · Gainsay fixed'!B8+'Gainsay economics · Gainsay ope'!H6)*'Gainsay drivers · Gainsay fixed'!B9+'Gainsay drivers · Gainsay fixed'!B11*'Gainsay drivers · Gainsay fixed'!B10)*'Gainsay drivers · Gainsay fixed'!B29/'Gainsay drivers · Gainsay fixed'!B32+'Gainsay economics · Gainsay ope'!H5*'Gainsay drivers · Gainsay fixed'!B14 -> 91.985781 | I44: =(('Gainsay economics · Gainsay ope'!I5*'Gainsay drivers · Gainsay fixed'!B8+'Gainsay economics · Gainsay ope'!I6)*'Gainsay drivers · Gainsay fixed'!B9+'Gainsay drivers · Gainsay fixed'!B11*'Gainsay drivers · Gainsay fixed'!B10)*'Gainsay drivers · Gainsay fixed'!B29/'Gainsay drivers · Gainsay fixed'!B32+'Gainsay economics · Gainsay ope'!I5*'Gainsay drivers · Gainsay fixed'!B14 -> 102.68471 | J44: =(('Gainsay economics · Gainsay ope'!J5*'Gainsay drivers · Gainsay fixed'!B8+'Gainsay economics · Gainsay ope'!J6)*'Gainsay drivers · Gainsay fixed'!B9+'Gainsay drivers · Gainsay fixed'!B11*'Gainsay drivers · Gainsay fixed'!B10)*'Gainsay drivers · Gainsay fixed'!B29/'Gainsay drivers · Gainsay fixed'!B32+'Gainsay economics · Gainsay ope'!J5*'Gainsay drivers · Gainsay fixed'!B14 -> 113.71192 | K44: =(('Gainsay economics · Gainsay ope'!K5*'Gainsay drivers · Gainsay fixed'!B8+'Gainsay economics · Gainsay ope'!K6)*'Gainsay drivers · Gainsay fixed'!B9+'Gainsay drivers · Gainsay fixed'!B11*'Gainsay drivers · Gainsay fixed'!B10)*'Gainsay drivers · Gainsay fixed'!B29/'Gainsay drivers · Gainsay fixed'!B32+'Gainsay economics · Gainsay ope'!K5*'Gainsay drivers · Gainsay fixed'!B14 -> 125.09001 | L44: =(('Gainsay economics · Gainsay ope'!L5*'Gainsay drivers · Gainsay fixed'!B8+'Gainsay economics · Gainsay ope'!L6)*'Gainsay drivers · Gainsay fixed'!B9+'Gainsay drivers · Gainsay fixed'!B11*'Gainsay drivers · Gainsay fixed'!B10)*'Gainsay drivers · Gainsay fixed'!B29/'Gainsay drivers · Gainsay fixed'!B32+'Gainsay economics · Gainsay ope'!L5*'Gainsay drivers · Gainsay fixed'!B14 -> 136.84255 | M44: =(('Gainsay economics · Gainsay ope'!M5*'Gainsay drivers · Gainsay fixed'!B8+'Gainsay economics · Gainsay ope'!M6)*'Gainsay drivers · Gainsay fixed'!B9+'Gainsay drivers · Gainsay fixed'!B11*'Gainsay drivers · Gainsay fixed'!B10)*'Gainsay drivers · Gainsay fixed'!B29/'Gainsay drivers · Gainsay fixed'!B32+'Gainsay economics · Gainsay ope'!M5*'Gainsay drivers · Gainsay fixed'!B14 -> 148.99409 | N44: =(('Gainsay economics · Gainsay ope'!N5*'Gainsay drivers · Gainsay fixed'!B8+'Gainsay economics · Gainsay ope'!N6)*'Gainsay drivers · Gainsay fixed'!B9+'Gainsay drivers · Gainsay fixed'!B11*'Gainsay drivers · Gainsay fixed'!B10)*'Gainsay drivers · Gainsay fixed'!B29/'Gainsay drivers · Gainsay fixed'!B32+'Gainsay economics · Gainsay ope'!N5*'Gainsay drivers · Gainsay fixed'!B14 -> 161.57024 | O44: =(('Gainsay economics · Gainsay ope'!O5*'Gainsay drivers · Gainsay fixed'!B8+'Gainsay economics · Gainsay ope'!O6)*'Gainsay drivers · Gainsay fixed'!B9+'Gainsay drivers · Gainsay fixed'!B11*'Gainsay drivers · Gainsay fixed'!B10)*'Gainsay drivers · Gainsay fixed'!B29/'Gainsay drivers · Gainsay fixed'!B32+'Gainsay economics · Gainsay ope'!O5*'Gainsay drivers · Gainsay fixed'!B14 -> 174.59772 | P44: =(('Gainsay economics · Gainsay ope'!P5*'Gainsay drivers · Gainsay fixed'!B8+'Gainsay economics · Gainsay ope'!P6)*'Gainsay drivers · Gainsay fixed'!B9+'Gainsay drivers · Gainsay fixed'!B11*'Gainsay drivers · Gainsay fixed'!B10)*'Gainsay drivers · Gainsay fixed'!B29/'Gainsay drivers · Gainsay fixed'!B32+'Gainsay economics · Gainsay ope'!P5*'Gainsay drivers · Gainsay fixed'!B14 -> 188.10442
A45: API quota exceeded conservative | B45: =IF(IF(IF(ISERROR('Gainsay economics · Gainsay ope'!B43>'Gainsay drivers · Gainsay fixed'!B13),'Gainsay economics · Gainsay ope'!B43>'Gainsay drivers · Gainsay fixed'!B13,IF(OR('Gainsay economics · Gainsay ope'!B43="",'Gainsay drivers · Gainsay fixed'!B13=""),"",'Gainsay economics · Gainsay ope'!B43>'Gainsay drivers · Gainsay fixed'!B13))="",FALSE(),IF(ISERROR('Gainsay economics · Gainsay ope'!B43>'Gainsay drivers · Gainsay fixed'!B13),'Gainsay economics · Gainsay ope'!B43>'Gainsay drivers · Gainsay fixed'!B13,IF(OR('Gainsay economics · Gainsay ope'!B43="",'Gainsay drivers · Gainsay fixed'!B13=""),"",'Gainsay economics · Gainsay ope'!B43>'Gainsay drivers · Gainsay fixed'!B13))),1,0) -> 0 | C45: =IF(IF(IF(ISERROR('Gainsay economics · Gainsay ope'!C43>'Gainsay drivers · Gainsay fixed'!B13),'Gainsay economics · Gainsay ope'!C43>'Gainsay drivers · Gainsay fixed'!B13,IF(OR('Gainsay economics · Gainsay ope'!C43="",'Gainsay drivers · Gainsay fixed'!B13=""),"",'Gainsay economics · Gainsay ope'!C43>'Gainsay drivers · Gainsay fixed'!B13))="",FALSE(),IF(ISERROR('Gainsay economics · Gainsay ope'!C43>'Gainsay drivers · Gainsay fixed'!B13),'Gainsay economics · Gainsay ope'!C43>'Gainsay drivers · Gainsay fixed'!B13,IF(OR('Gainsay economics · Gainsay ope'!C43="",'Gainsay drivers · Gainsay fixed'!B13=""),"",'Gainsay economics · Gainsay ope'!C43>'Gainsay drivers · Gainsay fixed'!B13))),1,0) -> 0 | D45: =IF(IF(IF(ISERROR('Gainsay economics · Gainsay ope'!D43>'Gainsay drivers · Gainsay fixed'!B13),'Gainsay economics · Gainsay ope'!D43>'Gainsay drivers · Gainsay fixed'!B13,IF(OR('Gainsay economics · Gainsay ope'!D43="",'Gainsay drivers · Gainsay fixed'!B13=""),"",'Gainsay economics · Gainsay ope'!D43>'Gainsay drivers · Gainsay fixed'!B13))="",FALSE(),IF(ISERROR('Gainsay economics · Gainsay ope'!D43>'Gainsay drivers · Gainsay fixed'!B13),'Gainsay economics · Gainsay ope'!D43>'Gainsay drivers · Gainsay fixed'!B13,IF(OR('Gainsay economics · Gainsay ope'!D43="",'Gainsay drivers · Gainsay fixed'!B13=""),"",'Gainsay economics · Gainsay ope'!D43>'Gainsay drivers · Gainsay fixed'!B13))),1,0) -> 0 | E45: =IF(IF(IF(ISERROR('Gainsay economics · Gainsay ope'!E43>'Gainsay drivers · Gainsay fixed'!B13),'Gainsay economics · Gainsay ope'!E43>'Gainsay drivers · Gainsay fixed'!B13,IF(OR('Gainsay economics · Gainsay ope'!E43="",'Gainsay drivers · Gainsay fixed'!B13=""),"",'Gainsay economics · Gainsay ope'!E43>'Gainsay drivers · Gainsay fixed'!B13))="",FALSE(),IF(ISERROR('Gainsay economics · Gainsay ope'!E43>'Gainsay drivers · Gainsay fixed'!B13),'Gainsay economics · Gainsay ope'!E43>'Gainsay drivers · Gainsay fixed'!B13,IF(OR('Gainsay economics · Gainsay ope'!E43="",'Gainsay drivers · Gainsay fixed'!B13=""),"",'Gainsay economics · Gainsay ope'!E43>'Gainsay drivers · Gainsay fixed'!B13))),1,0) -> 1 | F45: =IF(IF(IF(ISERROR('Gainsay economics · Gainsay ope'!F43>'Gainsay drivers · Gainsay fixed'!B13),'Gainsay economics · Gainsay ope'!F43>'Gainsay drivers · Gainsay fixed'!B13,IF(OR('Gainsay economics · Gainsay ope'!F43="",'Gainsay drivers · Gainsay fixed'!B13=""),"",'Gainsay economics · Gainsay ope'!F43>'Gainsay drivers · Gainsay fixed'!B13))="",FALSE(),IF(ISERROR('Gainsay economics · Gainsay ope'!F43>'Gainsay drivers · Gainsay fixed'!B13),'Gainsay economics · Gainsay ope'!F43>'Gainsay drivers · Gainsay fixed'!B13,IF(OR('Gainsay economics · Gainsay ope'!F43="",'Gainsay drivers · Gainsay fixed'!B13=""),"",'Gainsay economics · Gainsay ope'!F43>'Gainsay drivers · Gainsay fixed'!B13))),1,0) -> 1 | G45: =IF(IF(IF(ISERROR('Gainsay economics · Gainsay ope'!G43>'Gainsay drivers · Gainsay fixed'!B13),'Gainsay economics · Gainsay ope'!G43>'Gainsay drivers · Gainsay fixed'!B13,IF(OR('Gainsay economics · Gainsay ope'!G43="",'Gainsay drivers · Gainsay fixed'!B13=""),"",'Gainsay economics · Gainsay ope'!G43>'Gainsay drivers · Gainsay fixed'!B13))="",FALSE(),IF(ISERROR('Gainsay economics · Gainsay ope'!G43>'Gainsay drivers · Gainsay fixed'!B13),'Gainsay economics · Gainsay ope'!G43>'Gainsay drivers · Gainsay fixed'!B13,IF(OR('Gainsay economics · Gainsay ope'!G43="",'Gainsay drivers · Gainsay fixed'!B13=""),"",'Gainsay economics · Gainsay ope'!G43>'Gainsay drivers · Gainsay fixed'!B13))),1,0) -> 1 | H45: =IF(IF(IF(ISERROR('Gainsay economics · Gainsay ope'!H43>'Gainsay drivers · Gainsay fixed'!B13),'Gainsay economics · Gainsay ope'!H43>'Gainsay drivers · Gainsay fixed'!B13,IF(OR('Gainsay economics · Gainsay ope'!H43="",'Gainsay drivers · Gainsay fixed'!B13=""),"",'Gainsay economics · Gainsay ope'!H43>'Gainsay drivers · Gainsay fixed'!B13))="",FALSE(),IF(ISERROR('Gainsay economics · Gainsay ope'!H43>'Gainsay drivers · Gainsay fixed'!B13),'Gainsay economics · Gainsay ope'!H43>'Gainsay drivers · Gainsay fixed'!B13,IF(OR('Gainsay economics · Gainsay ope'!H43="",'Gainsay drivers · Gainsay fixed'!B13=""),"",'Gainsay economics · Gainsay ope'!H43>'Gainsay drivers · Gainsay fixed'!B13))),1,0) -> 1 | I45: =IF(IF(IF(ISERROR('Gainsay economics · Gainsay ope'!I43>'Gainsay drivers · Gainsay fixed'!B13),'Gainsay economics · Gainsay ope'!I43>'Gainsay drivers · Gainsay fixed'!B13,IF(OR('Gainsay economics · Gainsay ope'!I43="",'Gainsay drivers · Gainsay fixed'!B13=""),"",'Gainsay economics · Gainsay ope'!I43>'Gainsay drivers · Gainsay fixed'!B13))="",FALSE(),IF(ISERROR('Gainsay economics · Gainsay ope'!I43>'Gainsay drivers · Gainsay fixed'!B13),'Gainsay economics · Gainsay ope'!I43>'Gainsay drivers · Gainsay fixed'!B13,IF(OR('Gainsay economics · Gainsay ope'!I43="",'Gainsay drivers · Gainsay fixed'!B13=""),"",'Gainsay economics · Gainsay ope'!I43>'Gainsay drivers · Gainsay fixed'!B13))),1,0) -> 1 | J45: =IF(IF(IF(ISERROR('Gainsay economics · Gainsay ope'!J43>'Gainsay drivers · Gainsay fixed'!B13),'Gainsay economics · Gainsay ope'!J43>'Gainsay drivers · Gainsay fixed'!B13,IF(OR('Gainsay economics · Gainsay ope'!J43="",'Gainsay drivers · Gainsay fixed'!B13=""),"",'Gainsay economics · Gainsay ope'!J43>'Gainsay drivers · Gainsay fixed'!B13))="",FALSE(),IF(ISERROR('Gainsay economics · Gainsay ope'!J43>'Gainsay drivers · Gainsay fixed'!B13),'Gainsay economics · Gainsay ope'!J43>'Gainsay drivers · Gainsay fixed'!B13,IF(OR('Gainsay economics · Gainsay ope'!J43="",'Gainsay drivers · Gainsay fixed'!B13=""),"",'Gainsay economics · Gainsay ope'!J43>'Gainsay drivers · Gainsay fixed'!B13))),1,0) -> 1 | K45: =IF(IF(IF(ISERROR('Gainsay economics · Gainsay ope'!K43>'Gainsay drivers · Gainsay fixed'!B13),'Gainsay economics · Gainsay ope'!K43>'Gainsay drivers · Gainsay fixed'!B13,IF(OR('Gainsay economics · Gainsay ope'!K43="",'Gainsay drivers · Gainsay fixed'!B13=""),"",'Gainsay economics · Gainsay ope'!K43>'Gainsay drivers · Gainsay fixed'!B13))="",FALSE(),IF(ISERROR('Gainsay economics · Gainsay ope'!K43>'Gainsay drivers · Gainsay fixed'!B13),'Gainsay economics · Gainsay ope'!K43>'Gainsay drivers · Gainsay fixed'!B13,IF(OR('Gainsay economics · Gainsay ope'!K43="",'Gainsay drivers · Gainsay fixed'!B13=""),"",'Gainsay economics · Gainsay ope'!K43>'Gainsay drivers · Gainsay fixed'!B13))),1,0) -> 1 | L45: =IF(IF(IF(ISERROR('Gainsay economics · Gainsay ope'!L43>'Gainsay drivers · Gainsay fixed'!B13),'Gainsay economics · Gainsay ope'!L43>'Gainsay drivers · Gainsay fixed'!B13,IF(OR('Gainsay economics · Gainsay ope'!L43="",'Gainsay drivers · Gainsay fixed'!B13=""),"",'Gainsay economics · Gainsay ope'!L43>'Gainsay drivers · Gainsay fixed'!B13))="",FALSE(),IF(ISERROR('Gainsay economics · Gainsay ope'!L43>'Gainsay drivers · Gainsay fixed'!B13),'Gainsay economics · Gainsay ope'!L43>'Gainsay drivers · Gainsay fixed'!B13,IF(OR('Gainsay economics · Gainsay ope'!L43="",'Gainsay drivers · Gainsay fixed'!B13=""),"",'Gainsay economics · Gainsay ope'!L43>'Gainsay drivers · Gainsay fixed'!B13))),1,0) -> 1 | M45: =IF(IF(IF(ISERROR('Gainsay economics · Gainsay ope'!M43>'Gainsay drivers · Gainsay fixed'!B13),'Gainsay economics · Gainsay ope'!M43>'Gainsay drivers · Gainsay fixed'!B13,IF(OR('Gainsay economics · Gainsay ope'!M43="",'Gainsay drivers · Gainsay fixed'!B13=""),"",'Gainsay economics · Gainsay ope'!M43>'Gainsay drivers · Gainsay fixed'!B13))="",FALSE(),IF(ISERROR('Gainsay economics · Gainsay ope'!M43>'Gainsay drivers · Gainsay fixed'!B13),'Gainsay economics · Gainsay ope'!M43>'Gainsay drivers · Gainsay fixed'!B13,IF(OR('Gainsay economics · Gainsay ope'!M43="",'Gainsay drivers · Gainsay fixed'!B13=""),"",'Gainsay economics · Gainsay ope'!M43>'Gainsay drivers · Gainsay fixed'!B13))),1,0) -> 1 | N45: =IF(IF(IF(ISERROR('Gainsay economics · Gainsay ope'!N43>'Gainsay drivers · Gainsay fixed'!B13),'Gainsay economics · Gainsay ope'!N43>'Gainsay drivers · Gainsay fixed'!B13,IF(OR('Gainsay economics · Gainsay ope'!N43="",'Gainsay drivers · Gainsay fixed'!B13=""),"",'Gainsay economics · Gainsay ope'!N43>'Gainsay drivers · Gainsay fixed'!B13))="",FALSE(),IF(ISERROR('Gainsay economics · Gainsay ope'!N43>'Gainsay drivers · Gainsay fixed'!B13),'Gainsay economics · Gainsay ope'!N43>'Gainsay drivers · Gainsay fixed'!B13,IF(OR('Gainsay economics · Gainsay ope'!N43="",'Gainsay drivers · Gainsay fixed'!B13=""),"",'Gainsay economics · Gainsay ope'!N43>'Gainsay drivers · Gainsay fixed'!B13))),1,0) -> 1 | O45: =IF(IF(IF(ISERROR('Gainsay economics · Gainsay ope'!O43>'Gainsay drivers · Gainsay fixed'!B13),'Gainsay economics · Gainsay ope'!O43>'Gainsay drivers · Gainsay fixed'!B13,IF(OR('Gainsay economics · Gainsay ope'!O43="",'Gainsay drivers · Gainsay fixed'!B13=""),"",'Gainsay economics · Gainsay ope'!O43>'Gainsay drivers · Gainsay fixed'!B13))="",FALSE(),IF(ISERROR('Gainsay economics · Gainsay ope'!O43>'Gainsay drivers · Gainsay fixed'!B13),'Gainsay economics · Gainsay ope'!O43>'Gainsay drivers · Gainsay fixed'!B13,IF(OR('Gainsay economics · Gainsay ope'!O43="",'Gainsay drivers · Gainsay fixed'!B13=""),"",'Gainsay economics · Gainsay ope'!O43>'Gainsay drivers · Gainsay fixed'!B13))),1,0) -> 1 | P45: =IF(IF(IF(ISERROR('Gainsay economics · Gainsay ope'!P43>'Gainsay drivers · Gainsay fixed'!B13),'Gainsay economics · Gainsay ope'!P43>'Gainsay drivers · Gainsay fixed'!B13,IF(OR('Gainsay economics · Gainsay ope'!P43="",'Gainsay drivers · Gainsay fixed'!B13=""),"",'Gainsay economics · Gainsay ope'!P43>'Gainsay drivers · Gainsay fixed'!B13))="",FALSE(),IF(ISERROR('Gainsay economics · Gainsay ope'!P43>'Gainsay drivers · Gainsay fixed'!B13),'Gainsay economics · Gainsay ope'!P43>'Gainsay drivers · Gainsay fixed'!B13,IF(OR('Gainsay economics · Gainsay ope'!P43="",'Gainsay drivers · Gainsay fixed'!B13=""),"",'Gainsay economics · Gainsay ope'!P43>'Gainsay drivers · Gainsay fixed'!B13))),1,0) -> 1
A46: API quota exceeded measured | B46: =IF(IF(IF(ISERROR('Gainsay economics · Gainsay ope'!B44>'Gainsay drivers · Gainsay fixed'!B13),'Gainsay economics · Gainsay ope'!B44>'Gainsay drivers · Gainsay fixed'!B13,IF(OR('Gainsay economics · Gainsay ope'!B44="",'Gainsay drivers · Gainsay fixed'!B13=""),"",'Gainsay economics · Gainsay ope'!B44>'Gainsay drivers · Gainsay fixed'!B13))="",FALSE(),IF(ISERROR('Gainsay economics · Gainsay ope'!B44>'Gainsay drivers · Gainsay fixed'!B13),'Gainsay economics · Gainsay ope'!B44>'Gainsay drivers · Gainsay fixed'!B13,IF(OR('Gainsay economics · Gainsay ope'!B44="",'Gainsay drivers · Gainsay fixed'!B13=""),"",'Gainsay economics · Gainsay ope'!B44>'Gainsay drivers · Gainsay fixed'!B13))),1,0) -> 0 | C46: =IF(IF(IF(ISERROR('Gainsay economics · Gainsay ope'!C44>'Gainsay drivers · Gainsay fixed'!B13),'Gainsay economics · Gainsay ope'!C44>'Gainsay drivers · Gainsay fixed'!B13,IF(OR('Gainsay economics · Gainsay ope'!C44="",'Gainsay drivers · Gainsay fixed'!B13=""),"",'Gainsay economics · Gainsay ope'!C44>'Gainsay drivers · Gainsay fixed'!B13))="",FALSE(),IF(ISERROR('Gainsay economics · Gainsay ope'!C44>'Gainsay drivers · Gainsay fixed'!B13),'Gainsay economics · Gainsay ope'!C44>'Gainsay drivers · Gainsay fixed'!B13,IF(OR('Gainsay economics · Gainsay ope'!C44="",'Gainsay drivers · Gainsay fixed'!B13=""),"",'Gainsay economics · Gainsay ope'!C44>'Gainsay drivers · Gainsay fixed'!B13))),1,0) -> 0 | D46: =IF(IF(IF(ISERROR('Gainsay economics · Gainsay ope'!D44>'Gainsay drivers · Gainsay fixed'!B13),'Gainsay economics · Gainsay ope'!D44>'Gainsay drivers · Gainsay fixed'!B13,IF(OR('Gainsay economics · Gainsay ope'!D44="",'Gainsay drivers · Gainsay fixed'!B13=""),"",'Gainsay economics · Gainsay ope'!D44>'Gainsay drivers · Gainsay fixed'!B13))="",FALSE(),IF(ISERROR('Gainsay economics · Gainsay ope'!D44>'Gainsay drivers · Gainsay fixed'!B13),'Gainsay economics · Gainsay ope'!D44>'Gainsay drivers · Gainsay fixed'!B13,IF(OR('Gainsay economics · Gainsay ope'!D44="",'Gainsay drivers · Gainsay fixed'!B13=""),"",'Gainsay economics · Gainsay ope'!D44>'Gainsay drivers · Gainsay fixed'!B13))),1,0) -> 0 | E46: =IF(IF(IF(ISERROR('Gainsay economics · Gainsay ope'!E44>'Gainsay drivers · Gainsay fixed'!B13),'Gainsay economics · Gainsay ope'!E44>'Gainsay drivers · Gainsay fixed'!B13,IF(OR('Gainsay economics · Gainsay ope'!E44="",'Gainsay drivers · Gainsay fixed'!B13=""),"",'Gainsay economics · Gainsay ope'!E44>'Gainsay drivers · Gainsay fixed'!B13))="",FALSE(),IF(ISERROR('Gainsay economics · Gainsay ope'!E44>'Gainsay drivers · Gainsay fixed'!B13),'Gainsay economics · Gainsay ope'!E44>'Gainsay drivers · Gainsay fixed'!B13,IF(OR('Gainsay economics · Gainsay ope'!E44="",'Gainsay drivers · Gainsay fixed'!B13=""),"",'Gainsay economics · Gainsay ope'!E44>'Gainsay drivers · Gainsay fixed'!B13))),1,0) -> 0 | F46: =IF(IF(IF(ISERROR('Gainsay economics · Gainsay ope'!F44>'Gainsay drivers · Gainsay fixed'!B13),'Gainsay economics · Gainsay ope'!F44>'Gainsay drivers · Gainsay fixed'!B13,IF(OR('Gainsay economics · Gainsay ope'!F44="",'Gainsay drivers · Gainsay fixed'!B13=""),"",'Gainsay economics · Gainsay ope'!F44>'Gainsay drivers · Gainsay fixed'!B13))="",FALSE(),IF(ISERROR('Gainsay economics · Gainsay ope'!F44>'Gainsay drivers · Gainsay fixed'!B13),'Gainsay economics · Gainsay ope'!F44>'Gainsay drivers · Gainsay fixed'!B13,IF(OR('Gainsay economics · Gainsay ope'!F44="",'Gainsay drivers · Gainsay fixed'!B13=""),"",'Gainsay economics · Gainsay ope'!F44>'Gainsay drivers · Gainsay fixed'!B13))),1,0) -> 0 | G46: =IF(IF(IF(ISERROR('Gainsay economics · Gainsay ope'!G44>'Gainsay drivers · Gainsay fixed'!B13),'Gainsay economics · Gainsay ope'!G44>'Gainsay drivers · Gainsay fixed'!B13,IF(OR('Gainsay economics · Gainsay ope'!G44="",'Gainsay drivers · Gainsay fixed'!B13=""),"",'Gainsay economics · Gainsay ope'!G44>'Gainsay drivers · Gainsay fixed'!B13))="",FALSE(),IF(ISERROR('Gainsay economics · Gainsay ope'!G44>'Gainsay drivers · Gainsay fixed'!B13),'Gainsay economics · Gainsay ope'!G44>'Gainsay drivers · Gainsay fixed'!B13,IF(OR('Gainsay economics · Gainsay ope'!G44="",'Gainsay drivers · Gainsay fixed'!B13=""),"",'Gainsay economics · Gainsay ope'!G44>'Gainsay drivers · Gainsay fixed'!B13))),1,0) -> 0 | H46: =IF(IF(IF(ISERROR('Gainsay economics · Gainsay ope'!H44>'Gainsay drivers · Gainsay fixed'!B13),'Gainsay economics · Gainsay ope'!H44>'Gainsay drivers · Gainsay fixed'!B13,IF(OR('Gainsay economics · Gainsay ope'!H44="",'Gainsay drivers · Gainsay fixed'!B13=""),"",'Gainsay economics · Gainsay ope'!H44>'Gainsay drivers · Gainsay fixed'!B13))="",FALSE(),IF(ISERROR('Gainsay economics · Gainsay ope'!H44>'Gainsay drivers · Gainsay fixed'!B13),'Gainsay economics · Gainsay ope'!H44>'Gainsay drivers · Gainsay fixed'!B13,IF(OR('Gainsay economics · Gainsay ope'!H44="",'Gainsay drivers · Gainsay fixed'!B13=""),"",'Gainsay economics · Gainsay ope'!H44>'Gainsay drivers · Gainsay fixed'!B13))),1,0) -> 0 | I46: =IF(IF(IF(ISERROR('Gainsay economics · Gainsay ope'!I44>'Gainsay drivers · Gainsay fixed'!B13),'Gainsay economics · Gainsay ope'!I44>'Gainsay drivers · Gainsay fixed'!B13,IF(OR('Gainsay economics · Gainsay ope'!I44="",'Gainsay drivers · Gainsay fixed'!B13=""),"",'Gainsay economics · Gainsay ope'!I44>'Gainsay drivers · Gainsay fixed'!B13))="",FALSE(),IF(ISERROR('Gainsay economics · Gainsay ope'!I44>'Gainsay drivers · Gainsay fixed'!B13),'Gainsay economics · Gainsay ope'!I44>'Gainsay drivers · Gainsay fixed'!B13,IF(OR('Gainsay economics · Gainsay ope'!I44="",'Gainsay drivers · Gainsay fixed'!B13=""),"",'Gainsay economics · Gainsay ope'!I44>'Gainsay drivers · Gainsay fixed'!B13))),1,0) -> 0 | J46: =IF(IF(IF(ISERROR('Gainsay economics · Gainsay ope'!J44>'Gainsay drivers · Gainsay fixed'!B13),'Gainsay economics · Gainsay ope'!J44>'Gainsay drivers · Gainsay fixed'!B13,IF(OR('Gainsay economics · Gainsay ope'!J44="",'Gainsay drivers · Gainsay fixed'!B13=""),"",'Gainsay economics · Gainsay ope'!J44>'Gainsay drivers · Gainsay fixed'!B13))="",FALSE(),IF(ISERROR('Gainsay economics · Gainsay ope'!J44>'Gainsay drivers · Gainsay fixed'!B13),'Gainsay economics · Gainsay ope'!J44>'Gainsay drivers · Gainsay fixed'!B13,IF(OR('Gainsay economics · Gainsay ope'!J44="",'Gainsay drivers · Gainsay fixed'!B13=""),"",'Gainsay economics · Gainsay ope'!J44>'Gainsay drivers · Gainsay fixed'!B13))),1,0) -> 0 | K46: =IF(IF(IF(ISERROR('Gainsay economics · Gainsay ope'!K44>'Gainsay drivers · Gainsay fixed'!B13),'Gainsay economics · Gainsay ope'!K44>'Gainsay drivers · Gainsay fixed'!B13,IF(OR('Gainsay economics · Gainsay ope'!K44="",'Gainsay drivers · Gainsay fixed'!B13=""),"",'Gainsay economics · Gainsay ope'!K44>'Gainsay drivers · Gainsay fixed'!B13))="",FALSE(),IF(ISERROR('Gainsay economics · Gainsay ope'!K44>'Gainsay drivers · Gainsay fixed'!B13),'Gainsay economics · Gainsay ope'!K44>'Gainsay drivers · Gainsay fixed'!B13,IF(OR('Gainsay economics · Gainsay ope'!K44="",'Gainsay drivers · Gainsay fixed'!B13=""),"",'Gainsay economics · Gainsay ope'!K44>'Gainsay drivers · Gainsay fixed'!B13))),1,0) -> 1 | L46: =IF(IF(IF(ISERROR('Gainsay economics · Gainsay ope'!L44>'Gainsay drivers · Gainsay fixed'!B13),'Gainsay economics · Gainsay ope'!L44>'Gainsay drivers · Gainsay fixed'!B13,IF(OR('Gainsay economics · Gainsay ope'!L44="",'Gainsay drivers · Gainsay fixed'!B13=""),"",'Gainsay economics · Gainsay ope'!L44>'Gainsay drivers · Gainsay fixed'!B13))="",FALSE(),IF(ISERROR('Gainsay economics · Gainsay ope'!L44>'Gainsay drivers · Gainsay fixed'!B13),'Gainsay economics · Gainsay ope'!L44>'Gainsay drivers · Gainsay fixed'!B13,IF(OR('Gainsay economics · Gainsay ope'!L44="",'Gainsay drivers · Gainsay fixed'!B13=""),"",'Gainsay economics · Gainsay ope'!L44>'Gainsay drivers · Gainsay fixed'!B13))),1,0) -> 1 | M46: =IF(IF(IF(ISERROR('Gainsay economics · Gainsay ope'!M44>'Gainsay drivers · Gainsay fixed'!B13),'Gainsay economics · Gainsay ope'!M44>'Gainsay drivers · Gainsay fixed'!B13,IF(OR('Gainsay economics · Gainsay ope'!M44="",'Gainsay drivers · Gainsay fixed'!B13=""),"",'Gainsay economics · Gainsay ope'!M44>'Gainsay drivers · Gainsay fixed'!B13))="",FALSE(),IF(ISERROR('Gainsay economics · Gainsay ope'!M44>'Gainsay drivers · Gainsay fixed'!B13),'Gainsay economics · Gainsay ope'!M44>'Gainsay drivers · Gainsay fixed'!B13,IF(OR('Gainsay economics · Gainsay ope'!M44="",'Gainsay drivers · Gainsay fixed'!B13=""),"",'Gainsay economics · Gainsay ope'!M44>'Gainsay drivers · Gainsay fixed'!B13))),1,0) -> 1 | N46: =IF(IF(IF(ISERROR('Gainsay economics · Gainsay ope'!N44>'Gainsay drivers · Gainsay fixed'!B13),'Gainsay economics · Gainsay ope'!N44>'Gainsay drivers · Gainsay fixed'!B13,IF(OR('Gainsay economics · Gainsay ope'!N44="",'Gainsay drivers · Gainsay fixed'!B13=""),"",'Gainsay economics · Gainsay ope'!N44>'Gainsay drivers · Gainsay fixed'!B13))="",FALSE(),IF(ISERROR('Gainsay economics · Gainsay ope'!N44>'Gainsay drivers · Gainsay fixed'!B13),'Gainsay economics · Gainsay ope'!N44>'Gainsay drivers · Gainsay fixed'!B13,IF(OR('Gainsay economics · Gainsay ope'!N44="",'Gainsay drivers · Gainsay fixed'!B13=""),"",'Gainsay economics · Gainsay ope'!N44>'Gainsay drivers · Gainsay fixed'!B13))),1,0) -> 1 | O46: =IF(IF(IF(ISERROR('Gainsay economics · Gainsay ope'!O44>'Gainsay drivers · Gainsay fixed'!B13),'Gainsay economics · Gainsay ope'!O44>'Gainsay drivers · Gainsay fixed'!B13,IF(OR('Gainsay economics · Gainsay ope'!O44="",'Gainsay drivers · Gainsay fixed'!B13=""),"",'Gainsay economics · Gainsay ope'!O44>'Gainsay drivers · Gainsay fixed'!B13))="",FALSE(),IF(ISERROR('Gainsay economics · Gainsay ope'!O44>'Gainsay drivers · Gainsay fixed'!B13),'Gainsay economics · Gainsay ope'!O44>'Gainsay drivers · Gainsay fixed'!B13,IF(OR('Gainsay economics · Gainsay ope'!O44="",'Gainsay drivers · Gainsay fixed'!B13=""),"",'Gainsay economics · Gainsay ope'!O44>'Gainsay drivers · Gainsay fixed'!B13))),1,0) -> 1 | P46: =IF(IF(IF(ISERROR('Gainsay economics · Gainsay ope'!P44>'Gainsay drivers · Gainsay fixed'!B13),'Gainsay economics · Gainsay ope'!P44>'Gainsay drivers · Gainsay fixed'!B13,IF(OR('Gainsay economics · Gainsay ope'!P44="",'Gainsay drivers · Gainsay fixed'!B13=""),"",'Gainsay economics · Gainsay ope'!P44>'Gainsay drivers · Gainsay fixed'!B13))="",FALSE(),IF(ISERROR('Gainsay economics · Gainsay ope'!P44>'Gainsay drivers · Gainsay fixed'!B13),'Gainsay economics · Gainsay ope'!P44>'Gainsay drivers · Gainsay fixed'!B13,IF(OR('Gainsay economics · Gainsay ope'!P44="",'Gainsay drivers · Gainsay fixed'!B13=""),"",'Gainsay economics · Gainsay ope'!P44>'Gainsay drivers · Gainsay fixed'!B13))),1,0) -> 1
A47: Raised access active conservative | B47: =IF(IF(IF(IFERROR(IF(ISERROR('Model inputs'!J143>0),'Model inputs'!J143>0,IF('Model inputs'!J143="","",'Model inputs'!J143>0))=TRUE(),FALSE()),TRUE(),IF(IFERROR('Model inputs'!B497=TRUE(),FALSE()),TRUE(),IF(OR(IF(ISERROR('Model inputs'!J143>0),'Model inputs'!J143>0,IF('Model inputs'!J143="","",'Model inputs'!J143>0))="",'Model inputs'!B497=""),"",OR(IF(ISERROR('Model inputs'!J143>0),'Model inputs'!J143>0,IF('Model inputs'!J143="","",'Model inputs'!J143>0)),'Model inputs'!B497))))="",FALSE(),IF(IFERROR(IF(ISERROR('Model inputs'!J143>0),'Model inputs'!J143>0,IF('Model inputs'!J143="","",'Model inputs'!J143>0))=TRUE(),FALSE()),TRUE(),IF(IFERROR('Model inputs'!B497=TRUE(),FALSE()),TRUE(),IF(OR(IF(ISERROR('Model inputs'!J143>0),'Model inputs'!J143>0,IF('Model inputs'!J143="","",'Model inputs'!J143>0))="",'Model inputs'!B497=""),"",OR(IF(ISERROR('Model inputs'!J143>0),'Model inputs'!J143>0,IF('Model inputs'!J143="","",'Model inputs'!J143>0)),'Model inputs'!B497))))),1,0) -> 0 | C47: =IF(IF(IF(IFERROR('Model inputs'!B1036=TRUE(),FALSE()),TRUE(),IF(IFERROR('Model inputs'!B499=TRUE(),FALSE()),TRUE(),IF(OR('Model inputs'!B1036="",'Model inputs'!B499=""),"",OR('Model inputs'!B1036,'Model inputs'!B499))))="",FALSE(),IF(IFERROR('Model inputs'!B1036=TRUE(),FALSE()),TRUE(),IF(IFERROR('Model inputs'!B499=TRUE(),FALSE()),TRUE(),IF(OR('Model inputs'!B1036="",'Model inputs'!B499=""),"",OR('Model inputs'!B1036,'Model inputs'!B499))))),1,0) -> 0 | D47: =IF(IF(IF(IFERROR('Model inputs'!B1037=TRUE(),FALSE()),TRUE(),IF(IFERROR('Model inputs'!B501=TRUE(),FALSE()),TRUE(),IF(OR('Model inputs'!B1037="",'Model inputs'!B501=""),"",OR('Model inputs'!B1037,'Model inputs'!B501))))="",FALSE(),IF(IFERROR('Model inputs'!B1037=TRUE(),FALSE()),TRUE(),IF(IFERROR('Model inputs'!B501=TRUE(),FALSE()),TRUE(),IF(OR('Model inputs'!B1037="",'Model inputs'!B501=""),"",OR('Model inputs'!B1037,'Model inputs'!B501))))),1,0) -> 0 | E47: =IF(IF(IF(IFERROR('Model inputs'!B1038=TRUE(),FALSE()),TRUE(),IF(IFERROR('Model inputs'!B503=TRUE(),FALSE()),TRUE(),IF(OR('Model inputs'!B1038="",'Model inputs'!B503=""),"",OR('Model inputs'!B1038,'Model inputs'!B503))))="",FALSE(),IF(IFERROR('Model inputs'!B1038=TRUE(),FALSE()),TRUE(),IF(IFERROR('Model inputs'!B503=TRUE(),FALSE()),TRUE(),IF(OR('Model inputs'!B1038="",'Model inputs'!B503=""),"",OR('Model inputs'!B1038,'Model inputs'!B503))))),1,0) -> 1 | F47: =IF(IF(IF(IFERROR('Model inputs'!B1039=TRUE(),FALSE()),TRUE(),IF(IFERROR('Model inputs'!B505=TRUE(),FALSE()),TRUE(),IF(OR('Model inputs'!B1039="",'Model inputs'!B505=""),"",OR('Model inputs'!B1039,'Model inputs'!B505))))="",FALSE(),IF(IFERROR('Model inputs'!B1039=TRUE(),FALSE()),TRUE(),IF(IFERROR('Model inputs'!B505=TRUE(),FALSE()),TRUE(),IF(OR('Model inputs'!B1039="",'Model inputs'!B505=""),"",OR('Model inputs'!B1039,'Model inputs'!B505))))),1,0) -> 1 | G47: =IF(IF(IF(IFERROR('Model inputs'!B1040=TRUE(),FALSE()),TRUE(),IF(IFERROR('Model inputs'!B507=TRUE(),FALSE()),TRUE(),IF(OR('Model inputs'!B1040="",'Model inputs'!B507=""),"",OR('Model inputs'!B1040,'Model inputs'!B507))))="",FALSE(),IF(IFERROR('Model inputs'!B1040=TRUE(),FALSE()),TRUE(),IF(IFERROR('Model inputs'!B507=TRUE(),FALSE()),TRUE(),IF(OR('Model inputs'!B1040="",'Model inputs'!B507=""),"",OR('Model inputs'!B1040,'Model inputs'!B507))))),1,0) -> 1 | H47: =IF(IF(IF(IFERROR('Model inputs'!B1041=TRUE(),FALSE()),TRUE(),IF(IFERROR('Model inputs'!B509=TRUE(),FALSE()),TRUE(),IF(OR('Model inputs'!B1041="",'Model inputs'!B509=""),"",OR('Model inputs'!B1041,'Model inputs'!B509))))="",FALSE(),IF(IFERROR('Model inputs'!B1041=TRUE(),FALSE()),TRUE(),IF(IFERROR('Model inputs'!B509=TRUE(),FALSE()),TRUE(),IF(OR('Model inputs'!B1041="",'Model inputs'!B509=""),"",OR('Model inputs'!B1041,'Model inputs'!B509))))),1,0) -> 1 | I47: =IF(IF(IF(IFERROR('Model inputs'!B1042=TRUE(),FALSE()),TRUE(),IF(IFERROR('Model inputs'!B511=TRUE(),FALSE()),TRUE(),IF(OR('Model inputs'!B1042="",'Model inputs'!B511=""),"",OR('Model inputs'!B1042,'Model inputs'!B511))))="",FALSE(),IF(IFERROR('Model inputs'!B1042=TRUE(),FALSE()),TRUE(),IF(IFERROR('Model inputs'!B511=TRUE(),FALSE()),TRUE(),IF(OR('Model inputs'!B1042="",'Model inputs'!B511=""),"",OR('Model inputs'!B1042,'Model inputs'!B511))))),1,0) -> 1 | J47: =IF(IF(IF(IFERROR('Model inputs'!B1043=TRUE(),FALSE()),TRUE(),IF(IFERROR('Model inputs'!B513=TRUE(),FALSE()),TRUE(),IF(OR('Model inputs'!B1043="",'Model inputs'!B513=""),"",OR('Model inputs'!B1043,'Model inputs'!B513))))="",FALSE(),IF(IFERROR('Model inputs'!B1043=TRUE(),FALSE()),TRUE(),IF(IFERROR('Model inputs'!B513=TRUE(),FALSE()),TRUE(),IF(OR('Model inputs'!B1043="",'Model inputs'!B513=""),"",OR('Model inputs'!B1043,'Model inputs'!B513))))),1,0) -> 1 | K47: =IF(IF(IF(IFERROR('Model inputs'!B1044=TRUE(),FALSE()),TRUE(),IF(IFERROR('Model inputs'!B515=TRUE(),FALSE()),TRUE(),IF(OR('Model inputs'!B1044="",'Model inputs'!B515=""),"",OR('Model inputs'!B1044,'Model inputs'!B515))))="",FALSE(),IF(IFERROR('Model inputs'!B1044=TRUE(),FALSE()),TRUE(),IF(IFERROR('Model inputs'!B515=TRUE(),FALSE()),TRUE(),IF(OR('Model inputs'!B1044="",'Model inputs'!B515=""),"",OR('Model inputs'!B1044,'Model inputs'!B515))))),1,0) -> 1 | L47: =IF(IF(IF(IFERROR('Model inputs'!B1045=TRUE(),FALSE()),TRUE(),IF(IFERROR('Model inputs'!B517=TRUE(),FALSE()),TRUE(),IF(OR('Model inputs'!B1045="",'Model inputs'!B517=""),"",OR('Model inputs'!B1045,'Model inputs'!B517))))="",FALSE(),IF(IFERROR('Model inputs'!B1045=TRUE(),FALSE()),TRUE(),IF(IFERROR('Model inputs'!B517=TRUE(),FALSE()),TRUE(),IF(OR('Model inputs'!B1045="",'Model inputs'!B517=""),"",OR('Model inputs'!B1045,'Model inputs'!B517))))),1,0) -> 1 | M47: =IF(IF(IF(IFERROR('Model inputs'!B1046=TRUE(),FALSE()),TRUE(),IF(IFERROR('Model inputs'!B519=TRUE(),FALSE()),TRUE(),IF(OR('Model inputs'!B1046="",'Model inputs'!B519=""),"",OR('Model inputs'!B1046,'Model inputs'!B519))))="",FALSE(),IF(IFERROR('Model inputs'!B1046=TRUE(),FALSE()),TRUE(),IF(IFERROR('Model inputs'!B519=TRUE(),FALSE()),TRUE(),IF(OR('Model inputs'!B1046="",'Model inputs'!B519=""),"",OR('Model inputs'!B1046,'Model inputs'!B519))))),1,0) -> 1 | N47: =IF(IF(IF(IFERROR('Model inputs'!B1047=TRUE(),FALSE()),TRUE(),IF(IFERROR('Model inputs'!B521=TRUE(),FALSE()),TRUE(),IF(OR('Model inputs'!B1047="",'Model inputs'!B521=""),"",OR('Model inputs'!B1047,'Model inputs'!B521))))="",FALSE(),IF(IFERROR('Model inputs'!B1047=TRUE(),FALSE()),TRUE(),IF(IFERROR('Model inputs'!B521=TRUE(),FALSE()),TRUE(),IF(OR('Model inputs'!B1047="",'Model inputs'!B521=""),"",OR('Model inputs'!B1047,'Model inputs'!B521))))),1,0) -> 1 | O47: =IF(IF(IF(IFERROR('Model inputs'!B1048=TRUE(),FALSE()),TRUE(),IF(IFERROR('Model inputs'!B523=TRUE(),FALSE()),TRUE(),IF(OR('Model inputs'!B1048="",'Model inputs'!B523=""),"",OR('Model inputs'!B1048,'Model inputs'!B523))))="",FALSE(),IF(IFERROR('Model inputs'!B1048=TRUE(),FALSE()),TRUE(),IF(IFERROR('Model inputs'!B523=TRUE(),FALSE()),TRUE(),IF(OR('Model inputs'!B1048="",'Model inputs'!B523=""),"",OR('Model inputs'!B1048,'Model inputs'!B523))))),1,0) -> 1 | P47: =IF(IF(IF(IFERROR('Model inputs'!B1049=TRUE(),FALSE()),TRUE(),IF(IFERROR('Model inputs'!B525=TRUE(),FALSE()),TRUE(),IF(OR('Model inputs'!B1049="",'Model inputs'!B525=""),"",OR('Model inputs'!B1049,'Model inputs'!B525))))="",FALSE(),IF(IFERROR('Model inputs'!B1049=TRUE(),FALSE()),TRUE(),IF(IFERROR('Model inputs'!B525=TRUE(),FALSE()),TRUE(),IF(OR('Model inputs'!B1049="",'Model inputs'!B525=""),"",OR('Model inputs'!B1049,'Model inputs'!B525))))),1,0) -> 1
A48: Raised access active measured | B48: =IF(IF(IF(IFERROR(IF(ISERROR('Model inputs'!J98>0),'Model inputs'!J98>0,IF('Model inputs'!J98="","",'Model inputs'!J98>0))=TRUE(),FALSE()),TRUE(),IF(IFERROR('Model inputs'!B561=TRUE(),FALSE()),TRUE(),IF(OR(IF(ISERROR('Model inputs'!J98>0),'Model inputs'!J98>0,IF('Model inputs'!J98="","",'Model inputs'!J98>0))="",'Model inputs'!B561=""),"",OR(IF(ISERROR('Model inputs'!J98>0),'Model inputs'!J98>0,IF('Model inputs'!J98="","",'Model inputs'!J98>0)),'Model inputs'!B561))))="",FALSE(),IF(IFERROR(IF(ISERROR('Model inputs'!J98>0),'Model inputs'!J98>0,IF('Model inputs'!J98="","",'Model inputs'!J98>0))=TRUE(),FALSE()),TRUE(),IF(IFERROR('Model inputs'!B561=TRUE(),FALSE()),TRUE(),IF(OR(IF(ISERROR('Model inputs'!J98>0),'Model inputs'!J98>0,IF('Model inputs'!J98="","",'Model inputs'!J98>0))="",'Model inputs'!B561=""),"",OR(IF(ISERROR('Model inputs'!J98>0),'Model inputs'!J98>0,IF('Model inputs'!J98="","",'Model inputs'!J98>0)),'Model inputs'!B561))))),1,0) -> 0 | C48: =IF(IF(IF(IFERROR('Model inputs'!B1050=TRUE(),FALSE()),TRUE(),IF(IFERROR('Model inputs'!B563=TRUE(),FALSE()),TRUE(),IF(OR('Model inputs'!B1050="",'Model inputs'!B563=""),"",OR('Model inputs'!B1050,'Model inputs'!B563))))="",FALSE(),IF(IFERROR('Model inputs'!B1050=TRUE(),FALSE()),TRUE(),IF(IFERROR('Model inputs'!B563=TRUE(),FALSE()),TRUE(),IF(OR('Model inputs'!B1050="",'Model inputs'!B563=""),"",OR('Model inputs'!B1050,'Model inputs'!B563))))),1,0) -> 0 | D48: =IF(IF(IF(IFERROR('Model inputs'!B1051=TRUE(),FALSE()),TRUE(),IF(IFERROR('Model inputs'!B565=TRUE(),FALSE()),TRUE(),IF(OR('Model inputs'!B1051="",'Model inputs'!B565=""),"",OR('Model inputs'!B1051,'Model inputs'!B565))))="",FALSE(),IF(IFERROR('Model inputs'!B1051=TRUE(),FALSE()),TRUE(),IF(IFERROR('Model inputs'!B565=TRUE(),FALSE()),TRUE(),IF(OR('Model inputs'!B1051="",'Model inputs'!B565=""),"",OR('Model inputs'!B1051,'Model inputs'!B565))))),1,0) -> 0 | E48: =IF(IF(IF(IFERROR('Model inputs'!B1052=TRUE(),FALSE()),TRUE(),IF(IFERROR('Model inputs'!B567=TRUE(),FALSE()),TRUE(),IF(OR('Model inputs'!B1052="",'Model inputs'!B567=""),"",OR('Model inputs'!B1052,'Model inputs'!B567))))="",FALSE(),IF(IFERROR('Model inputs'!B1052=TRUE(),FALSE()),TRUE(),IF(IFERROR('Model inputs'!B567=TRUE(),FALSE()),TRUE(),IF(OR('Model inputs'!B1052="",'Model inputs'!B567=""),"",OR('Model inputs'!B1052,'Model inputs'!B567))))),1,0) -> 0 | F48: =IF(IF(IF(IFERROR('Model inputs'!B1053=TRUE(),FALSE()),TRUE(),IF(IFERROR('Model inputs'!B569=TRUE(),FALSE()),TRUE(),IF(OR('Model inputs'!B1053="",'Model inputs'!B569=""),"",OR('Model inputs'!B1053,'Model inputs'!B569))))="",FALSE(),IF(IFERROR('Model inputs'!B1053=TRUE(),FALSE()),TRUE(),IF(IFERROR('Model inputs'!B569=TRUE(),FALSE()),TRUE(),IF(OR('Model inputs'!B1053="",'Model inputs'!B569=""),"",OR('Model inputs'!B1053,'Model inputs'!B569))))),1,0) -> 0 | G48: =IF(IF(IF(IFERROR('Model inputs'!B1054=TRUE(),FALSE()),TRUE(),IF(IFERROR('Model inputs'!B571=TRUE(),FALSE()),TRUE(),IF(OR('Model inputs'!B1054="",'Model inputs'!B571=""),"",OR('Model inputs'!B1054,'Model inputs'!B571))))="",FALSE(),IF(IFERROR('Model inputs'!B1054=TRUE(),FALSE()),TRUE(),IF(IFERROR('Model inputs'!B571=TRUE(),FALSE()),TRUE(),IF(OR('Model inputs'!B1054="",'Model inputs'!B571=""),"",OR('Model inputs'!B1054,'Model inputs'!B571))))),1,0) -> 0 | H48: =IF(IF(IF(IFERROR('Model inputs'!B1055=TRUE(),FALSE()),TRUE(),IF(IFERROR('Model inputs'!B573=TRUE(),FALSE()),TRUE(),IF(OR('Model inputs'!B1055="",'Model inputs'!B573=""),"",OR('Model inputs'!B1055,'Model inputs'!B573))))="",FALSE(),IF(IFERROR('Model inputs'!B1055=TRUE(),FALSE()),TRUE(),IF(IFERROR('Model inputs'!B573=TRUE(),FALSE()),TRUE(),IF(OR('Model inputs'!B1055="",'Model inputs'!B573=""),"",OR('Model inputs'!B1055,'Model inputs'!B573))))),1,0) -> 0 | I48: =IF(IF(IF(IFERROR('Model inputs'!B1056=TRUE(),FALSE()),TRUE(),IF(IFERROR('Model inputs'!B575=TRUE(),FALSE()),TRUE(),IF(OR('Model inputs'!B1056="",'Model inputs'!B575=""),"",OR('Model inputs'!B1056,'Model inputs'!B575))))="",FALSE(),IF(IFERROR('Model inputs'!B1056=TRUE(),FALSE()),TRUE(),IF(IFERROR('Model inputs'!B575=TRUE(),FALSE()),TRUE(),IF(OR('Model inputs'!B1056="",'Model inputs'!B575=""),"",OR('Model inputs'!B1056,'Model inputs'!B575))))),1,0) -> 0 | J48: =IF(IF(IF(IFERROR('Model inputs'!B1057=TRUE(),FALSE()),TRUE(),IF(IFERROR('Model inputs'!B577=TRUE(),FALSE()),TRUE(),IF(OR('Model inputs'!B1057="",'Model inputs'!B577=""),"",OR('Model inputs'!B1057,'Model inputs'!B577))))="",FALSE(),IF(IFERROR('Model inputs'!B1057=TRUE(),FALSE()),TRUE(),IF(IFERROR('Model inputs'!B577=TRUE(),FALSE()),TRUE(),IF(OR('Model inputs'!B1057="",'Model inputs'!B577=""),"",OR('Model inputs'!B1057,'Model inputs'!B577))))),1,0) -> 0 | K48: =IF(IF(IF(IFERROR('Model inputs'!B1058=TRUE(),FALSE()),TRUE(),IF(IFERROR('Model inputs'!B579=TRUE(),FALSE()),TRUE(),IF(OR('Model inputs'!B1058="",'Model inputs'!B579=""),"",OR('Model inputs'!B1058,'Model inputs'!B579))))="",FALSE(),IF(IFERROR('Model inputs'!B1058=TRUE(),FALSE()),TRUE(),IF(IFERROR('Model inputs'!B579=TRUE(),FALSE()),TRUE(),IF(OR('Model inputs'!B1058="",'Model inputs'!B579=""),"",OR('Model inputs'!B1058,'Model inputs'!B579))))),1,0) -> 1 | L48: =IF(IF(IF(IFERROR('Model inputs'!B1059=TRUE(),FALSE()),TRUE(),IF(IFERROR('Model inputs'!B581=TRUE(),FALSE()),TRUE(),IF(OR('Model inputs'!B1059="",'Model inputs'!B581=""),"",OR('Model inputs'!B1059,'Model inputs'!B581))))="",FALSE(),IF(IFERROR('Model inputs'!B1059=TRUE(),FALSE()),TRUE(),IF(IFERROR('Model inputs'!B581=TRUE(),FALSE()),TRUE(),IF(OR('Model inputs'!B1059="",'Model inputs'!B581=""),"",OR('Model inputs'!B1059,'Model inputs'!B581))))),1,0) -> 1 | M48: =IF(IF(IF(IFERROR('Model inputs'!B1060=TRUE(),FALSE()),TRUE(),IF(IFERROR('Model inputs'!B583=TRUE(),FALSE()),TRUE(),IF(OR('Model inputs'!B1060="",'Model inputs'!B583=""),"",OR('Model inputs'!B1060,'Model inputs'!B583))))="",FALSE(),IF(IFERROR('Model inputs'!B1060=TRUE(),FALSE()),TRUE(),IF(IFERROR('Model inputs'!B583=TRUE(),FALSE()),TRUE(),IF(OR('Model inputs'!B1060="",'Model inputs'!B583=""),"",OR('Model inputs'!B1060,'Model inputs'!B583))))),1,0) -> 1 | N48: =IF(IF(IF(IFERROR('Model inputs'!B1061=TRUE(),FALSE()),TRUE(),IF(IFERROR('Model inputs'!B585=TRUE(),FALSE()),TRUE(),IF(OR('Model inputs'!B1061="",'Model inputs'!B585=""),"",OR('Model inputs'!B1061,'Model inputs'!B585))))="",FALSE(),IF(IFERROR('Model inputs'!B1061=TRUE(),FALSE()),TRUE(),IF(IFERROR('Model inputs'!B585=TRUE(),FALSE()),TRUE(),IF(OR('Model inputs'!B1061="",'Model inputs'!B585=""),"",OR('Model inputs'!B1061,'Model inputs'!B585))))),1,0) -> 1 | O48: =IF(IF(IF(IFERROR('Model inputs'!B1062=TRUE(),FALSE()),TRUE(),IF(IFERROR('Model inputs'!B587=TRUE(),FALSE()),TRUE(),IF(OR('Model inputs'!B1062="",'Model inputs'!B587=""),"",OR('Model inputs'!B1062,'Model inputs'!B587))))="",FALSE(),IF(IFERROR('Model inputs'!B1062=TRUE(),FALSE()),TRUE(),IF(IFERROR('Model inputs'!B587=TRUE(),FALSE()),TRUE(),IF(OR('Model inputs'!B1062="",'Model inputs'!B587=""),"",OR('Model inputs'!B1062,'Model inputs'!B587))))),1,0) -> 1 | P48: =IF(IF(IF(IFERROR('Model inputs'!B1063=TRUE(),FALSE()),TRUE(),IF(IFERROR('Model inputs'!B589=TRUE(),FALSE()),TRUE(),IF(OR('Model inputs'!B1063="",'Model inputs'!B589=""),"",OR('Model inputs'!B1063,'Model inputs'!B589))))="",FALSE(),IF(IFERROR('Model inputs'!B1063=TRUE(),FALSE()),TRUE(),IF(IFERROR('Model inputs'!B589=TRUE(),FALSE()),TRUE(),IF(OR('Model inputs'!B1063="",'Model inputs'!B589=""),"",OR('Model inputs'!B1063,'Model inputs'!B589))))),1,0) -> 1
A49: Raised API access cost conservative | B49: ='Gainsay economics · Gainsay ope'!B47*'Gainsay drivers · Gainsay fixed'!B30 -> 0 | C49: ='Gainsay economics · Gainsay ope'!C47*'Gainsay drivers · Gainsay fixed'!B30 -> 0 | D49: ='Gainsay economics · Gainsay ope'!D47*'Gainsay drivers · Gainsay fixed'!B30 -> 0 | E49: ='Gainsay economics · Gainsay ope'!E47*'Gainsay drivers · Gainsay fixed'!B30 -> 0 | F49: ='Gainsay economics · Gainsay ope'!F47*'Gainsay drivers · Gainsay fixed'!B30 -> 0 | G49: ='Gainsay economics · Gainsay ope'!G47*'Gainsay drivers · Gainsay fixed'!B30 -> 0 | H49: ='Gainsay economics · Gainsay ope'!H47*'Gainsay drivers · Gainsay fixed'!B30 -> 0 | I49: ='Gainsay economics · Gainsay ope'!I47*'Gainsay drivers · Gainsay fixed'!B30 -> 0 | J49: ='Gainsay economics · Gainsay ope'!J47*'Gainsay drivers · Gainsay fixed'!B30 -> 0 | K49: ='Gainsay economics · Gainsay ope'!K47*'Gainsay drivers · Gainsay fixed'!B30 -> 0 | L49: ='Gainsay economics · Gainsay ope'!L47*'Gainsay drivers · Gainsay fixed'!B30 -> 0 | M49: ='Gainsay economics · Gainsay ope'!M47*'Gainsay drivers · Gainsay fixed'!B30 -> 0 | N49: ='Gainsay economics · Gainsay ope'!N47*'Gainsay drivers · Gainsay fixed'!B30 -> 0 | O49: ='Gainsay economics · Gainsay ope'!O47*'Gainsay drivers · Gainsay fixed'!B30 -> 0 | P49: ='Gainsay economics · Gainsay ope'!P47*'Gainsay drivers · Gainsay fixed'!B30 -> 0
A50: Raised API access cost measured | B50: ='Gainsay economics · Gainsay ope'!B48*'Gainsay drivers · Gainsay fixed'!B30 -> 0 | C50: ='Gainsay economics · Gainsay ope'!C48*'Gainsay drivers · Gainsay fixed'!B30 -> 0 | D50: ='Gainsay economics · Gainsay ope'!D48*'Gainsay drivers · Gainsay fixed'!B30 -> 0 | E50: ='Gainsay economics · Gainsay ope'!E48*'Gainsay drivers · Gainsay fixed'!B30 -> 0 | F50: ='Gainsay economics · Gainsay ope'!F48*'Gainsay drivers · Gainsay fixed'!B30 -> 0 | G50: ='Gainsay economics · Gainsay ope'!G48*'Gainsay drivers · Gainsay fixed'!B30 -> 0 | H50: ='Gainsay economics · Gainsay ope'!H48*'Gainsay drivers · Gainsay fixed'!B30 -> 0 | I50: ='Gainsay economics · Gainsay ope'!I48*'Gainsay drivers · Gainsay fixed'!B30 -> 0 | J50: ='Gainsay economics · Gainsay ope'!J48*'Gainsay drivers · Gainsay fixed'!B30 -> 0 | K50: ='Gainsay economics · Gainsay ope'!K48*'Gainsay drivers · Gainsay fixed'!B30 -> 0 | L50: ='Gainsay economics · Gainsay ope'!L48*'Gainsay drivers · Gainsay fixed'!B30 -> 0 | M50: ='Gainsay economics · Gainsay ope'!M48*'Gainsay drivers · Gainsay fixed'!B30 -> 0 | N50: ='Gainsay economics · Gainsay ope'!N48*'Gainsay drivers · Gainsay fixed'!B30 -> 0 | O50: ='Gainsay economics · Gainsay ope'!O48*'Gainsay drivers · Gainsay fixed'!B30 -> 0 | P50: ='Gainsay economics · Gainsay ope'!P48*'Gainsay drivers · Gainsay fixed'!B30 -> 0
A51: Monthly result measured API | B51: ='Gainsay economics · Gainsay ope'!B11+'Gainsay economics · Gainsay ope'!B49-'Gainsay economics · Gainsay ope'!B50 -> -857.193 | C51: ='Gainsay economics · Gainsay ope'!C11+'Gainsay economics · Gainsay ope'!C49-'Gainsay economics · Gainsay ope'!C50 -> -773.74916 | D51: ='Gainsay economics · Gainsay ope'!D11+'Gainsay economics · Gainsay ope'!D49-'Gainsay economics · Gainsay ope'!D50 -> -688.40633 | E51: ='Gainsay economics · Gainsay ope'!E11+'Gainsay economics · Gainsay ope'!E49-'Gainsay economics · Gainsay ope'!E50 -> -601.00137 | F51: ='Gainsay economics · Gainsay ope'!F11+'Gainsay economics · Gainsay ope'!F49-'Gainsay economics · Gainsay ope'!F50 -> -511.36502 | G51: ='Gainsay economics · Gainsay ope'!G11+'Gainsay economics · Gainsay ope'!G49-'Gainsay economics · Gainsay ope'!G50 -> -419.32155 | H51: ='Gainsay economics · Gainsay ope'!H11+'Gainsay economics · Gainsay ope'!H49-'Gainsay economics · Gainsay ope'!H50 -> -324.68835 | I51: ='Gainsay economics · Gainsay ope'!I11+'Gainsay economics · Gainsay ope'!I49-'Gainsay economics · Gainsay ope'!I50 -> -227.27557 | ... P51: ='Gainsay economics · Gainsay ope'!P11+'Gainsay economics · Gainsay ope'!P49-'Gainsay economics · Gainsay ope'!P50 -> 150.11842
A52: Cumulative cash measured API | B52: =IF(IF(DATE(2026,10,1)=DATE(2026,10,1),'Gainsay drivers · Gainsay fixed'!B21-'Gainsay drivers · Gainsay fixed'!B22,IF('Model inputs'!J31="","",'Model inputs'!J31))="",0,IF(DATE(2026,10,1)=DATE(2026,10,1),'Gainsay drivers · Gainsay fixed'!B21-'Gainsay drivers · Gainsay fixed'!B22,IF('Model inputs'!J31="","",'Model inputs'!J31)))+'Gainsay economics · Gainsay ope'!B51 -> 3642.807 | C52: =IF(IF(DATE(2026,11,1)=DATE(2026,10,1),'Gainsay drivers · Gainsay fixed'!B21-'Gainsay drivers · Gainsay fixed'!B22,IF('Gainsay economics · Gainsay ope'!B52="","",'Gainsay economics · Gainsay ope'!B52))="",0,IF(DATE(2026,11,1)=DATE(2026,10,1),'Gainsay drivers · Gainsay fixed'!B21-'Gainsay drivers · Gainsay fixed'!B22,IF('Gainsay economics · Gainsay ope'!B52="","",'Gainsay economics · Gainsay ope'!B52)))+'Gainsay economics · Gainsay ope'!C51 -> 2869.0578 | D52: =IF(IF(DATE(2026,12,1)=DATE(2026,10,1),'Gainsay drivers · Gainsay fixed'!B21-'Gainsay drivers · Gainsay fixed'!B22,IF('Gainsay economics · Gainsay ope'!C52="","",'Gainsay economics · Gainsay ope'!C52))="",0,IF(DATE(2026,12,1)=DATE(2026,10,1),'Gainsay drivers · Gainsay fixed'!B21-'Gainsay drivers · Gainsay fixed'!B22,IF('Gainsay economics · Gainsay ope'!C52="","",'Gainsay economics · Gainsay ope'!C52)))+'Gainsay economics · Gainsay ope'!D51 -> 2180.6515 | E52: =IF(IF(DATE(2027,1,1)=DATE(2026,10,1),'Gainsay drivers · Gainsay fixed'!B21-'Gainsay drivers · Gainsay fixed'!B22,IF('Gainsay economics · Gainsay ope'!D52="","",'Gainsay economics · Gainsay ope'!D52))="",0,IF(DATE(2027,1,1)=DATE(2026,10,1),'Gainsay drivers · Gainsay fixed'!B21-'Gainsay drivers · Gainsay fixed'!B22,IF('Gainsay economics · Gainsay ope'!D52="","",'Gainsay economics · Gainsay ope'!D52)))+'Gainsay economics · Gainsay ope'!E51 -> 1579.6501 | F52: =IF(IF(DATE(2027,2,1)=DATE(2026,10,1),'Gainsay drivers · Gainsay fixed'!B21-'Gainsay drivers · Gainsay fixed'!B22,IF('Gainsay economics · Gainsay ope'!E52="","",'Gainsay economics · Gainsay ope'!E52))="",0,IF(DATE(2027,2,1)=DATE(2026,10,1),'Gainsay drivers · Gainsay fixed'!B21-'Gainsay drivers · Gainsay fixed'!B22,IF('Gainsay economics · Gainsay ope'!E52="","",'Gainsay economics · Gainsay ope'!E52)))+'Gainsay economics · Gainsay ope'!F51 -> 1068.2851 | G52: =IF(IF(DATE(2027,3,1)=DATE(2026,10,1),'Gainsay drivers · Gainsay fixed'!B21-'Gainsay drivers · Gainsay fixed'!B22,IF('Gainsay economics · Gainsay ope'!F52="","",'Gainsay economics · Gainsay ope'!F52))="",0,IF(DATE(2027,3,1)=DATE(2026,10,1),'Gainsay drivers · Gainsay fixed'!B21-'Gainsay drivers · Gainsay fixed'!B22,IF('Gainsay economics · Gainsay ope'!F52="","",'Gainsay economics · Gainsay ope'!F52)))+'Gainsay economics · Gainsay ope'!G51 -> 648.96356 | H52: =IF(IF(DATE(2027,4,1)=DATE(2026,10,1),'Gainsay drivers · Gainsay fixed'!B21-'Gainsay drivers · Gainsay fixed'!B22,IF('Gainsay economics · Gainsay ope'!G52="","",'Gainsay economics · Gainsay ope'!G52))="",0,IF(DATE(2027,4,1)=DATE(2026,10,1),'Gainsay drivers · Gainsay fixed'!B21-'Gainsay drivers · Gainsay fixed'!B22,IF('Gainsay economics · Gainsay ope'!G52="","",'Gainsay economics · Gainsay ope'!G52)))+'Gainsay economics · Gainsay ope'!H51 -> 324.27521 | I52: =IF(IF(DATE(2027,5,1)=DATE(2026,10,1),'Gainsay drivers · Gainsay fixed'!B21-'Gainsay drivers · Gainsay fixed'!B22,IF('Gainsay economics · Gainsay ope'!H52="","",'Gainsay economics · Gainsay ope'!H52))="",0,IF(DATE(2027,5,1)=DATE(2026,10,1),'Gainsay drivers · Gainsay fixed'!B21-'Gainsay drivers · Gainsay fixed'!B22,IF('Gainsay economics · Gainsay ope'!H52="","",'Gainsay economics · Gainsay ope'!H52)))+'Gainsay economics · Gainsay ope'!I51 -> 96.99964 | J52: =IF(IF(DATE(2027,6,1)=DATE(2026,10,1),'Gainsay drivers · Gainsay fixed'!B21-'Gainsay drivers · Gainsay fixed'!B22,IF('Gainsay economics · Gainsay ope'!I52="","",'Gainsay economics · Gainsay ope'!I52))="",0,IF(DATE(2027,6,1)=DATE(2026,10,1),'Gainsay drivers · Gainsay fixed'!B21-'Gainsay drivers · Gainsay fixed'!B22,IF('Gainsay economics · Gainsay ope'!I52="","",'Gainsay economics · Gainsay ope'!I52)))+'Gainsay economics · Gainsay ope'!J51 -> -29.886032 | K52: =IF(IF(DATE(2027,7,1)=DATE(2026,10,1),'Gainsay drivers · Gainsay fixed'!B21-'Gainsay drivers · Gainsay fixed'!B22,IF('Gainsay economics · Gainsay ope'!J52="","",'Gainsay economics · Gainsay ope'!J52))="",0,IF(DATE(2027,7,1)=DATE(2026,10,1),'Gainsay drivers · Gainsay fixed'!B21-'Gainsay drivers · Gainsay fixed'!B22,IF('Gainsay economics · Gainsay ope'!J52="","",'Gainsay economics · Gainsay ope'!J52)))+'Gainsay economics · Gainsay ope'!K51 -> -53.199018 | L52: =IF(IF(DATE(2027,8,1)=DATE(2026,10,1),'Gainsay drivers · Gainsay fixed'!B21-'Gainsay drivers · Gainsay fixed'!B22,IF('Gainsay economics · Gainsay ope'!K52="","",'Gainsay economics · Gainsay ope'!K52))="",0,IF(DATE(2027,8,1)=DATE(2026,10,1),'Gainsay drivers · Gainsay fixed'!B21-'Gainsay drivers · Gainsay fixed'!B22,IF('Gainsay economics · Gainsay ope'!K52="","",'Gainsay economics · Gainsay ope'!K52)))+'Gainsay economics · Gainsay ope'!L51 -> 30.457708 | M52: =IF(IF(DATE(2027,9,1)=DATE(2026,10,1),'Gainsay drivers · Gainsay fixed'!B21-'Gainsay drivers · Gainsay fixed'!B22,IF('Gainsay economics · Gainsay ope'!L52="","",'Gainsay economics · Gainsay ope'!L52))="",0,IF(DATE(2027,9,1)=DATE(2026,10,1),'Gainsay drivers · Gainsay fixed'!B21-'Gainsay drivers · Gainsay fixed'!B22,IF('Gainsay economics · Gainsay ope'!L52="","",'Gainsay economics · Gainsay ope'!L52)))+'Gainsay economics · Gainsay ope'!M51 -> 224.70447 | N52: =IF(IF(DATE(2027,10,1)=DATE(2026,10,1),'Gainsay drivers · Gainsay fixed'!B21-'Gainsay drivers · Gainsay fixed'!B22,IF('Gainsay economics · Gainsay ope'!M52="","",'Gainsay economics · Gainsay ope'!M52))="",0,IF(DATE(2027,10,1)=DATE(2026,10,1),'Gainsay drivers · Gainsay fixed'!B21-'Gainsay drivers · Gainsay fixed'!B22,IF('Gainsay economics · Gainsay ope'!M52="","",'Gainsay economics · Gainsay ope'!M52)))+'Gainsay economics · Gainsay ope'!N51 -> 533.39445 | O52: =IF(IF(DATE(2027,11,1)=DATE(2026,10,1),'Gainsay drivers · Gainsay fixed'!B21-'Gainsay drivers · Gainsay fixed'!B22,IF('Gainsay economics · Gainsay ope'!N52="","",'Gainsay economics · Gainsay ope'!N52))="",0,IF(DATE(2027,11,1)=DATE(2026,10,1),'Gainsay drivers · Gainsay fixed'!B21-'Gainsay drivers · Gainsay fixed'!B22,IF('Gainsay economics · Gainsay ope'!N52="","",'Gainsay economics · Gainsay ope'!N52)))+'Gainsay economics · Gainsay ope'!O51 -> 960.62379 | P52: =IF(IF(DATE(2027,12,1)=DATE(2026,10,1),'Gainsay drivers · Gainsay fixed'!B21-'Gainsay drivers · Gainsay fixed'!B22,IF('Gainsay economics · Gainsay ope'!O52="","",'Gainsay economics · Gainsay ope'!O52))="",0,IF(DATE(2027,12,1)=DATE(2026,10,1),'Gainsay drivers · Gainsay fixed'!B21-'Gainsay drivers · Gainsay fixed'!B22,IF('Gainsay economics · Gainsay ope'!O52="","",'Gainsay economics · Gainsay ope'!O52)))+'Gainsay economics · Gainsay ope'!P51 -> 1110.7422
A53: Three month cash floor | B53: ='Gainsay drivers · Gainsay fixed'!B31*('Gainsay drivers · Gainsay prici'!B10+'Gainsay drivers · Gainsay fixed'!B30) -> 3031.8 | C53: ='Gainsay drivers · Gainsay fixed'!B31*('Gainsay drivers · Gainsay prici'!B10+'Gainsay drivers · Gainsay fixed'!B30) -> 3031.8 | D53: ='Gainsay drivers · Gainsay fixed'!B31*('Gainsay drivers · Gainsay prici'!B10+'Gainsay drivers · Gainsay fixed'!B30) -> 3031.8 | E53: ='Gainsay drivers · Gainsay fixed'!B31*('Gainsay drivers · Gainsay prici'!B10+'Gainsay drivers · Gainsay fixed'!B30) -> 3031.8 | F53: ='Gainsay drivers · Gainsay fixed'!B31*('Gainsay drivers · Gainsay prici'!B10+'Gainsay drivers · Gainsay fixed'!B30) -> 3031.8 | G53: ='Gainsay drivers · Gainsay fixed'!B31*('Gainsay drivers · Gainsay prici'!B10+'Gainsay drivers · Gainsay fixed'!B30) -> 3031.8 | H53: ='Gainsay drivers · Gainsay fixed'!B31*('Gainsay drivers · Gainsay prici'!B10+'Gainsay drivers · Gainsay fixed'!B30) -> 3031.8 | I53: ='Gainsay drivers · Gainsay fixed'!B31*('Gainsay drivers · Gainsay prici'!B10+'Gainsay drivers · Gainsay fixed'!B30) -> 3031.8 | J53: ='Gainsay drivers · Gainsay fixed'!B31*('Gainsay drivers · Gainsay prici'!B10+'Gainsay drivers · Gainsay fixed'!B30) -> 3031.8 | K53: ='Gainsay drivers · Gainsay fixed'!B31*('Gainsay drivers · Gainsay prici'!B10+'Gainsay drivers · Gainsay fixed'!B30) -> 3031.8 | L53: ='Gainsay drivers · Gainsay fixed'!B31*('Gainsay drivers · Gainsay prici'!B10+'Gainsay drivers · Gainsay fixed'!B30) -> 3031.8 | M53: ='Gainsay drivers · Gainsay fixed'!B31*('Gainsay drivers · Gainsay prici'!B10+'Gainsay drivers · Gainsay fixed'!B30) -> 3031.8 | N53: ='Gainsay drivers · Gainsay fixed'!B31*('Gainsay drivers · Gainsay prici'!B10+'Gainsay drivers · Gainsay fixed'!B30) -> 3031.8 | O53: ='Gainsay drivers · Gainsay fixed'!B31*('Gainsay drivers · Gainsay prici'!B10+'Gainsay drivers · Gainsay fixed'!B30) -> 3031.8 | P53: ='Gainsay drivers · Gainsay fixed'!B31*('Gainsay drivers · Gainsay prici'!B10+'Gainsay drivers · Gainsay fixed'!B30) -> 3031.8
A54: Monthly reserve buffer shortfall | B54: =MAX('Gainsay economics · Gainsay ope'!B53-'Gainsay economics · Gainsay ope'!B12,0) -> 0 | C54: =MAX('Gainsay economics · Gainsay ope'!C53-'Gainsay economics · Gainsay ope'!C12,0) -> 162.74216 | D54: =MAX('Gainsay economics · Gainsay ope'!D53-'Gainsay economics · Gainsay ope'!D12,0) -> 851.14849 | E54: =MAX('Gainsay economics · Gainsay ope'!E53-'Gainsay economics · Gainsay ope'!E12,0) -> 1452.1499 | F54: =MAX('Gainsay economics · Gainsay ope'!F53-'Gainsay economics · Gainsay ope'!F12,0) -> 1963.5149 | G54: =MAX('Gainsay economics · Gainsay ope'!G53-'Gainsay economics · Gainsay ope'!G12,0) -> 2382.8364 | H54: =MAX('Gainsay economics · Gainsay ope'!H53-'Gainsay economics · Gainsay ope'!H12,0) -> 2707.5248 | I54: =MAX('Gainsay economics · Gainsay ope'!I53-'Gainsay economics · Gainsay ope'!I12,0) -> 2934.8004 | ... P54: =MAX('Gainsay economics · Gainsay ope'!P53-'Gainsay economics · Gainsay ope'!P12,0) -> 1921.0578
A55: Cumulative cash at recommended opening | B55: ='Gainsay economics · Gainsay ope'!B12+'Gainsay drivers · Gainsay prici'!B23-'Gainsay drivers · Gainsay fixed'!B21 -> 7142.807 | C55: ='Gainsay economics · Gainsay ope'!C12+'Gainsay drivers · Gainsay prici'!B23-'Gainsay drivers · Gainsay fixed'!B21 -> 6369.0578 | D55: ='Gainsay economics · Gainsay ope'!D12+'Gainsay drivers · Gainsay prici'!B23-'Gainsay drivers · Gainsay fixed'!B21 -> 5680.6515 | E55: ='Gainsay economics · Gainsay ope'!E12+'Gainsay drivers · Gainsay prici'!B23-'Gainsay drivers · Gainsay fixed'!B21 -> 5079.6501 | F55: ='Gainsay economics · Gainsay ope'!F12+'Gainsay drivers · Gainsay prici'!B23-'Gainsay drivers · Gainsay fixed'!B21 -> 4568.2851 | G55: ='Gainsay economics · Gainsay ope'!G12+'Gainsay drivers · Gainsay prici'!B23-'Gainsay drivers · Gainsay fixed'!B21 -> 4148.9636 | H55: ='Gainsay economics · Gainsay ope'!H12+'Gainsay drivers · Gainsay prici'!B23-'Gainsay drivers · Gainsay fixed'!B21 -> 3824.2752 | I55: ='Gainsay economics · Gainsay ope'!I12+'Gainsay drivers · Gainsay prici'!B23-'Gainsay drivers · Gainsay fixed'!B21 -> 3596.9996 | J55: ='Gainsay economics · Gainsay ope'!J12+'Gainsay drivers · Gainsay prici'!B23-'Gainsay drivers · Gainsay fixed'!B21 -> 3470.114 | K55: ='Gainsay economics · Gainsay ope'!K12+'Gainsay drivers · Gainsay prici'!B23-'Gainsay drivers · Gainsay fixed'!B21 -> 3446.801 | L55: ='Gainsay economics · Gainsay ope'!L12+'Gainsay drivers · Gainsay prici'!B23-'Gainsay drivers · Gainsay fixed'!B21 -> 3530.4577 | M55: ='Gainsay economics · Gainsay ope'!M12+'Gainsay drivers · Gainsay prici'!B23-'Gainsay drivers · Gainsay fixed'!B21 -> 3724.7045 | N55: ='Gainsay economics · Gainsay ope'!N12+'Gainsay drivers · Gainsay prici'!B23-'Gainsay drivers · Gainsay fixed'!B21 -> 4033.3945 | O55: ='Gainsay economics · Gainsay ope'!O12+'Gainsay drivers · Gainsay prici'!B23-'Gainsay drivers · Gainsay fixed'!B21 -> 4460.6238 | P55: ='Gainsay economics · Gainsay ope'!P12+'Gainsay drivers · Gainsay prici'!B23-'Gainsay drivers · Gainsay fixed'!B21 -> 4610.7422
A56: Recommended cash buffer check | B56: ='Gainsay economics · Gainsay ope'!B55-'Gainsay economics · Gainsay ope'!B53 -> 4111.007 | C56: ='Gainsay economics · Gainsay ope'!C55-'Gainsay economics · Gainsay ope'!C53 -> 3337.2578 | D56: ='Gainsay economics · Gainsay ope'!D55-'Gainsay economics · Gainsay ope'!D53 -> 2648.8515 | E56: ='Gainsay economics · Gainsay ope'!E55-'Gainsay economics · Gainsay ope'!E53 -> 2047.8501 | F56: ='Gainsay economics · Gainsay ope'!F55-'Gainsay economics · Gainsay ope'!F53 -> 1536.4851 | G56: ='Gainsay economics · Gainsay ope'!G55-'Gainsay economics · Gainsay ope'!G53 -> 1117.1636 | H56: ='Gainsay economics · Gainsay ope'!H55-'Gainsay economics · Gainsay ope'!H53 -> 792.47521 | I56: ='Gainsay economics · Gainsay ope'!I55-'Gainsay economics · Gainsay ope'!I53 -> 565.19964 | ... P56: ='Gainsay economics · Gainsay ope'!P55-'Gainsay economics · Gainsay ope'!P53 -> 1578.9422

Sheet Gainsay economics · Gainsay dat
A1: Gainsay economics · Gainsay data-fee cash sensitivity
A2: Financial model (3 pages) · Main Scenario
A4: Variable / dimension | B4: 2026-10 | C4: 2026-11 | D4: 2026-12 | E4: 2027-01 | F4: 2027-02 | G4: 2027-03 | H4: 2027-04 | I4: 2027-05 | J4: 2027-06 | K4: 2027-07 | L4: 2027-08 | M4: 2027-09 | N4: 2027-10 | O4: 2027-11 | P4: 2027-12
A5: Fee-test ending cash | B5: ="" | C5: ="" | D5: ="" | E5: ="" | F5: ="" | G5: ="" | H5: ="" | I5: ="" | ... P5: =""
A6: High fee stress | B6: ='Gainsay economics · Gainsay ope'!B33+('Gainsay drivers · Gainsay fixed'!B20-'Gainsay drivers · Gainsay data-'!B5)*IF(IF(IFERROR(YEAR(DATE(2026,10,1))=2026=TRUE(),FALSE()),TRUE(),IF(IFERROR(MONTH(DATE(2026,10,1))<10=TRUE(),FALSE()),TRUE(),OR(YEAR(DATE(2026,10,1))=2026,MONTH(DATE(2026,10,1))<10))),1,2) -> -6107.193 | C6: ='Gainsay economics · Gainsay ope'!C33+('Gainsay drivers · Gainsay fixed'!B20-'Gainsay drivers · Gainsay data-'!B5)*IF(IF(IFERROR(YEAR(DATE(2026,11,1))=2026=TRUE(),FALSE()),TRUE(),IF(IFERROR(MONTH(DATE(2026,11,1))<10=TRUE(),FALSE()),TRUE(),OR(YEAR(DATE(2026,11,1))=2026,MONTH(DATE(2026,11,1))<10))),1,2) -> -6630.9422 | D6: ='Gainsay economics · Gainsay ope'!D33+('Gainsay drivers · Gainsay fixed'!B20-'Gainsay drivers · Gainsay data-'!B5)*IF(IF(IFERROR(YEAR(DATE(2026,12,1))=2026=TRUE(),FALSE()),TRUE(),IF(IFERROR(MONTH(DATE(2026,12,1))<10=TRUE(),FALSE()),TRUE(),OR(YEAR(DATE(2026,12,1))=2026,MONTH(DATE(2026,12,1))<10))),1,2) -> -7069.3485 | E6: ='Gainsay economics · Gainsay ope'!E33+('Gainsay drivers · Gainsay fixed'!B20-'Gainsay drivers · Gainsay data-'!B5)*IF(IF(IFERROR(YEAR(DATE(2027,1,1))=2026=TRUE(),FALSE()),TRUE(),IF(IFERROR(MONTH(DATE(2027,1,1))<10=TRUE(),FALSE()),TRUE(),OR(YEAR(DATE(2027,1,1))=2026,MONTH(DATE(2027,1,1))<10))),1,2) -> -7420.3499 | F6: ='Gainsay economics · Gainsay ope'!F33+('Gainsay drivers · Gainsay fixed'!B20-'Gainsay drivers · Gainsay data-'!B5)*IF(IF(IFERROR(YEAR(DATE(2027,2,1))=2026=TRUE(),FALSE()),TRUE(),IF(IFERROR(MONTH(DATE(2027,2,1))<10=TRUE(),FALSE()),TRUE(),OR(YEAR(DATE(2027,2,1))=2026,MONTH(DATE(2027,2,1))<10))),1,2) -> -7681.7149 | G6: ='Gainsay economics · Gainsay ope'!G33+('Gainsay drivers · Gainsay fixed'!B20-'Gainsay drivers · Gainsay data-'!B5)*IF(IF(IFERROR(YEAR(DATE(2027,3,1))=2026=TRUE(),FALSE()),TRUE(),IF(IFERROR(MONTH(DATE(2027,3,1))<10=TRUE(),FALSE()),TRUE(),OR(YEAR(DATE(2027,3,1))=2026,MONTH(DATE(2027,3,1))<10))),1,2) -> -7851.0364 | H6: ='Gainsay economics · Gainsay ope'!H33+('Gainsay drivers · Gainsay fixed'!B20-'Gainsay drivers · Gainsay data-'!B5)*IF(IF(IFERROR(YEAR(DATE(2027,4,1))=2026=TRUE(),FALSE()),TRUE(),IF(IFERROR(MONTH(DATE(2027,4,1))<10=TRUE(),FALSE()),TRUE(),OR(YEAR(DATE(2027,4,1))=2026,MONTH(DATE(2027,4,1))<10))),1,2) -> -7925.7248 | I6: ='Gainsay economics · Gainsay ope'!I33+('Gainsay drivers · Gainsay fixed'!B20-'Gainsay drivers · Gainsay data-'!B5)*IF(IF(IFERROR(YEAR(DATE(2027,5,1))=2026=TRUE(),FALSE()),TRUE(),IF(IFERROR(MONTH(DATE(2027,5,1))<10=TRUE(),FALSE()),TRUE(),OR(YEAR(DATE(2027,5,1))=2026,MONTH(DATE(2027,5,1))<10))),1,2) -> -7903.0004 | J6: ='Gainsay economics · Gainsay ope'!J33+('Gainsay drivers · Gainsay fixed'!B20-'Gainsay drivers · Gainsay data-'!B5)*IF(IF(IFERROR(YEAR(DATE(2027,6,1))=2026=TRUE(),FALSE()),TRUE(),IF(IFERROR(MONTH(DATE(2027,6,1))<10=TRUE(),FALSE()),TRUE(),OR(YEAR(DATE(2027,6,1))=2026,MONTH(DATE(2027,6,1))<10))),1,2) -> -7779.886 | K6: ='Gainsay economics · Gainsay ope'!K33+('Gainsay drivers · Gainsay fixed'!B20-'Gainsay drivers · Gainsay data-'!B5)*IF(IF(IFERROR(YEAR(DATE(2027,7,1))=2026=TRUE(),FALSE()),TRUE(),IF(IFERROR(MONTH(DATE(2027,7,1))<10=TRUE(),FALSE()),TRUE(),OR(YEAR(DATE(2027,7,1))=2026,MONTH(DATE(2027,7,1))<10))),1,2) -> -7553.199 | L6: ='Gainsay economics · Gainsay ope'!L33+('Gainsay drivers · Gainsay fixed'!B20-'Gainsay drivers · Gainsay data-'!B5)*IF(IF(IFERROR(YEAR(DATE(2027,8,1))=2026=TRUE(),FALSE()),TRUE(),IF(IFERROR(MONTH(DATE(2027,8,1))<10=TRUE(),FALSE()),TRUE(),OR(YEAR(DATE(2027,8,1))=2026,MONTH(DATE(2027,8,1))<10))),1,2) -> -7219.5423 | M6: ='Gainsay economics · Gainsay ope'!M33+('Gainsay drivers · Gainsay fixed'!B20-'Gainsay drivers · Gainsay data-'!B5)*IF(IF(IFERROR(YEAR(DATE(2027,9,1))=2026=TRUE(),FALSE()),TRUE(),IF(IFERROR(MONTH(DATE(2027,9,1))<10=TRUE(),FALSE()),TRUE(),OR(YEAR(DATE(2027,9,1))=2026,MONTH(DATE(2027,9,1))<10))),1,2) -> -6775.2955 | N6: ='Gainsay economics · Gainsay ope'!N33+('Gainsay drivers · Gainsay fixed'!B20-'Gainsay drivers · Gainsay data-'!B5)*IF(IF(IFERROR(YEAR(DATE(2027,10,1))=2026=TRUE(),FALSE()),TRUE(),IF(IFERROR(MONTH(DATE(2027,10,1))<10=TRUE(),FALSE()),TRUE(),OR(YEAR(DATE(2027,10,1))=2026,MONTH(DATE(2027,10,1))<10))),1,2) -> -16216.606 | O6: ='Gainsay economics · Gainsay ope'!O33+('Gainsay drivers · Gainsay fixed'!B20-'Gainsay drivers · Gainsay data-'!B5)*IF(IF(IFERROR(YEAR(DATE(2027,11,1))=2026=TRUE(),FALSE()),TRUE(),IF(IFERROR(MONTH(DATE(2027,11,1))<10=TRUE(),FALSE()),TRUE(),OR(YEAR(DATE(2027,11,1))=2026,MONTH(DATE(2027,11,1))<10))),1,2) -> -15539.376 | P6: ='Gainsay economics · Gainsay ope'!P33+('Gainsay drivers · Gainsay fixed'!B20-'Gainsay drivers · Gainsay data-'!B5)*IF(IF(IFERROR(YEAR(DATE(2027,12,1))=2026=TRUE(),FALSE()),TRUE(),IF(IFERROR(MONTH(DATE(2027,12,1))<10=TRUE(),FALSE()),TRUE(),OR(YEAR(DATE(2027,12,1))=2026,MONTH(DATE(2027,12,1))<10))),1,2) -> -15139.258
A7: Illustrative fee | B7: ='Gainsay economics · Gainsay ope'!B33+('Gainsay drivers · Gainsay fixed'!B20-'Gainsay drivers · Gainsay data-'!B6)*IF(IF(IFERROR(YEAR(DATE(2026,10,1))=2026=TRUE(),FALSE()),TRUE(),IF(IFERROR(MONTH(DATE(2026,10,1))<10=TRUE(),FALSE()),TRUE(),OR(YEAR(DATE(2026,10,1))=2026,MONTH(DATE(2026,10,1))<10))),1,2) -> 892.807 | C7: ='Gainsay economics · Gainsay ope'!C33+('Gainsay drivers · Gainsay fixed'!B20-'Gainsay drivers · Gainsay data-'!B6)*IF(IF(IFERROR(YEAR(DATE(2026,11,1))=2026=TRUE(),FALSE()),TRUE(),IF(IFERROR(MONTH(DATE(2026,11,1))<10=TRUE(),FALSE()),TRUE(),OR(YEAR(DATE(2026,11,1))=2026,MONTH(DATE(2026,11,1))<10))),1,2) -> 369.05784 | D7: ='Gainsay economics · Gainsay ope'!D33+('Gainsay drivers · Gainsay fixed'!B20-'Gainsay drivers · Gainsay data-'!B6)*IF(IF(IFERROR(YEAR(DATE(2026,12,1))=2026=TRUE(),FALSE()),TRUE(),IF(IFERROR(MONTH(DATE(2026,12,1))<10=TRUE(),FALSE()),TRUE(),OR(YEAR(DATE(2026,12,1))=2026,MONTH(DATE(2026,12,1))<10))),1,2) -> -69.348493 | E7: ='Gainsay economics · Gainsay ope'!E33+('Gainsay drivers · Gainsay fixed'!B20-'Gainsay drivers · Gainsay data-'!B6)*IF(IF(IFERROR(YEAR(DATE(2027,1,1))=2026=TRUE(),FALSE()),TRUE(),IF(IFERROR(MONTH(DATE(2027,1,1))<10=TRUE(),FALSE()),TRUE(),OR(YEAR(DATE(2027,1,1))=2026,MONTH(DATE(2027,1,1))<10))),1,2) -> -420.34987 | F7: ='Gainsay economics · Gainsay ope'!F33+('Gainsay drivers · Gainsay fixed'!B20-'Gainsay drivers · Gainsay data-'!B6)*IF(IF(IFERROR(YEAR(DATE(2027,2,1))=2026=TRUE(),FALSE()),TRUE(),IF(IFERROR(MONTH(DATE(2027,2,1))<10=TRUE(),FALSE()),TRUE(),OR(YEAR(DATE(2027,2,1))=2026,MONTH(DATE(2027,2,1))<10))),1,2) -> -681.71489 | G7: ='Gainsay economics · Gainsay ope'!G33+('Gainsay drivers · Gainsay fixed'!B20-'Gainsay drivers · Gainsay data-'!B6)*IF(IF(IFERROR(YEAR(DATE(2027,3,1))=2026=TRUE(),FALSE()),TRUE(),IF(IFERROR(MONTH(DATE(2027,3,1))<10=TRUE(),FALSE()),TRUE(),OR(YEAR(DATE(2027,3,1))=2026,MONTH(DATE(2027,3,1))<10))),1,2) -> -851.03644 | H7: ='Gainsay economics · Gainsay ope'!H33+('Gainsay drivers · Gainsay fixed'!B20-'Gainsay drivers · Gainsay data-'!B6)*IF(IF(IFERROR(YEAR(DATE(2027,4,1))=2026=TRUE(),FALSE()),TRUE(),IF(IFERROR(MONTH(DATE(2027,4,1))<10=TRUE(),FALSE()),TRUE(),OR(YEAR(DATE(2027,4,1))=2026,MONTH(DATE(2027,4,1))<10))),1,2) -> -925.72479 | I7: ='Gainsay economics · Gainsay ope'!I33+('Gainsay drivers · Gainsay fixed'!B20-'Gainsay drivers · Gainsay data-'!B6)*IF(IF(IFERROR(YEAR(DATE(2027,5,1))=2026=TRUE(),FALSE()),TRUE(),IF(IFERROR(MONTH(DATE(2027,5,1))<10=TRUE(),FALSE()),TRUE(),OR(YEAR(DATE(2027,5,1))=2026,MONTH(DATE(2027,5,1))<10))),1,2) -> -903.00036 | J7: ='Gainsay economics · Gainsay ope'!J33+('Gainsay drivers · Gainsay fixed'!B20-'Gainsay drivers · Gainsay data-'!B6)*IF(IF(IFERROR(YEAR(DATE(2027,6,1))=2026=TRUE(),FALSE()),TRUE(),IF(IFERROR(MONTH(DATE(2027,6,1))<10=TRUE(),FALSE()),TRUE(),OR(YEAR(DATE(2027,6,1))=2026,MONTH(DATE(2027,6,1))<10))),1,2) -> -779.88603 | K7: ='Gainsay economics · Gainsay ope'!K33+('Gainsay drivers · Gainsay fixed'!B20-'Gainsay drivers · Gainsay data-'!B6)*IF(IF(IFERROR(YEAR(DATE(2027,7,1))=2026=TRUE(),FALSE()),TRUE(),IF(IFERROR(MONTH(DATE(2027,7,1))<10=TRUE(),FALSE()),TRUE(),OR(YEAR(DATE(2027,7,1))=2026,MONTH(DATE(2027,7,1))<10))),1,2) -> -553.19902 | L7: ='Gainsay economics · Gainsay ope'!L33+('Gainsay drivers · Gainsay fixed'!B20-'Gainsay drivers · Gainsay data-'!B6)*IF(IF(IFERROR(YEAR(DATE(2027,8,1))=2026=TRUE(),FALSE()),TRUE(),IF(IFERROR(MONTH(DATE(2027,8,1))<10=TRUE(),FALSE()),TRUE(),OR(YEAR(DATE(2027,8,1))=2026,MONTH(DATE(2027,8,1))<10))),1,2) -> -219.54229 | M7: ='Gainsay economics · Gainsay ope'!M33+('Gainsay drivers · Gainsay fixed'!B20-'Gainsay drivers · Gainsay data-'!B6)*IF(IF(IFERROR(YEAR(DATE(2027,9,1))=2026=TRUE(),FALSE()),TRUE(),IF(IFERROR(MONTH(DATE(2027,9,1))<10=TRUE(),FALSE()),TRUE(),OR(YEAR(DATE(2027,9,1))=2026,MONTH(DATE(2027,9,1))<10))),1,2) -> 224.70447 | N7: ='Gainsay economics · Gainsay ope'!N33+('Gainsay drivers · Gainsay fixed'!B20-'Gainsay drivers · Gainsay data-'!B6)*IF(IF(IFERROR(YEAR(DATE(2027,10,1))=2026=TRUE(),FALSE()),TRUE(),IF(IFERROR(MONTH(DATE(2027,10,1))<10=TRUE(),FALSE()),TRUE(),OR(YEAR(DATE(2027,10,1))=2026,MONTH(DATE(2027,10,1))<10))),1,2) -> -2216.6055 | O7: ='Gainsay economics · Gainsay ope'!O33+('Gainsay drivers · Gainsay fixed'!B20-'Gainsay drivers · Gainsay data-'!B6)*IF(IF(IFERROR(YEAR(DATE(2027,11,1))=2026=TRUE(),FALSE()),TRUE(),IF(IFERROR(MONTH(DATE(2027,11,1))<10=TRUE(),FALSE()),TRUE(),OR(YEAR(DATE(2027,11,1))=2026,MONTH(DATE(2027,11,1))<10))),1,2) -> -1539.3762 | P7: ='Gainsay economics · Gainsay ope'!P33+('Gainsay drivers · Gainsay fixed'!B20-'Gainsay drivers · Gainsay data-'!B6)*IF(IF(IFERROR(YEAR(DATE(2027,12,1))=2026=TRUE(),FALSE()),TRUE(),IF(IFERROR(MONTH(DATE(2027,12,1))<10=TRUE(),FALSE()),TRUE(),OR(YEAR(DATE(2027,12,1))=2026,MONTH(DATE(2027,12,1))<10))),1,2) -> -1139.2578
