Workbook

Sheet Gainsay fixed assumptions
A1: Gainsay fixed assumptions
A2: Gainsay drivers · Main Scenario
A4: Variable / dimension | B4: Value
A5: Claude cost per citation | B5: =0.026 -> 0.026
A6: Docket monthly price | B6: =29 -> 29
A7: Brief price | B7: =9 -> 9
A8: New filings per docket | B8: =2 -> 2
A9: Citations per paid filing | B9: =35 -> 35
A10: Citations per free check | B10: =30 -> 30
A11: Global free checks per month | B11: =20 -> 20
A12: API calls per citation | B12: =2 -> 2
A13: Daily default API quota | B13: =125 -> 125
A14: Poll calls per docket per day | B14: =1 -> 1
A15: Hosting per month | B15: =15 -> 15
A16: Tools per month | B16: =30 -> 30
A17: Legal and insurance reserve per month | B17: =100 -> 100
A18: Marketing per month | B18: =100 -> 100
A19: Founder draw per month | B19: =500 -> 500
A20: Annual data fee placeholder | B20: =3000 -> 3000
A21: Opening cash placeholder | B21: =5000 -> 5000
A22: Launch cost | B22: =500 -> 500
A23: Payment percentage | B23: =0.029 -> 0.029
A24: Payment fee per transaction | B24: =0.3 -> 0.3
A25: Human review minutes per filing | B25: =3 -> 3
A26: Founder review hours per month | B26: =60 -> 60
A27: Contractor docket trigger | B27: =50 -> 50
A28: Contractor per month | B28: =400 -> 400

Sheet Gainsay demand assumptions
A1: Gainsay demand assumptions
A2: Gainsay drivers · Main Scenario
A4: Variable / dimension | B4: 2026-10 | C4: 2026-11 | D4: 2026-12 | E4: 2027-01 | F4: 2027-02 | G4: 2027-03 | H4: 2027-04 | I4: 2027-05 | J4: 2027-06 | K4: 2027-07 | L4: 2027-08 | M4: 2027-09 | N4: 2027-10 | O4: 2027-11 | P4: 2027-12
A5: New dockets per month | B5: =3 -> 3 | C5: ='Gainsay demand assumptions'!B5*(1+'Gainsay demand assumptions'!C6) -> 3.15 | D5: ='Gainsay demand assumptions'!C5*(1+'Gainsay demand assumptions'!D6) -> 3.3075 | E5: ='Gainsay demand assumptions'!D5*(1+'Gainsay demand assumptions'!E6) -> 3.472875 | F5: ='Gainsay demand assumptions'!E5*(1+'Gainsay demand assumptions'!F6) -> 3.6465188 | G5: ='Gainsay demand assumptions'!F5*(1+'Gainsay demand assumptions'!G6) -> 3.8288447 | H5: ='Gainsay demand assumptions'!G5*(1+'Gainsay demand assumptions'!H6) -> 4.0202869 | I5: ='Gainsay demand assumptions'!H5*(1+'Gainsay demand assumptions'!I6) -> 4.2213013 | J5: ='Gainsay demand assumptions'!I5*(1+'Gainsay demand assumptions'!J6) -> 4.4323663 | ... P5: ='Gainsay demand assumptions'!O5*(1+'Gainsay demand assumptions'!P6) -> 5.9397948
A6: Monthly acquisition growth | B6: =0.05 -> 0.05 | C6: =IF('Gainsay demand assumptions'!B6="","",'Gainsay demand assumptions'!B6) -> 0.05 | D6: =IF('Gainsay demand assumptions'!C6="","",'Gainsay demand assumptions'!C6) -> 0.05 | E6: =IF('Gainsay demand assumptions'!D6="","",'Gainsay demand assumptions'!D6) -> 0.05 | F6: =IF('Gainsay demand assumptions'!E6="","",'Gainsay demand assumptions'!E6) -> 0.05 | G6: =IF('Gainsay demand assumptions'!F6="","",'Gainsay demand assumptions'!F6) -> 0.05 | H6: =IF('Gainsay demand assumptions'!G6="","",'Gainsay demand assumptions'!G6) -> 0.05 | I6: =IF('Gainsay demand assumptions'!H6="","",'Gainsay demand assumptions'!H6) -> 0.05 | J6: =IF('Gainsay demand assumptions'!I6="","",'Gainsay demand assumptions'!I6) -> 0.05 | ... P6: =IF('Gainsay demand assumptions'!O6="","",'Gainsay demand assumptions'!O6) -> 0.05
A7: Monthly docket churn | B7: =0.03 -> 0.03 | C7: =IF('Gainsay demand assumptions'!B7="","",'Gainsay demand assumptions'!B7) -> 0.03 | D7: =IF('Gainsay demand assumptions'!C7="","",'Gainsay demand assumptions'!C7) -> 0.03 | E7: =IF('Gainsay demand assumptions'!D7="","",'Gainsay demand assumptions'!D7) -> 0.03 | F7: =IF('Gainsay demand assumptions'!E7="","",'Gainsay demand assumptions'!E7) -> 0.03 | G7: =IF('Gainsay demand assumptions'!F7="","",'Gainsay demand assumptions'!F7) -> 0.03 | H7: =IF('Gainsay demand assumptions'!G7="","",'Gainsay demand assumptions'!G7) -> 0.03 | I7: =IF('Gainsay demand assumptions'!H7="","",'Gainsay demand assumptions'!H7) -> 0.03 | J7: =IF('Gainsay demand assumptions'!I7="","",'Gainsay demand assumptions'!I7) -> 0.03 | ... P7: =IF('Gainsay demand assumptions'!O7="","",'Gainsay demand assumptions'!O7) -> 0.03
A8: Brief checks sold | B8: =10 -> 10 | C8: ='Gainsay demand assumptions'!B8*(1+'Gainsay demand assumptions'!C9) -> 10.5 | D8: ='Gainsay demand assumptions'!C8*(1+'Gainsay demand assumptions'!D9) -> 11.025 | E8: ='Gainsay demand assumptions'!D8*(1+'Gainsay demand assumptions'!E9) -> 11.57625 | F8: ='Gainsay demand assumptions'!E8*(1+'Gainsay demand assumptions'!F9) -> 12.155063 | G8: ='Gainsay demand assumptions'!F8*(1+'Gainsay demand assumptions'!G9) -> 12.762816 | H8: ='Gainsay demand assumptions'!G8*(1+'Gainsay demand assumptions'!H9) -> 13.400956 | I8: ='Gainsay demand assumptions'!H8*(1+'Gainsay demand assumptions'!I9) -> 14.071004 | J8: ='Gainsay demand assumptions'!I8*(1+'Gainsay demand assumptions'!J9) -> 14.774554 | ... P8: ='Gainsay demand assumptions'!O8*(1+'Gainsay demand assumptions'!P9) -> 19.799316
A9: Monthly brief demand growth | B9: =0.05 -> 0.05 | C9: =IF('Gainsay demand assumptions'!B9="","",'Gainsay demand assumptions'!B9) -> 0.05 | D9: =IF('Gainsay demand assumptions'!C9="","",'Gainsay demand assumptions'!C9) -> 0.05 | E9: =IF('Gainsay demand assumptions'!D9="","",'Gainsay demand assumptions'!D9) -> 0.05 | F9: =IF('Gainsay demand assumptions'!E9="","",'Gainsay demand assumptions'!E9) -> 0.05 | G9: =IF('Gainsay demand assumptions'!F9="","",'Gainsay demand assumptions'!F9) -> 0.05 | H9: =IF('Gainsay demand assumptions'!G9="","",'Gainsay demand assumptions'!G9) -> 0.05 | I9: =IF('Gainsay demand assumptions'!H9="","",'Gainsay demand assumptions'!H9) -> 0.05 | J9: =IF('Gainsay demand assumptions'!I9="","",'Gainsay demand assumptions'!I9) -> 0.05 | ... P9: =IF('Gainsay demand assumptions'!O9="","",'Gainsay demand assumptions'!O9) -> 0.05

Sheet Gainsay pricing economics
A1: Gainsay pricing economics
A2: Gainsay drivers · Main Scenario
A4: Variable / dimension | B4: Value
A5: AI cost per average filing | B5: ='Gainsay fixed assumptions'!B5*'Gainsay fixed assumptions'!B9 -> 0.91
A6: AI cost at 15 citations | B6: ='Gainsay fixed assumptions'!B5*15 -> 0.39
A7: AI cost at 50 citations | B7: ='Gainsay fixed assumptions'!B5*50 -> 1.3
A8: Docket contribution per month | B8: ='Gainsay fixed assumptions'!B6*(1-'Gainsay fixed assumptions'!B23)-'Gainsay fixed assumptions'!B24-'Gainsay fixed assumptions'!B8*'Gainsay pricing economics'!B5 -> 26.039
A9: Brief contribution | B9: ='Gainsay fixed assumptions'!B7*(1-'Gainsay fixed assumptions'!B23)-'Gainsay fixed assumptions'!B24-'Gainsay pricing economics'!B5 -> 7.529
A10: Fixed monthly cash budget | B10: ='Gainsay fixed assumptions'!B15+'Gainsay fixed assumptions'!B16+'Gainsay fixed assumptions'!B17+'Gainsay fixed assumptions'!B18+'Gainsay fixed assumptions'!B20/12+'Gainsay fixed assumptions'!B19+'Gainsay fixed assumptions'!B11*'Gainsay fixed assumptions'!B10*'Gainsay fixed assumptions'!B5 -> 1010.6
A11: Dockets needed for fixed cash budget | B11: =CEILING('Gainsay pricing economics'!B10/'Gainsay pricing economics'!B8,1) -> 39

Sheet Gainsay data-fee tests
A1: Gainsay data-fee tests
A2: Gainsay drivers · Main Scenario
A4: Variable / dimension | B4: Test annual data fee
A5: High fee stress | B5: =10000 -> 10000
A6: Illustrative fee | B6: =3000 -> 3000
A7: No fee sensitivity only | B7: =0 -> 0
